Workbook
Name Nome: 'Config'!$C$6
Name Ano: 'Config'!$C$7
Name Moeda: 'Config'!$C$8
Name MetaPoup: 'Config'!$C$9
Name MetaReserva: 'Config'!$C$10
Name MetaSono: 'Config'!$C$11
Name MetaTreinosSem: 'Config'!$C$12
Name MetaPassos: 'Config'!$C$13
Name PesoAlvo: 'Config'!$C$14
Name MetaEstudoMes: 'Config'!$C$15
Name MetaLivrosAno: 'Config'!$C$16
Name MetaLazerSem: 'Config'!$C$17
Name AlertaDocs: 'Config'!$C$18
Name AlertaAniv: 'Config'!$C$19
Name FollowUpDias: 'Config'!$C$20
Name Hoje: 'Config'!$C$23
Name RefMes: 'Config'!$C$24
Name RefIni: 'Config'!$C$25
Name RefFim: 'Config'!$C$26
Name Corte: 'Config'!$C$27
Name DiasRef: 'Config'!$C$28
Name IniAno: 'Config'!$C$29
Name FimAno: 'Config'!$C$30
Name DiasAno: 'Config'!$C$31
Name IdxHoje: 'Config'!$C$32
Name RotuloMes: 'Config'!$C$33
Name DiasMes: 'Config'!$C$34
Name lst_Areas: 'Config'!$F$6:$F$16
Name Meses: 'Config'!$G$6:$G$17
Name lst_MesSel: 'Config'!$H$6:$H$18
Name lst_CatDesp: OFFSET('Config'!$I$6,0,0,MAX(1,COUNTA('Config'!$I$6:$I$40)),1)
Name lst_GrupoDesp: OFFSET('Config'!$J$6,0,0,MAX(1,COUNTA('Config'!$J$6:$J$40)),1)
Name lst_CatRec: OFFSET('Config'!$K$6,0,0,MAX(1,COUNTA('Config'!$K$6:$K$40)),1)
Name lst_CatAporte: OFFSET('Config'!$L$6,0,0,MAX(1,COUNTA('Config'!$L$6:$L$40)),1)
Name lst_Contas: OFFSET('Config'!$M$6,0,0,MAX(1,COUNTA('Config'!$M$6:$M$40)),1)
Name lst_TipoLanc: OFFSET('Config'!$N$6,0,0,MAX(1,COUNTA('Config'!$N$6:$N$40)),1)
Name lst_FixVar: OFFSET('Config'!$O$6,0,0,MAX(1,COUNTA('Config'!$O$6:$O$40)),1)
Name lst_StatusTarefa: OFFSET('Config'!$P$6,0,0,MAX(1,COUNTA('Config'!$P$6:$P$40)),1)
Name lst_Prioridade: OFFSET('Config'!$Q$6,0,0,MAX(1,COUNTA('Config'!$Q$6:$Q$40)),1)
Name lst_StatusProjeto: OFFSET('Config'!$R$6,0,0,MAX(1,COUNTA('Config'!$R$6:$R$40)),1)
Name lst_StatusMeta: OFFSET('Config'!$S$6,0,0,MAX(1,COUNTA('Config'!$S$6:$S$40)),1)
Name lst_Treino: OFFSET('Config'!$T$6,0,0,MAX(1,COUNTA('Config'!$T$6:$T$40)),1)
Name lst_TipoConsulta: OFFSET('Config'!$U$6,0,0,MAX(1,COUNTA('Config'!$U$6:$U$40)),1)
Name lst_StatusConsulta: OFFSET('Config'!$V$6,0,0,MAX(1,COUNTA('Config'!$V$6:$V$40)),1)
Name lst_Relacao: OFFSET('Config'!$W$6,0,0,MAX(1,COUNTA('Config'!$W$6:$W$40)),1)
Name lst_Circulo: OFFSET('Config'!$X$6,0,0,MAX(1,COUNTA('Config'!$X$6:$X$40)),1)
Name lst_TipoInter: OFFSET('Config'!$Y$6,0,0,MAX(1,COUNTA('Config'!$Y$6:$Y$40)),1)
Name lst_TipoApr: OFFSET('Config'!$Z$6,0,0,MAX(1,COUNTA('Config'!$Z$6:$Z$40)),1)
Name lst_StatusApr: OFFSET('Config'!$AA$6,0,0,MAX(1,COUNTA('Config'!$AA$6:$AA$40)),1)
Name lst_AtivEstudo: OFFSET('Config'!$AB$6,0,0,MAX(1,COUNTA('Config'!$AB$6:$AB$40)),1)
Name lst_CatLazer: OFFSET('Config'!$AC$6,0,0,MAX(1,COUNTA('Config'!$AC$6:$AC$40)),1)
Name lst_StatusSonho: OFFSET('Config'!$AD$6,0,0,MAX(1,COUNTA('Config'!$AD$6:$AD$40)),1)
Name lst_Etapa: OFFSET('Config'!$AE$6,0,0,MAX(1,COUNTA('Config'!$AE$6:$AE$40)),1)
Name lst_TipoMarco: OFFSET('Config'!$AF$6,0,0,MAX(1,COUNTA('Config'!$AF$6:$AF$40)),1)
Name lst_CatComp: OFFSET('Config'!$AG$6,0,0,MAX(1,COUNTA('Config'!$AG$6:$AG$40)),1)
Name lst_CatManut: OFFSET('Config'!$AH$6,0,0,MAX(1,COUNTA('Config'!$AH$6:$AH$40)),1)
Name lst_Periodo: OFFSET('Config'!$AI$6,0,0,MAX(1,COUNTA('Config'!$AI$6:$AI$40)),1)
Name lst_PeriodoMeses: OFFSET('Config'!$AJ$6,0,0,MAX(1,COUNTA('Config'!$AJ$6:$AJ$40)),1)
Name lst_Uso: OFFSET('Config'!$AK$6,0,0,MAX(1,COUNTA('Config'!$AK$6:$AK$40)),1)
Name lst_SimNao: OFFSET('Config'!$AL$6,0,0,MAX(1,COUNTA('Config'!$AL$6:$AL$40)),1)

Sheet Dashboard
B1: =IF(Nome="","PAINEL DA VIDA","PAINEL DA VIDA · "&UPPER(Nome)) -> PAINEL DA VIDA | T1: MÊS DE REFERÊNCIA ▸ | Z1: Mês atual
B2: ="Visão integrada de "&RotuloMes&" · hoje: "&DAY(Hoje)&"/"&MONTH(Hoje)&"/"&YEAR(Hoje)&" · dados até "&DAY(Corte)&"/"&MONTH(Corte) -> Visão integrada de Outubro 2026 · hoje: 2/10/2026 · dados até 2/10 | T2: =IF('Cálculos'!$C$165="","","Tema do ano: "&'Cálculos'!$C$165)
B3: Roda | D3: Metas | F3: Tarefas | H3: Finanças | J3: Orçamento | L3: Saúde | N3: Hábitos | P3: Carreira | R3: Relações | T3: Estudo | V3: Lazer | X3: Casa | Z3: Guia | AB3: Config
B5: ="VISÃO GERAL · "&UPPER(RotuloMes) -> VISÃO GERAL · OUTUBRO 2026
B6: ÍNDICE DE VIDA · DADOS | I6: METAS NO RITMO | P6: TAREFAS ATRASADAS | W6: PRÓXIMOS 7 DIAS
B7: =IF(ISNUMBER('Cálculos'!$H$16),'Cálculos'!$H$16,"–") -> – | I7: =IF('Metas'!$C$11=0,"–",'Metas'!$D$11&" de "&'Metas'!$C$11) -> – | P7: ='Tarefas'!$C$6 -> 0 | W7: ='Tarefas'!$E$6+COUNTIFS('Relações'!$K$10:$K$69,">=0",'Relações'!$K$10:$K$69,"<=7")+COUNTIFS('Casa'!$N$11:$N$101,">=0",'Casa'!$N$11:$N$101,"<8")+COUNTIFS('Saúde'!$W$27:$W$56,">=0",'Saúde'!$W$27:$W$56,"<=7") -> 0
B8: =IF(AND(ISNUMBER('Cálculos'!$H$16),ISNUMBER('Cálculos'!$I$16)),IF(ABS('Cálculos'!$I$16*10-'Cálculos'!$H$16)<=10,"✔ ","▲ "),"")&"Percepção "&IF(ISNUMBER('Cálculos'!$I$16),FIXED('Cálculos'!$I$16,1)&"/10","–")&IF(AND(ISNUMBER('Cálculos'!$H$16),ISNUMBER('Cálculos'!$I$16)),IF(ABS('Cálculos'!$I$16*10-'Cálculos'!$H$16)<=10," · alinhada aos dados",IF('Cálculos'!$I$16*10>'Cálculos'!$H$16," · acima dos dados"," · abaixo dos dados")),"") -> Percepção – | I8: =IF('Metas'!$C$11=0,"○ Cadastre suas metas na aba Metas",IF('Metas'!$I$11>0,"▲ "&'Metas'!$I$11&" atrasada(s) · ","✔ ")&"progresso médio "&IF(ISNUMBER('Metas'!$L$11),ROUND('Metas'!$L$11*100,0)&"%","–")) -> ○ Cadastre suas metas na aba Metas | P8: =IF('Tarefas'!$C$6>0,"✖ ","✔ ")&'Tarefas'!$B$6&" abertas · "&'Tarefas'!$H$6&" concluídas no mês" -> ✔ 0 abertas · 0 concluídas no mês | W8: ='Tarefas'!$E$6&" tarefa(s) · "&COUNTIFS('Relações'!$K$10:$K$69,">=0",'Relações'!$K$10:$K$69,"<=7")&" aniversário(s) · "&COUNTIFS('Casa'!$N$11:$N$101,">=0",'Casa'!$N$11:$N$101,"<8")&" vencimento(s) · "&COUNTIFS('Saúde'!$W$27:$W$56,">=0",'Saúde'!$W$27:$W$56,"<=7")&" consulta(s)" -> 0 tarefa(s) · 0 aniversário(s) · 0 vencimento(s) · 0 consulta(s)
B10: RESULTADO DO MÊS | I10: TAXA DE POUPANÇA | P10: PATRIMÔNIO LÍQUIDO | W10: RESERVA DE EMERGÊNCIA
B11: ='Finanças'!$E$6 -> 0 | I11: ='Finanças'!$H$6 -> – | P11: =IF(ISNUMBER('Orçamento'!$S$84),'Orçamento'!$S$84,"–") -> – | W11: =IF(ISNUMBER('Orçamento'!$S$86),'Orçamento'!$S$86,"–") -> –
B12: =IF('Finanças'!$B$6+'Finanças'!$D$6=0,"○ Sem lançamentos no mês",IF('Finanças'!$E$6>=0,"✔ ","✖ ")&"Receitas € "&FIXED('Finanças'!$B$6,0)&" · despesas € "&FIXED('Finanças'!$D$6,0)) -> ○ Sem lançamentos no mês | I12: ='Finanças'!$H$7 -> ○ Sem receitas no mês | P12: =IF(ISNUMBER('Orçamento'!$S$85),IF('Orçamento'!$S$85>=0,"✔ +€ ","✖ −€ ")&FIXED(ABS('Orçamento'!$S$85),0)&" no mês","○ Atualize os saldos em Orçamento") -> ○ Atualize os saldos em Orçamento | W12: =IF(ISNUMBER('Orçamento'!$S$86),IF('Orçamento'!$S$86>=MetaReserva,"✔ ","▲ ")&"meta "&MetaReserva&" meses de despesas","○ sem dados") -> ○ sem dados
B14: HÁBITOS · % DA META | I14: SONO MÉDIO | P14: TREINOS NO MÊS | W14: HUMOR MÉDIO
B15: =IF(ISNUMBER('Hábitos'!$N$10),'Hábitos'!$N$10,"–") -> – | I15: ='Saúde'!$B$6 -> – | P15: ='Saúde'!$H$6 -> 0 | W15: ='Saúde'!$F$6 -> –
B16: =IF('Cálculos'!$C$158>0,"Maior sequência: "&'Cálculos'!$C$159&" ("&'Cálculos'!$C$158&" dias)","Marque seus hábitos na aba Hábitos") -> Marque seus hábitos na aba Hábitos | I16: ='Saúde'!$B$7 -> ○ Sem registros | P16: ='Saúde'!$H$7 -> ▲ meta 1 · 0 min | W16: ='Saúde'!$F$7 -> Energia – · Estresse –
B18: RELAÇÕES EM DIA | I18: ESTUDO NO MÊS | P18: LAZER NO MÊS | W18: CASA & DOCUMENTOS
B19: ='Relações'!$C$6 -> – | I19: ='Aprendizado'!$B$6 -> 0 | P19: ='Lazer'!$B$6 -> 0 | W19: ='Cálculos'!$C$167 -> 0
B20: =IF('Relações'!$B$6=0,"○ Cadastre pessoas na aba Relações",IF('Relações'!$E$6>0,"▲ ","✔ ")&'Relações'!$E$6&" contato(s) atrasado(s) · "&'Relações'!$G$6&" no mês") -> ○ Cadastre pessoas na aba Relações | I20: ='Aprendizado'!$B$7 -> ▲ meta 24 h/mês | P20: ='Lazer'!$B$7 -> ▲ meta 2 h até agora | W20: =IF('Cálculos'!$C$167>0,"▲ ","✔ ")&('Casa'!$B$6+'Casa'!$C$6)&" doc(s) · "&'Casa'!$E$6&" rotina(s) atrasada(s)" -> ✔ 0 doc(s) · 0 rotina(s) atrasada(s)
B22: ÁREAS DA VIDA · percepção (sua nota) × dados (o que os registros mostram)
B23: Área | G23: Percepção | I23: Dados | K23: Tend. | L23: Indicador-chave do mês
B24: ='Cálculos'!$B$5 -> Saúde física | G24: ='Cálculos'!$I$5 | I24: ='Cálculos'!$H$5 | K24: ='Roda da Vida'!$S$7 | L24: ='Cálculos'!$M$5 -> 0 treinos
B25: ='Cálculos'!$B$6 -> Saúde mental | G25: ='Cálculos'!$I$6 | I25: ='Cálculos'!$H$6 | K25: ='Roda da Vida'!$S$8 | L25: ='Cálculos'!$M$6 -> Sem registros de humor no mês
B26: ='Cálculos'!$B$7 -> Finanças | G26: ='Cálculos'!$I$7 | I26: ='Cálculos'!$H$7 | K26: ='Roda da Vida'!$S$9 | L26: ='Cálculos'!$M$7 -> Sem receitas no mês
B27: ='Cálculos'!$B$8 -> Carreira | G27: ='Cálculos'!$I$8 | I27: ='Cálculos'!$H$8 | K27: ='Roda da Vida'!$S$10 | L27: ='Cálculos'!$M$8 -> 0 candidaturas ativas
B28: ='Cálculos'!$B$9 -> Aprendizado | G28: ='Cálculos'!$I$9 | I28: ='Cálculos'!$H$9 | K28: ='Roda da Vida'!$S$11 | L28: ='Cálculos'!$M$9 -> 0.0 h de estudo no mês · 0 livros no ano
B29: ='Cálculos'!$B$10 -> Família | G29: ='Cálculos'!$I$10 | I29: ='Cálculos'!$H$10 | K29: ='Roda da Vida'!$S$12 | L29: ='Cálculos'!$M$10 -> 0 de 0 em dia · 0 contatos no mês
B30: ='Cálculos'!$B$11 -> Amor & parceria | G30: ='Cálculos'!$I$11 | I30: ='Cálculos'!$H$11 | K30: ='Roda da Vida'!$S$13 | L30: ='Cálculos'!$M$11 -> 0 de 0 em dia · 0 contatos no mês
B31: ='Cálculos'!$B$12 -> Amizades & social | G31: ='Cálculos'!$I$12 | I31: ='Cálculos'!$H$12 | K31: ='Roda da Vida'!$S$14 | L31: ='Cálculos'!$M$12 -> 0 de 0 em dia · 0 contatos no mês
B32: ='Cálculos'!$B$13 -> Lazer & criatividade | G32: ='Cálculos'!$I$13 | I32: ='Cálculos'!$H$13 | K32: ='Roda da Vida'!$S$15 | L32: ='Cálculos'!$M$13 -> 0.0 h de lazer · 0 atividades
B33: ='Cálculos'!$B$14 -> Propósito & espiritualidade | G33: ='Cálculos'!$I$14 | I33: ='Cálculos'!$H$14 | K33: ='Roda da Vida'!$S$16 | L33: ='Cálculos'!$M$14 -> Ligue hábitos e metas a esta área
B34: ='Cálculos'!$B$15 -> Casa & organização | G34: ='Cálculos'!$I$15 | I34: ='Cálculos'!$H$15 | K34: ='Roda da Vida'!$S$17 | L34: ='Cálculos'!$M$15 -> 0 doc(s) p/ renovar · 0 rotina(s) atrasada(s)
B35: Percepção = sua nota na Roda da Vida · Dados = placar calculado (metas, hábitos e métricas da área). Diferença grande entre os dois merece atenção. Detalhe na aba Cálculos.
B37: FOCO & REFLEXÃO
B38: FOCO DO MÊS · da sua revisão mensal | P38: PRIORIDADES DA SEMANA · escreva aqui
B39: =IF('Cálculos'!$C$160="","Ainda sem foco definido. No fim do mês, escreva em Roda da Vida → 'Foco do próximo mês'.",'Cálculos'!$C$160) -> Ainda sem foco definido. No fim do mês, escreva em Roda da Vida → 'Foco do próximo mês'. | P39: 1
P40: 2
P41: 3
B43: VITÓRIAS DO MÊS · e o que aprendi | P43: ÚLTIMO REGISTRO DO DIÁRIO
B44: =IF(AND('Cálculos'!$C$161="",'Cálculos'!$C$162=""),"Preencha a revisão de "&RotuloMes&" na aba Roda da Vida.",'Cálculos'!$C$161&IF('Cálculos'!$C$162="",""," · Aprendi: "&'Cálculos'!$C$162)) -> Preencha a revisão de Outubro 2026 na aba Roda da Vida. | P44: =IF('Cálculos'!$C$157="","Use a coluna Notas da aba Saúde para registrar como foi o dia.",DAY('Cálculos'!$C$156)&"/"&MONTH('Cálculos'!$C$156)&" — "&'Cálculos'!$C$157) -> Use a coluna Notas da aba Saúde para registrar como foi o dia.
B48: MINHA VISÃO · daqui a 5 anos
B49: =IF('Cálculos'!$C$164="","Escreva sua visão no topo da aba Metas — é o norte de todas as outras abas.",'Cálculos'!$C$164) -> Escreva sua visão no topo da aba Metas — é o norte de todas as outras abas.
B52: ATENÇÃO AGORA
B53: Tarefas atrasadas e próximas | P53: Contatos a fazer | W53: Vencimentos & rotinas
B54: Tarefa | I54: Prazo | K54: Situação | N54: Projeto | P54: Pessoa | S54: Sem contato | U54: Status | W54: Item | AA54: Quando
B55: ='Cálculos'!$C$79 | I55: ='Cálculos'!$D$79 | K55: ='Cálculos'!$E$79 | N55: ='Cálculos'!$F$79 | P55: ='Cálculos'!$C$103 | S55: ='Cálculos'!$D$103 | U55: ='Cálculos'!$E$103 | W55: ='Cálculos'!$C$127 | AA55: ='Cálculos'!$D$127
B56: ='Cálculos'!$C$80 | I56: ='Cálculos'!$D$80 | K56: ='Cálculos'!$E$80 | N56: ='Cálculos'!$F$80 | P56: ='Cálculos'!$C$104 | S56: ='Cálculos'!$D$104 | U56: ='Cálculos'!$E$104 | W56: ='Cálculos'!$C$128 | AA56: ='Cálculos'!$D$128
B57: ='Cálculos'!$C$81 | I57: ='Cálculos'!$D$81 | K57: ='Cálculos'!$E$81 | N57: ='Cálculos'!$F$81 | P57: ='Cálculos'!$C$105 | S57: ='Cálculos'!$D$105 | U57: ='Cálculos'!$E$105 | W57: ='Cálculos'!$C$129 | AA57: ='Cálculos'!$D$129
B58: ='Cálculos'!$C$82 | I58: ='Cálculos'!$D$82 | K58: ='Cálculos'!$E$82 | N58: ='Cálculos'!$F$82 | P58: ='Cálculos'!$C$106 | S58: ='Cálculos'!$D$106 | U58: ='Cálculos'!$E$106 | W58: ='Cálculos'!$C$130 | AA58: ='Cálculos'!$D$130
B59: ='Cálculos'!$C$83 | I59: ='Cálculos'!$D$83 | K59: ='Cálculos'!$E$83 | N59: ='Cálculos'!$F$83 | P59: ='Cálculos'!$C$107 | S59: ='Cálculos'!$D$107 | U59: ='Cálculos'!$E$107 | W59: ='Cálculos'!$C$131 | AA59: ='Cálculos'!$D$131
B60: ='Cálculos'!$C$84 | I60: ='Cálculos'!$D$84 | K60: ='Cálculos'!$E$84 | N60: ='Cálculos'!$F$84 | P60: ='Cálculos'!$C$108 | S60: ='Cálculos'!$D$108 | U60: ='Cálculos'!$E$108 | W60: ='Cálculos'!$C$132 | AA60: ='Cálculos'!$D$132
B61: ='Cálculos'!$C$85 | I61: ='Cálculos'!$D$85 | K61: ='Cálculos'!$E$85 | N61: ='Cálculos'!$F$85 | P61: ='Cálculos'!$C$109 | S61: ='Cálculos'!$D$109 | U61: ='Cálculos'!$E$109 | W61: ='Cálculos'!$C$133 | AA61: ='Cálculos'!$D$133
B62: ='Cálculos'!$C$86 | I62: ='Cálculos'!$D$86 | K62: ='Cálculos'!$E$86 | N62: ='Cálculos'!$F$86 | P62: ='Cálculos'!$C$110 | S62: ='Cálculos'!$D$110 | U62: ='Cálculos'!$E$110 | W62: ='Cálculos'!$C$134 | AA62: ='Cálculos'!$D$134
B63: =IF(B55="","Nada por aqui ✔","") -> Nada por aqui ✔ | P63: =IF(P55="","Nada por aqui ✔","") -> Nada por aqui ✔ | W63: =IF(W55="","Nada por aqui ✔","") -> Nada por aqui ✔
B65: Metas em andamento · prazo mais próximo | P65: Próximos aniversários | W65: Aprendendo agora
B66: Meta | H66: Progresso | J66: Esperado | L66: Ritmo | N66: Prazo | P66: Pessoa | S66: Data | U66: Faltam | W66: Título | AB66: Progresso
B67: ='Cálculos'!$C$91 | H67: ='Cálculos'!$E$91 | J67: ='Cálculos'!$F$91 | L67: ='Cálculos'!$G$91 | N67: ='Cálculos'!$H$91 | P67: ='Cálculos'!$C$115 | S67: ='Cálculos'!$D$115 | U67: ='Cálculos'!$E$115 | W67: ='Cálculos'!$C$139 | AB67: ='Cálculos'!$E$139
B68: ='Cálculos'!$C$92 | H68: ='Cálculos'!$E$92 | J68: ='Cálculos'!$F$92 | L68: ='Cálculos'!$G$92 | N68: ='Cálculos'!$H$92 | P68: ='Cálculos'!$C$116 | S68: ='Cálculos'!$D$116 | U68: ='Cálculos'!$E$116 | W68: ='Cálculos'!$C$140 | AB68: ='Cálculos'!$E$140
B69: ='Cálculos'!$C$93 | H69: ='Cálculos'!$E$93 | J69: ='Cálculos'!$F$93 | L69: ='Cálculos'!$G$93 | N69: ='Cálculos'!$H$93 | P69: ='Cálculos'!$C$117 | S69: ='Cálculos'!$D$117 | U69: ='Cálculos'!$E$117 | W69: ='Cálculos'!$C$141 | AB69: ='Cálculos'!$E$141
B70: ='Cálculos'!$C$94 | H70: ='Cálculos'!$E$94 | J70: ='Cálculos'!$F$94 | L70: ='Cálculos'!$G$94 | N70: ='Cálculos'!$H$94 | P70: ='Cálculos'!$C$118 | S70: ='Cálculos'!$D$118 | U70: ='Cálculos'!$E$118 | W70: ='Cálculos'!$C$142 | AB70: ='Cálculos'!$E$142
B71: ='Cálculos'!$C$95 | H71: ='Cálculos'!$E$95 | J71: ='Cálculos'!$F$95 | L71: ='Cálculos'!$G$95 | N71: ='Cálculos'!$H$95 | P71: ='Cálculos'!$C$119 | S71: ='Cálculos'!$D$119 | U71: ='Cálculos'!$E$119 | W71: ='Cálculos'!$C$143 | AB71: ='Cálculos'!$E$143
B72: ='Cálculos'!$C$96 | H72: ='Cálculos'!$E$96 | J72: ='Cálculos'!$F$96 | L72: ='Cálculos'!$G$96 | N72: ='Cálculos'!$H$96 | P72: ='Cálculos'!$C$120 | S72: ='Cálculos'!$D$120 | U72: ='Cálculos'!$E$120 | W72: ='Cálculos'!$C$144 | AB72: ='Cálculos'!$E$144
B73: ='Cálculos'!$C$97 | H73: ='Cálculos'!$E$97 | J73: ='Cálculos'!$F$97 | L73: ='Cálculos'!$G$97 | N73: ='Cálculos'!$H$97 | P73: ='Cálculos'!$C$121 | S73: ='Cálculos'!$D$121 | U73: ='Cálculos'!$E$121 | W73: ='Cálculos'!$C$145 | AB73: ='Cálculos'!$E$145
B74: ='Cálculos'!$C$98 | H74: ='Cálculos'!$E$98 | J74: ='Cálculos'!$F$98 | L74: ='Cálculos'!$G$98 | N74: ='Cálculos'!$H$98 | P74: ='Cálculos'!$C$122 | S74: ='Cálculos'!$D$122 | U74: ='Cálculos'!$E$122 | W74: ='Cálculos'!$C$146 | AB74: ='Cálculos'!$E$146
B75: =IF(B67="","Nada por aqui ✔","") -> Nada por aqui ✔ | P75: =IF(P67="","Nada por aqui ✔","") -> Nada por aqui ✔ | W75: =IF(W67="","Nada por aqui ✔","") -> Nada por aqui ✔
B78: ="FINANÇAS · ANO "&Ano -> FINANÇAS · ANO 2026
B95: DISTRIBUIÇÃO DA RECEITA NO MÊS · referência 50/30/20
B96: ESSENCIAL · ref. ≤ 50% | I96: ESTILO DE VIDA · ref. ≤ 30% | P96: CRESCIMENTO · cursos, livros | W96: POUPANÇA · ref. ≥ 20%
B97: =IF('Orçamento'!$D$90="","–",'Orçamento'!$D$90) -> – | I97: =IF('Orçamento'!$D$91="","–",'Orçamento'!$D$91) -> – | P97: =IF('Orçamento'!$D$92="","–",'Orçamento'!$D$92) -> – | W97: =IF('Orçamento'!$D$93="","–",'Orçamento'!$D$93) -> –
B98: ='Orçamento'!$G$90 | I98: ='Orçamento'!$G$91 | P98: ='Orçamento'!$G$92 | W98: ='Orçamento'!$G$93
B116: SAÚDE & HÁBITOS
B117: HUMOR NOS ÚLTIMOS 28 DIAS · vermelho = dia ruim · cinza = neutro · azul = dia bom · vazio = sem registro
B118: =DAY('Cálculos'!$B$172) -> 5 | C118: =DAY('Cálculos'!$B$173) -> 6 | D118: =DAY('Cálculos'!$B$174) -> 7 | E118: =DAY('Cálculos'!$B$175) -> 8 | F118: =DAY('Cálculos'!$B$176) -> 9 | G118: =DAY('Cálculos'!$B$177) -> 10 | H118: =DAY('Cálculos'!$B$178) -> 11 | I118: =DAY('Cálculos'!$B$179) -> 12 | J118: =DAY('Cálculos'!$B$180) -> 13 | K118: =DAY('Cálculos'!$B$181) -> 14 | L118: =DAY('Cálculos'!$B$182) -> 15 | M118: =DAY('Cálculos'!$B$183) -> 16 | N118: =DAY('Cálculos'!$B$184) -> 17 | O118: =DAY('Cálculos'!$B$185) -> 18 | P118: =DAY('Cálculos'!$B$186) -> 19 | Q118: =DAY('Cálculos'!$B$187) -> 20 | R118: =DAY('Cálculos'!$B$188) -> 21 | S118: =DAY('Cálculos'!$B$189) -> 22 | T118: =DAY('Cálculos'!$B$190) -> 23 | U118: =DAY('Cálculos'!$B$191) -> 24 | V118: =DAY('Cálculos'!$B$192) -> 25 | W118: =DAY('Cálculos'!$B$193) -> 26 | X118: =DAY('Cálculos'!$B$194) -> 27 | Y118: =DAY('Cálculos'!$B$195) -> 28 | Z118: =DAY('Cálculos'!$B$196) -> 29 | AA118: =DAY('Cálculos'!$B$197) -> 30 | AB118: =DAY('Cálculos'!$B$198) -> 1 | AC118: =DAY('Cálculos'!$B$199) -> 2
B119: ='Cálculos'!$C$172 | C119: ='Cálculos'!$C$173 | D119: ='Cálculos'!$C$174 | E119: ='Cálculos'!$C$175 | F119: ='Cálculos'!$C$176 | G119: ='Cálculos'!$C$177 | H119: ='Cálculos'!$C$178 | I119: ='Cálculos'!$C$179 | J119: ='Cálculos'!$C$180 | K119: ='Cálculos'!$C$181 | L119: ='Cálculos'!$C$182 | M119: ='Cálculos'!$C$183 | N119: ='Cálculos'!$C$184 | O119: ='Cálculos'!$C$185 | P119: ='Cálculos'!$C$186 | Q119: ='Cálculos'!$C$187 | R119: ='Cálculos'!$C$188 | S119: ='Cálculos'!$C$189 | T119: ='Cálculos'!$C$190 | U119: ='Cálculos'!$C$191 | V119: ='Cálculos'!$C$192 | W119: ='Cálculos'!$C$193 | X119: ='Cálculos'!$C$194 | Y119: ='Cálculos'!$C$195 | Z119: ='Cálculos'!$C$196 | AA119: ='Cálculos'!$C$197 | AB119: ='Cálculos'!$C$198 | AC119: ='Cálculos'!$C$199
B120: HÁBITOS CUMPRIDOS POR DIA · quanto mais escuro, mais hábitos feitos naquele dia
B121: =DAY('Cálculos'!$B$172) -> 5 | C121: =DAY('Cálculos'!$B$173) -> 6 | D121: =DAY('Cálculos'!$B$174) -> 7 | E121: =DAY('Cálculos'!$B$175) -> 8 | F121: =DAY('Cálculos'!$B$176) -> 9 | G121: =DAY('Cálculos'!$B$177) -> 10 | H121: =DAY('Cálculos'!$B$178) -> 11 | I121: =DAY('Cálculos'!$B$179) -> 12 | J121: =DAY('Cálculos'!$B$180) -> 13 | K121: =DAY('Cálculos'!$B$181) -> 14 | L121: =DAY('Cálculos'!$B$182) -> 15 | M121: =DAY('Cálculos'!$B$183) -> 16 | N121: =DAY('Cálculos'!$B$184) -> 17 | O121: =DAY('Cálculos'!$B$185) -> 18 | P121: =DAY('Cálculos'!$B$186) -> 19 | Q121: =DAY('Cálculos'!$B$187) -> 20 | R121: =DAY('Cálculos'!$B$188) -> 21 | S121: =DAY('Cálculos'!$B$189) -> 22 | T121: =DAY('Cálculos'!$B$190) -> 23 | U121: =DAY('Cálculos'!$B$191) -> 24 | V121: =DAY('Cálculos'!$B$192) -> 25 | W121: =DAY('Cálculos'!$B$193) -> 26 | X121: =DAY('Cálculos'!$B$194) -> 27 | Y121: =DAY('Cálculos'!$B$195) -> 28 | Z121: =DAY('Cálculos'!$B$196) -> 29 | AA121: =DAY('Cálculos'!$B$197) -> 30 | AB121: =DAY('Cálculos'!$B$198) -> 1 | AC121: =DAY('Cálculos'!$B$199) -> 2
B122: ='Cálculos'!$D$172 | C122: ='Cálculos'!$D$173 | D122: ='Cálculos'!$D$174 | E122: ='Cálculos'!$D$175 | F122: ='Cálculos'!$D$176 | G122: ='Cálculos'!$D$177 | H122: ='Cálculos'!$D$178 | I122: ='Cálculos'!$D$179 | J122: ='Cálculos'!$D$180 | K122: ='Cálculos'!$D$181 | L122: ='Cálculos'!$D$182 | M122: ='Cálculos'!$D$183 | N122: ='Cálculos'!$D$184 | O122: ='Cálculos'!$D$185 | P122: ='Cálculos'!$D$186 | Q122: ='Cálculos'!$D$187 | R122: ='Cálculos'!$D$188 | S122: ='Cálculos'!$D$189 | T122: ='Cálculos'!$D$190 | U122: ='Cálculos'!$D$191 | V122: ='Cálculos'!$D$192 | W122: ='Cálculos'!$D$193 | X122: ='Cálculos'!$D$194 | Y122: ='Cálculos'!$D$195 | Z122: ='Cálculos'!$D$196 | AA122: ='Cálculos'!$D$197 | AB122: ='Cálculos'!$D$198 | AC122: ='Cálculos'!$D$199
B156: METAS, ESTUDO & LAZER

Sheet Roda da Vida
B1: Roda da Vida & revisão mensal | V1: ◀ Dashboard
B2: Uma vez por mês: dê uma nota de 0 a 10 para cada área e escreva a revisão. O Dashboard compara sua percepção com os dados.
B3: Legenda: branco = você preenche · cinza = automático (não editar) · ✔ ok ▲ atenção ✖ crítico ○ sem dados
B5: NOTAS MENSAIS · de 0 a 10, como você está em cada área
B6: Área da vida | C6: Jan | D6: Fev | E6: Mar | F6: Abr | G6: Mai | H6: Jun | I6: Jul | J6: Ago | K6: Set | L6: Out | M6: Nov | N6: Dez | O6: Alvo | P6: Atual | Q6: Anterior | R6: Δ | S6: Tend. | T6: Falta p/ alvo | U6: Dados | V6: Percepção − dados
B7: ='Config'!$F$6 -> Saúde física | P7: =IF(W7=0,"",INDEX($C7:$N7,W7)) | Q7: =IF(X7=0,"",INDEX($C7:$N7,X7)) | R7: =IF(OR(P7="",Q7=""),"",P7-Q7) | S7: =IF(R7="","",IF(R7>0,"↑",IF(R7<0,"↓","→"))) | T7: =IF(OR(O7="",P7=""),"",MAX(0,O7-P7)) | U7: ='Cálculos'!$H$5 | V7: =IF(OR(P7="",U7=""),"",P7-U7) | W7: =SUMPRODUCT(MAX(($C7:$N7<>"")*((COLUMN($C7:$N7)-COLUMN($C7)+1)<=RefMes)*(COLUMN($C7:$N7)-COLUMN($C7)+1))) -> 0 | X7: =SUMPRODUCT(MAX(($C7:$N7<>"")*((COLUMN($C7:$N7)-COLUMN($C7)+1)<W7)*(COLUMN($C7:$N7)-COLUMN($C7)+1))) -> 0
B8: ='Config'!$F$7 -> Saúde mental | P8: =IF(W8=0,"",INDEX($C8:$N8,W8)) | Q8: =IF(X8=0,"",INDEX($C8:$N8,X8)) | R8: =IF(OR(P8="",Q8=""),"",P8-Q8) | S8: =IF(R8="","",IF(R8>0,"↑",IF(R8<0,"↓","→"))) | T8: =IF(OR(O8="",P8=""),"",MAX(0,O8-P8)) | U8: ='Cálculos'!$H$6 | V8: =IF(OR(P8="",U8=""),"",P8-U8) | W8: =SUMPRODUCT(MAX(($C8:$N8<>"")*((COLUMN($C8:$N8)-COLUMN($C8)+1)<=RefMes)*(COLUMN($C8:$N8)-COLUMN($C8)+1))) -> 0 | X8: =SUMPRODUCT(MAX(($C8:$N8<>"")*((COLUMN($C8:$N8)-COLUMN($C8)+1)<W8)*(COLUMN($C8:$N8)-COLUMN($C8)+1))) -> 0
B9: ='Config'!$F$8 -> Finanças | P9: =IF(W9=0,"",INDEX($C9:$N9,W9)) | Q9: =IF(X9=0,"",INDEX($C9:$N9,X9)) | R9: =IF(OR(P9="",Q9=""),"",P9-Q9) | S9: =IF(R9="","",IF(R9>0,"↑",IF(R9<0,"↓","→"))) | T9: =IF(OR(O9="",P9=""),"",MAX(0,O9-P9)) | U9: ='Cálculos'!$H$7 | V9: =IF(OR(P9="",U9=""),"",P9-U9) | W9: =SUMPRODUCT(MAX(($C9:$N9<>"")*((COLUMN($C9:$N9)-COLUMN($C9)+1)<=RefMes)*(COLUMN($C9:$N9)-COLUMN($C9)+1))) -> 0 | X9: =SUMPRODUCT(MAX(($C9:$N9<>"")*((COLUMN($C9:$N9)-COLUMN($C9)+1)<W9)*(COLUMN($C9:$N9)-COLUMN($C9)+1))) -> 0
B10: ='Config'!$F$9 -> Carreira | P10: =IF(W10=0,"",INDEX($C10:$N10,W10)) | Q10: =IF(X10=0,"",INDEX($C10:$N10,X10)) | R10: =IF(OR(P10="",Q10=""),"",P10-Q10) | S10: =IF(R10="","",IF(R10>0,"↑",IF(R10<0,"↓","→"))) | T10: =IF(OR(O10="",P10=""),"",MAX(0,O10-P10)) | U10: ='Cálculos'!$H$8 | V10: =IF(OR(P10="",U10=""),"",P10-U10) | W10: =SUMPRODUCT(MAX(($C10:$N10<>"")*((COLUMN($C10:$N10)-COLUMN($C10)+1)<=RefMes)*(COLUMN($C10:$N10)-COLUMN($C10)+1))) -> 0 | X10: =SUMPRODUCT(MAX(($C10:$N10<>"")*((COLUMN($C10:$N10)-COLUMN($C10)+1)<W10)*(COLUMN($C10:$N10)-COLUMN($C10)+1))) -> 0
B11: ='Config'!$F$10 -> Aprendizado | P11: =IF(W11=0,"",INDEX($C11:$N11,W11)) | Q11: =IF(X11=0,"",INDEX($C11:$N11,X11)) | R11: =IF(OR(P11="",Q11=""),"",P11-Q11) | S11: =IF(R11="","",IF(R11>0,"↑",IF(R11<0,"↓","→"))) | T11: =IF(OR(O11="",P11=""),"",MAX(0,O11-P11)) | U11: ='Cálculos'!$H$9 | V11: =IF(OR(P11="",U11=""),"",P11-U11) | W11: =SUMPRODUCT(MAX(($C11:$N11<>"")*((COLUMN($C11:$N11)-COLUMN($C11)+1)<=RefMes)*(COLUMN($C11:$N11)-COLUMN($C11)+1))) -> 0 | X11: =SUMPRODUCT(MAX(($C11:$N11<>"")*((COLUMN($C11:$N11)-COLUMN($C11)+1)<W11)*(COLUMN($C11:$N11)-COLUMN($C11)+1))) -> 0
B12: ='Config'!$F$11 -> Família | P12: =IF(W12=0,"",INDEX($C12:$N12,W12)) | Q12: =IF(X12=0,"",INDEX($C12:$N12,X12)) | R12: =IF(OR(P12="",Q12=""),"",P12-Q12) | S12: =IF(R12="","",IF(R12>0,"↑",IF(R12<0,"↓","→"))) | T12: =IF(OR(O12="",P12=""),"",MAX(0,O12-P12)) | U12: ='Cálculos'!$H$10 | V12: =IF(OR(P12="",U12=""),"",P12-U12) | W12: =SUMPRODUCT(MAX(($C12:$N12<>"")*((COLUMN($C12:$N12)-COLUMN($C12)+1)<=RefMes)*(COLUMN($C12:$N12)-COLUMN($C12)+1))) -> 0 | X12: =SUMPRODUCT(MAX(($C12:$N12<>"")*((COLUMN($C12:$N12)-COLUMN($C12)+1)<W12)*(COLUMN($C12:$N12)-COLUMN($C12)+1))) -> 0
B13: ='Config'!$F$12 -> Amor & parceria | P13: =IF(W13=0,"",INDEX($C13:$N13,W13)) | Q13: =IF(X13=0,"",INDEX($C13:$N13,X13)) | R13: =IF(OR(P13="",Q13=""),"",P13-Q13) | S13: =IF(R13="","",IF(R13>0,"↑",IF(R13<0,"↓","→"))) | T13: =IF(OR(O13="",P13=""),"",MAX(0,O13-P13)) | U13: ='Cálculos'!$H$11 | V13: =IF(OR(P13="",U13=""),"",P13-U13) | W13: =SUMPRODUCT(MAX(($C13:$N13<>"")*((COLUMN($C13:$N13)-COLUMN($C13)+1)<=RefMes)*(COLUMN($C13:$N13)-COLUMN($C13)+1))) -> 0 | X13: =SUMPRODUCT(MAX(($C13:$N13<>"")*((COLUMN($C13:$N13)-COLUMN($C13)+1)<W13)*(COLUMN($C13:$N13)-COLUMN($C13)+1))) -> 0
B14: ='Config'!$F$13 -> Amizades & social | P14: =IF(W14=0,"",INDEX($C14:$N14,W14)) | Q14: =IF(X14=0,"",INDEX($C14:$N14,X14)) | R14: =IF(OR(P14="",Q14=""),"",P14-Q14) | S14: =IF(R14="","",IF(R14>0,"↑",IF(R14<0,"↓","→"))) | T14: =IF(OR(O14="",P14=""),"",MAX(0,O14-P14)) | U14: ='Cálculos'!$H$12 | V14: =IF(OR(P14="",U14=""),"",P14-U14) | W14: =SUMPRODUCT(MAX(($C14:$N14<>"")*((COLUMN($C14:$N14)-COLUMN($C14)+1)<=RefMes)*(COLUMN($C14:$N14)-COLUMN($C14)+1))) -> 0 | X14: =SUMPRODUCT(MAX(($C14:$N14<>"")*((COLUMN($C14:$N14)-COLUMN($C14)+1)<W14)*(COLUMN($C14:$N14)-COLUMN($C14)+1))) -> 0
B15: ='Config'!$F$14 -> Lazer & criatividade | P15: =IF(W15=0,"",INDEX($C15:$N15,W15)) | Q15: =IF(X15=0,"",INDEX($C15:$N15,X15)) | R15: =IF(OR(P15="",Q15=""),"",P15-Q15) | S15: =IF(R15="","",IF(R15>0,"↑",IF(R15<0,"↓","→"))) | T15: =IF(OR(O15="",P15=""),"",MAX(0,O15-P15)) | U15: ='Cálculos'!$H$13 | V15: =IF(OR(P15="",U15=""),"",P15-U15) | W15: =SUMPRODUCT(MAX(($C15:$N15<>"")*((COLUMN($C15:$N15)-COLUMN($C15)+1)<=RefMes)*(COLUMN($C15:$N15)-COLUMN($C15)+1))) -> 0 | X15: =SUMPRODUCT(MAX(($C15:$N15<>"")*((COLUMN($C15:$N15)-COLUMN($C15)+1)<W15)*(COLUMN($C15:$N15)-COLUMN($C15)+1))) -> 0
B16: ='Config'!$F$15 -> Propósito & espiritualidade | P16: =IF(W16=0,"",INDEX($C16:$N16,W16)) | Q16: =IF(X16=0,"",INDEX($C16:$N16,X16)) | R16: =IF(OR(P16="",Q16=""),"",P16-Q16) | S16: =IF(R16="","",IF(R16>0,"↑",IF(R16<0,"↓","→"))) | T16: =IF(OR(O16="",P16=""),"",MAX(0,O16-P16)) | U16: ='Cálculos'!$H$14 | V16: =IF(OR(P16="",U16=""),"",P16-U16) | W16: =SUMPRODUCT(MAX(($C16:$N16<>"")*((COLUMN($C16:$N16)-COLUMN($C16)+1)<=RefMes)*(COLUMN($C16:$N16)-COLUMN($C16)+1))) -> 0 | X16: =SUMPRODUCT(MAX(($C16:$N16<>"")*((COLUMN($C16:$N16)-COLUMN($C16)+1)<W16)*(COLUMN($C16:$N16)-COLUMN($C16)+1))) -> 0
B17: ='Config'!$F$16 -> Casa & organização | P17: =IF(W17=0,"",INDEX($C17:$N17,W17)) | Q17: =IF(X17=0,"",INDEX($C17:$N17,X17)) | R17: =IF(OR(P17="",Q17=""),"",P17-Q17) | S17: =IF(R17="","",IF(R17>0,"↑",IF(R17<0,"↓","→"))) | T17: =IF(OR(O17="",P17=""),"",MAX(0,O17-P17)) | U17: ='Cálculos'!$H$15 | V17: =IF(OR(P17="",U17=""),"",P17-U17) | W17: =SUMPRODUCT(MAX(($C17:$N17<>"")*((COLUMN($C17:$N17)-COLUMN($C17)+1)<=RefMes)*(COLUMN($C17:$N17)-COLUMN($C17)+1))) -> 0 | X17: =SUMPRODUCT(MAX(($C17:$N17<>"")*((COLUMN($C17:$N17)-COLUMN($C17)+1)<W17)*(COLUMN($C17:$N17)-COLUMN($C17)+1))) -> 0
B18: Média | C18: =IFERROR(AVERAGE(C7:C17),"") | D18: =IFERROR(AVERAGE(D7:D17),"") | E18: =IFERROR(AVERAGE(E7:E17),"") | F18: =IFERROR(AVERAGE(F7:F17),"") | G18: =IFERROR(AVERAGE(G7:G17),"") | H18: =IFERROR(AVERAGE(H7:H17),"") | I18: =IFERROR(AVERAGE(I7:I17),"") | J18: =IFERROR(AVERAGE(J7:J17),"") | ... R18: =IFERROR(AVERAGE(R7:R17),"") | T18: =IFERROR(AVERAGE(T7:T17),"") | U18: =IFERROR(AVERAGE(U7:U17),"") | V18: =IFERROR(AVERAGE(V7:V17),"")
B19: Dados = placar objetivo da área (0–10), vindo de metas, hábitos e métricas das abas. Diferença de 2 pontos ou mais (amarelo) merece uma pergunta: o que estou vendo que os números não mostram — ou o contrário?
B20: REVISÃO MENSAL · 15 minutos no último dia do mês
B21: Mês | C21: Nota do mês | D21: Vitórias & destaques | G21: O que não funcionou | J21: O que aprendi | M21: Foco do próximo mês | P21: Gratidão · notas livres
B22: =INDEX(Meses,1) -> Janeiro
B23: =INDEX(Meses,2) -> Fevereiro
B24: =INDEX(Meses,3) -> Março
B25: =INDEX(Meses,4) -> Abril
B26: =INDEX(Meses,5) -> Maio
B27: =INDEX(Meses,6) -> Junho
B28: =INDEX(Meses,7) -> Julho
B29: =INDEX(Meses,8) -> Agosto
B30: =INDEX(Meses,9) -> Setembro
B31: =INDEX(Meses,10) -> Outubro
B32: =INDEX(Meses,11) -> Novembro
B33: =INDEX(Meses,12) -> Dezembro

Sheet Metas
B1: Metas · curto, médio e longo prazo | T1: ◀ Dashboard
B2: Visão no topo, metas mensuráveis embaixo. Progresso, ritmo esperado e horizonte são calculados.
B3: Legenda: branco = você preenche · cinza = automático (não editar) · ✔ ok ▲ atenção ✖ crítico ○ sem dados
B5: Minha visão (daqui a 5 anos)
B6: Propósito · por que faço o que faço
B7: Valores que não negocio
B8: Tema / palavra do ano
C10: METAS EM ANDAMENTO | D10: NO RITMO | F10: EM ATENÇÃO | I10: ATRASADAS OU VENCIDAS | L10: PROGRESSO MÉDIO (EM ANDAMENTO) | O10: POR HORIZONTE
C11: =COUNTIF($O$15:$O$74,"✔ No ritmo")+COUNTIF($O$15:$O$74,"▲*")+COUNTIF($O$15:$O$74,"✖*")+COUNTIF($O$15:$O$74,"○*") -> 0 | D11: =COUNTIF($O$15:$O$74,"✔ No ritmo") -> 0 | F11: =COUNTIF($O$15:$O$74,"▲*") -> 0 | I11: =COUNTIF($O$15:$O$74,"✖*") -> 0 | L11: =IFERROR(AVERAGEIFS($M$15:$M$74,$U$15:$U$74,1,$O$15:$O$74,"<>✔ Concluída"),"–") -> – | O11: ="Curto "&COUNTIFS($Q$15:$Q$74,"Curto",$U$15:$U$74,1)&" · Médio "&COUNTIFS($Q$15:$Q$74,"Médio",$U$15:$U$74,1)&" · Longo "&COUNTIFS($Q$15:$Q$74,"Longo",$U$15:$U$74,1) -> Curto 0 · Médio 0 · Longo 0
C12: ="Concluídas: "&COUNTIF($O$15:$O$74,"✔ Concluída")&" · pausadas: "&COUNTIF($O$15:$O$74,"‖*") -> Concluídas: 0 · pausadas: 0 | D12: =IF(C11=0,"",IF(D11/C11>=0.7,"✔ ","▲ ")&ROUND(D11/C11*100,0)&"% das em andamento") | F12: ="progresso um pouco atrás do tempo" -> progresso um pouco atrás do tempo | I12: =IF(I11>0,"✖ replaneje ou ajuste o prazo","✔ nenhuma") -> ✔ nenhuma | L12: ="vs. tempo decorrido de cada meta" -> vs. tempo decorrido de cada meta | O12: ="pela duração: curto ≤ 6 meses · médio ≤ 2 anos · longo > 2 anos" -> pela duração: curto ≤ 6 meses · médio ≤ 2 anos · longo > 2 anos
B14: # | C14: Meta (específica e mensurável) | D14: Área da vida | E14: Status | F14: Início | G14: Prazo | H14: Unidade | I14: Valor inicial | J14: Valor atual | K14: Valor alvo | L14: Progresso manual | M14: Progresso | N14: Esperado hoje | O14: Ritmo | P14: Dias restantes | Q14: Horizonte | R14: Tarefas abertas | S14: Próximo passo concreto | T14: Por que importa / notas
B15: =IF(C15="","",ROW()-14) | M15: =IF(C15="","",IF(E15="Concluída",1,IF(AND(ISNUMBER(I15),ISNUMBER(J15),ISNUMBER(K15),K15<>I15),MAX(0,MIN(1,(J15-I15)/(K15-I15))),IF(ISNUMBER(L15),MAX(0,MIN(1,L15)),0)))) | N15: =IF(OR(C15="",F15="",G15=""),"",IF(G15<=F15,1,MAX(0,MIN(1,(Hoje-F15)/(G15-F15))))) | O15: =IF(C15="","",IF(OR(E15="Concluída",M15>=1),"✔ Concluída",IF(E15="Pausada","‖ Pausada",IF(E15="Abandonada","– Abandonada",IF(N15="","○ Sem prazo",IF(G15<Hoje,"✖ Vencida",IF(M15>=N15-0.1,"✔ No ritmo",IF(M15>=N15-0.25,"▲ Atenção","✖ Atrasada")))))))) | P15: =IF(OR(C15="",G15="",O15="✔ Concluída"),"",G15-Hoje) | Q15: =IF(OR(C15="",G15=""),"",IF(G15-IF(F15="",Hoje,F15)<=183,"Curto",IF(G15-IF(F15="",Hoje,F15)<=731,"Médio","Longo"))) | R15: =IF(C15="","",COUNTIFS('Tarefas'!$I$34:$I$333,C15,'Tarefas'!$G$34:$G$333,"<>Concluída",'Tarefas'!$G$34:$G$333,"<>Cancelada")) | U15: =IF(C15="",0,IF(OR(E15="Pausada",E15="Abandonada"),0,1)) -> 0 | V15: =IF(U15=0,0,IF(OR(O15="✔ Concluída",O15="✔ No ritmo",O15="○ Sem prazo"),1,0)) -> 0 | W15: =IF(AND(U15=1,O15<>"✔ Concluída",G15<>""),G15+ROW()/100000,"")
B16: =IF(C16="","",ROW()-14) | M16: =IF(C16="","",IF(E16="Concluída",1,IF(AND(ISNUMBER(I16),ISNUMBER(J16),ISNUMBER(K16),K16<>I16),MAX(0,MIN(1,(J16-I16)/(K16-I16))),IF(ISNUMBER(L16),MAX(0,MIN(1,L16)),0)))) | N16: =IF(OR(C16="",F16="",G16=""),"",IF(G16<=F16,1,MAX(0,MIN(1,(Hoje-F16)/(G16-F16))))) | O16: =IF(C16="","",IF(OR(E16="Concluída",M16>=1),"✔ Concluída",IF(E16="Pausada","‖ Pausada",IF(E16="Abandonada","– Abandonada",IF(N16="","○ Sem prazo",IF(G16<Hoje,"✖ Vencida",IF(M16>=N16-0.1,"✔ No ritmo",IF(M16>=N16-0.25,"▲ Atenção","✖ Atrasada")))))))) | P16: =IF(OR(C16="",G16="",O16="✔ Concluída"),"",G16-Hoje) | Q16: =IF(OR(C16="",G16=""),"",IF(G16-IF(F16="",Hoje,F16)<=183,"Curto",IF(G16-IF(F16="",Hoje,F16)<=731,"Médio","Longo"))) | R16: =IF(C16="","",COUNTIFS('Tarefas'!$I$34:$I$333,C16,'Tarefas'!$G$34:$G$333,"<>Concluída",'Tarefas'!$G$34:$G$333,"<>Cancelada")) | U16: =IF(C16="",0,IF(OR(E16="Pausada",E16="Abandonada"),0,1)) -> 0 | V16: =IF(U16=0,0,IF(OR(O16="✔ Concluída",O16="✔ No ritmo",O16="○ Sem prazo"),1,0)) -> 0 | W16: =IF(AND(U16=1,O16<>"✔ Concluída",G16<>""),G16+ROW()/100000,"")
B17: =IF(C17="","",ROW()-14) | M17: =IF(C17="","",IF(E17="Concluída",1,IF(AND(ISNUMBER(I17),ISNUMBER(J17),ISNUMBER(K17),K17<>I17),MAX(0,MIN(1,(J17-I17)/(K17-I17))),IF(ISNUMBER(L17),MAX(0,MIN(1,L17)),0)))) | N17: =IF(OR(C17="",F17="",G17=""),"",IF(G17<=F17,1,MAX(0,MIN(1,(Hoje-F17)/(G17-F17))))) | O17: =IF(C17="","",IF(OR(E17="Concluída",M17>=1),"✔ Concluída",IF(E17="Pausada","‖ Pausada",IF(E17="Abandonada","– Abandonada",IF(N17="","○ Sem prazo",IF(G17<Hoje,"✖ Vencida",IF(M17>=N17-0.1,"✔ No ritmo",IF(M17>=N17-0.25,"▲ Atenção","✖ Atrasada")))))))) | P17: =IF(OR(C17="",G17="",O17="✔ Concluída"),"",G17-Hoje) | Q17: =IF(OR(C17="",G17=""),"",IF(G17-IF(F17="",Hoje,F17)<=183,"Curto",IF(G17-IF(F17="",Hoje,F17)<=731,"Médio","Longo"))) | R17: =IF(C17="","",COUNTIFS('Tarefas'!$I$34:$I$333,C17,'Tarefas'!$G$34:$G$333,"<>Concluída",'Tarefas'!$G$34:$G$333,"<>Cancelada")) | U17: =IF(C17="",0,IF(OR(E17="Pausada",E17="Abandonada"),0,1)) -> 0 | V17: =IF(U17=0,0,IF(OR(O17="✔ Concluída",O17="✔ No ritmo",O17="○ Sem prazo"),1,0)) -> 0 | W17: =IF(AND(U17=1,O17<>"✔ Concluída",G17<>""),G17+ROW()/100000,"")
B18: =IF(C18="","",ROW()-14) | M18: =IF(C18="","",IF(E18="Concluída",1,IF(AND(ISNUMBER(I18),ISNUMBER(J18),ISNUMBER(K18),K18<>I18),MAX(0,MIN(1,(J18-I18)/(K18-I18))),IF(ISNUMBER(L18),MAX(0,MIN(1,L18)),0)))) | N18: =IF(OR(C18="",F18="",G18=""),"",IF(G18<=F18,1,MAX(0,MIN(1,(Hoje-F18)/(G18-F18))))) | O18: =IF(C18="","",IF(OR(E18="Concluída",M18>=1),"✔ Concluída",IF(E18="Pausada","‖ Pausada",IF(E18="Abandonada","– Abandonada",IF(N18="","○ Sem prazo",IF(G18<Hoje,"✖ Vencida",IF(M18>=N18-0.1,"✔ No ritmo",IF(M18>=N18-0.25,"▲ Atenção","✖ Atrasada")))))))) | P18: =IF(OR(C18="",G18="",O18="✔ Concluída"),"",G18-Hoje) | Q18: =IF(OR(C18="",G18=""),"",IF(G18-IF(F18="",Hoje,F18)<=183,"Curto",IF(G18-IF(F18="",Hoje,F18)<=731,"Médio","Longo"))) | R18: =IF(C18="","",COUNTIFS('Tarefas'!$I$34:$I$333,C18,'Tarefas'!$G$34:$G$333,"<>Concluída",'Tarefas'!$G$34:$G$333,"<>Cancelada")) | U18: =IF(C18="",0,IF(OR(E18="Pausada",E18="Abandonada"),0,1)) -> 0 | V18: =IF(U18=0,0,IF(OR(O18="✔ Concluída",O18="✔ No ritmo",O18="○ Sem prazo"),1,0)) -> 0 | W18: =IF(AND(U18=1,O18<>"✔ Concluída",G18<>""),G18+ROW()/100000,"")
B19: =IF(C19="","",ROW()-14) | M19: =IF(C19="","",IF(E19="Concluída",1,IF(AND(ISNUMBER(I19),ISNUMBER(J19),ISNUMBER(K19),K19<>I19),MAX(0,MIN(1,(J19-I19)/(K19-I19))),IF(ISNUMBER(L19),MAX(0,MIN(1,L19)),0)))) | N19: =IF(OR(C19="",F19="",G19=""),"",IF(G19<=F19,1,MAX(0,MIN(1,(Hoje-F19)/(G19-F19))))) | O19: =IF(C19="","",IF(OR(E19="Concluída",M19>=1),"✔ Concluída",IF(E19="Pausada","‖ Pausada",IF(E19="Abandonada","– Abandonada",IF(N19="","○ Sem prazo",IF(G19<Hoje,"✖ Vencida",IF(M19>=N19-0.1,"✔ No ritmo",IF(M19>=N19-0.25,"▲ Atenção","✖ Atrasada")))))))) | P19: =IF(OR(C19="",G19="",O19="✔ Concluída"),"",G19-Hoje) | Q19: =IF(OR(C19="",G19=""),"",IF(G19-IF(F19="",Hoje,F19)<=183,"Curto",IF(G19-IF(F19="",Hoje,F19)<=731,"Médio","Longo"))) | R19: =IF(C19="","",COUNTIFS('Tarefas'!$I$34:$I$333,C19,'Tarefas'!$G$34:$G$333,"<>Concluída",'Tarefas'!$G$34:$G$333,"<>Cancelada")) | U19: =IF(C19="",0,IF(OR(E19="Pausada",E19="Abandonada"),0,1)) -> 0 | V19: =IF(U19=0,0,IF(OR(O19="✔ Concluída",O19="✔ No ritmo",O19="○ Sem prazo"),1,0)) -> 0 | W19: =IF(AND(U19=1,O19<>"✔ Concluída",G19<>""),G19+ROW()/100000,"")
B20: =IF(C20="","",ROW()-14) | M20: =IF(C20="","",IF(E20="Concluída",1,IF(AND(ISNUMBER(I20),ISNUMBER(J20),ISNUMBER(K20),K20<>I20),MAX(0,MIN(1,(J20-I20)/(K20-I20))),IF(ISNUMBER(L20),MAX(0,MIN(1,L20)),0)))) | N20: =IF(OR(C20="",F20="",G20=""),"",IF(G20<=F20,1,MAX(0,MIN(1,(Hoje-F20)/(G20-F20))))) | O20: =IF(C20="","",IF(OR(E20="Concluída",M20>=1),"✔ Concluída",IF(E20="Pausada","‖ Pausada",IF(E20="Abandonada","– Abandonada",IF(N20="","○ Sem prazo",IF(G20<Hoje,"✖ Vencida",IF(M20>=N20-0.1,"✔ No ritmo",IF(M20>=N20-0.25,"▲ Atenção","✖ Atrasada")))))))) | P20: =IF(OR(C20="",G20="",O20="✔ Concluída"),"",G20-Hoje) | Q20: =IF(OR(C20="",G20=""),"",IF(G20-IF(F20="",Hoje,F20)<=183,"Curto",IF(G20-IF(F20="",Hoje,F20)<=731,"Médio","Longo"))) | R20: =IF(C20="","",COUNTIFS('Tarefas'!$I$34:$I$333,C20,'Tarefas'!$G$34:$G$333,"<>Concluída",'Tarefas'!$G$34:$G$333,"<>Cancelada")) | U20: =IF(C20="",0,IF(OR(E20="Pausada",E20="Abandonada"),0,1)) -> 0 | V20: =IF(U20=0,0,IF(OR(O20="✔ Concluída",O20="✔ No ritmo",O20="○ Sem prazo"),1,0)) -> 0 | W20: =IF(AND(U20=1,O20<>"✔ Concluída",G20<>""),G20+ROW()/100000,"")
B21: =IF(C21="","",ROW()-14) | M21: =IF(C21="","",IF(E21="Concluída",1,IF(AND(ISNUMBER(I21),ISNUMBER(J21),ISNUMBER(K21),K21<>I21),MAX(0,MIN(1,(J21-I21)/(K21-I21))),IF(ISNUMBER(L21),MAX(0,MIN(1,L21)),0)))) | N21: =IF(OR(C21="",F21="",G21=""),"",IF(G21<=F21,1,MAX(0,MIN(1,(Hoje-F21)/(G21-F21))))) | O21: =IF(C21="","",IF(OR(E21="Concluída",M21>=1),"✔ Concluída",IF(E21="Pausada","‖ Pausada",IF(E21="Abandonada","– Abandonada",IF(N21="","○ Sem prazo",IF(G21<Hoje,"✖ Vencida",IF(M21>=N21-0.1,"✔ No ritmo",IF(M21>=N21-0.25,"▲ Atenção","✖ Atrasada")))))))) | P21: =IF(OR(C21="",G21="",O21="✔ Concluída"),"",G21-Hoje) | Q21: =IF(OR(C21="",G21=""),"",IF(G21-IF(F21="",Hoje,F21)<=183,"Curto",IF(G21-IF(F21="",Hoje,F21)<=731,"Médio","Longo"))) | R21: =IF(C21="","",COUNTIFS('Tarefas'!$I$34:$I$333,C21,'Tarefas'!$G$34:$G$333,"<>Concluída",'Tarefas'!$G$34:$G$333,"<>Cancelada")) | U21: =IF(C21="",0,IF(OR(E21="Pausada",E21="Abandonada"),0,1)) -> 0 | V21: =IF(U21=0,0,IF(OR(O21="✔ Concluída",O21="✔ No ritmo",O21="○ Sem prazo"),1,0)) -> 0 | W21: =IF(AND(U21=1,O21<>"✔ Concluída",G21<>""),G21+ROW()/100000,"")
B22: =IF(C22="","",ROW()-14) | M22: =IF(C22="","",IF(E22="Concluída",1,IF(AND(ISNUMBER(I22),ISNUMBER(J22),ISNUMBER(K22),K22<>I22),MAX(0,MIN(1,(J22-I22)/(K22-I22))),IF(ISNUMBER(L22),MAX(0,MIN(1,L22)),0)))) | N22: =IF(OR(C22="",F22="",G22=""),"",IF(G22<=F22,1,MAX(0,MIN(1,(Hoje-F22)/(G22-F22))))) | O22: =IF(C22="","",IF(OR(E22="Concluída",M22>=1),"✔ Concluída",IF(E22="Pausada","‖ Pausada",IF(E22="Abandonada","– Abandonada",IF(N22="","○ Sem prazo",IF(G22<Hoje,"✖ Vencida",IF(M22>=N22-0.1,"✔ No ritmo",IF(M22>=N22-0.25,"▲ Atenção","✖ Atrasada")))))))) | P22: =IF(OR(C22="",G22="",O22="✔ Concluída"),"",G22-Hoje) | Q22: =IF(OR(C22="",G22=""),"",IF(G22-IF(F22="",Hoje,F22)<=183,"Curto",IF(G22-IF(F22="",Hoje,F22)<=731,"Médio","Longo"))) | R22: =IF(C22="","",COUNTIFS('Tarefas'!$I$34:$I$333,C22,'Tarefas'!$G$34:$G$333,"<>Concluída",'Tarefas'!$G$34:$G$333,"<>Cancelada")) | U22: =IF(C22="",0,IF(OR(E22="Pausada",E22="Abandonada"),0,1)) -> 0 | V22: =IF(U22=0,0,IF(OR(O22="✔ Concluída",O22="✔ No ritmo",O22="○ Sem prazo"),1,0)) -> 0 | W22: =IF(AND(U22=1,O22<>"✔ Concluída",G22<>""),G22+ROW()/100000,"")
B23: =IF(C23="","",ROW()-14) | M23: =IF(C23="","",IF(E23="Concluída",1,IF(AND(ISNUMBER(I23),ISNUMBER(J23),ISNUMBER(K23),K23<>I23),MAX(0,MIN(1,(J23-I23)/(K23-I23))),IF(ISNUMBER(L23),MAX(0,MIN(1,L23)),0)))) | N23: =IF(OR(C23="",F23="",G23=""),"",IF(G23<=F23,1,MAX(0,MIN(1,(Hoje-F23)/(G23-F23))))) | O23: =IF(C23="","",IF(OR(E23="Concluída",M23>=1),"✔ Concluída",IF(E23="Pausada","‖ Pausada",IF(E23="Abandonada","– Abandonada",IF(N23="","○ Sem prazo",IF(G23<Hoje,"✖ Vencida",IF(M23>=N23-0.1,"✔ No ritmo",IF(M23>=N23-0.25,"▲ Atenção","✖ Atrasada")))))))) | P23: =IF(OR(C23="",G23="",O23="✔ Concluída"),"",G23-Hoje) | Q23: =IF(OR(C23="",G23=""),"",IF(G23-IF(F23="",Hoje,F23)<=183,"Curto",IF(G23-IF(F23="",Hoje,F23)<=731,"Médio","Longo"))) | R23: =IF(C23="","",COUNTIFS('Tarefas'!$I$34:$I$333,C23,'Tarefas'!$G$34:$G$333,"<>Concluída",'Tarefas'!$G$34:$G$333,"<>Cancelada")) | U23: =IF(C23="",0,IF(OR(E23="Pausada",E23="Abandonada"),0,1)) -> 0 | V23: =IF(U23=0,0,IF(OR(O23="✔ Concluída",O23="✔ No ritmo",O23="○ Sem prazo"),1,0)) -> 0 | W23: =IF(AND(U23=1,O23<>"✔ Concluída",G23<>""),G23+ROW()/100000,"")
B24: =IF(C24="","",ROW()-14) | M24: =IF(C24="","",IF(E24="Concluída",1,IF(AND(ISNUMBER(I24),ISNUMBER(J24),ISNUMBER(K24),K24<>I24),MAX(0,MIN(1,(J24-I24)/(K24-I24))),IF(ISNUMBER(L24),MAX(0,MIN(1,L24)),0)))) | N24: =IF(OR(C24="",F24="",G24=""),"",IF(G24<=F24,1,MAX(0,MIN(1,(Hoje-F24)/(G24-F24))))) | O24: =IF(C24="","",IF(OR(E24="Concluída",M24>=1),"✔ Concluída",IF(E24="Pausada","‖ Pausada",IF(E24="Abandonada","– Abandonada",IF(N24="","○ Sem prazo",IF(G24<Hoje,"✖ Vencida",IF(M24>=N24-0.1,"✔ No ritmo",IF(M24>=N24-0.25,"▲ Atenção","✖ Atrasada")))))))) | P24: =IF(OR(C24="",G24="",O24="✔ Concluída"),"",G24-Hoje) | Q24: =IF(OR(C24="",G24=""),"",IF(G24-IF(F24="",Hoje,F24)<=183,"Curto",IF(G24-IF(F24="",Hoje,F24)<=731,"Médio","Longo"))) | R24: =IF(C24="","",COUNTIFS('Tarefas'!$I$34:$I$333,C24,'Tarefas'!$G$34:$G$333,"<>Concluída",'Tarefas'!$G$34:$G$333,"<>Cancelada")) | U24: =IF(C24="",0,IF(OR(E24="Pausada",E24="Abandonada"),0,1)) -> 0 | V24: =IF(U24=0,0,IF(OR(O24="✔ Concluída",O24="✔ No ritmo",O24="○ Sem prazo"),1,0)) -> 0 | W24: =IF(AND(U24=1,O24<>"✔ Concluída",G24<>""),G24+ROW()/100000,"")
B25: =IF(C25="","",ROW()-14) | M25: =IF(C25="","",IF(E25="Concluída",1,IF(AND(ISNUMBER(I25),ISNUMBER(J25),ISNUMBER(K25),K25<>I25),MAX(0,MIN(1,(J25-I25)/(K25-I25))),IF(ISNUMBER(L25),MAX(0,MIN(1,L25)),0)))) | N25: =IF(OR(C25="",F25="",G25=""),"",IF(G25<=F25,1,MAX(0,MIN(1,(Hoje-F25)/(G25-F25))))) | O25: =IF(C25="","",IF(OR(E25="Concluída",M25>=1),"✔ Concluída",IF(E25="Pausada","‖ Pausada",IF(E25="Abandonada","– Abandonada",IF(N25="","○ Sem prazo",IF(G25<Hoje,"✖ Vencida",IF(M25>=N25-0.1,"✔ No ritmo",IF(M25>=N25-0.25,"▲ Atenção","✖ Atrasada")))))))) | P25: =IF(OR(C25="",G25="",O25="✔ Concluída"),"",G25-Hoje) | Q25: =IF(OR(C25="",G25=""),"",IF(G25-IF(F25="",Hoje,F25)<=183,"Curto",IF(G25-IF(F25="",Hoje,F25)<=731,"Médio","Longo"))) | R25: =IF(C25="","",COUNTIFS('Tarefas'!$I$34:$I$333,C25,'Tarefas'!$G$34:$G$333,"<>Concluída",'Tarefas'!$G$34:$G$333,"<>Cancelada")) | U25: =IF(C25="",0,IF(OR(E25="Pausada",E25="Abandonada"),0,1)) -> 0 | V25: =IF(U25=0,0,IF(OR(O25="✔ Concluída",O25="✔ No ritmo",O25="○ Sem prazo"),1,0)) -> 0 | W25: =IF(AND(U25=1,O25<>"✔ Concluída",G25<>""),G25+ROW()/100000,"")
B26: =IF(C26="","",ROW()-14) | M26: =IF(C26="","",IF(E26="Concluída",1,IF(AND(ISNUMBER(I26),ISNUMBER(J26),ISNUMBER(K26),K26<>I26),MAX(0,MIN(1,(J26-I26)/(K26-I26))),IF(ISNUMBER(L26),MAX(0,MIN(1,L26)),0)))) | N26: =IF(OR(C26="",F26="",G26=""),"",IF(G26<=F26,1,MAX(0,MIN(1,(Hoje-F26)/(G26-F26))))) | O26: =IF(C26="","",IF(OR(E26="Concluída",M26>=1),"✔ Concluída",IF(E26="Pausada","‖ Pausada",IF(E26="Abandonada","– Abandonada",IF(N26="","○ Sem prazo",IF(G26<Hoje,"✖ Vencida",IF(M26>=N26-0.1,"✔ No ritmo",IF(M26>=N26-0.25,"▲ Atenção","✖ Atrasada")))))))) | P26: =IF(OR(C26="",G26="",O26="✔ Concluída"),"",G26-Hoje) | Q26: =IF(OR(C26="",G26=""),"",IF(G26-IF(F26="",Hoje,F26)<=183,"Curto",IF(G26-IF(F26="",Hoje,F26)<=731,"Médio","Longo"))) | R26: =IF(C26="","",COUNTIFS('Tarefas'!$I$34:$I$333,C26,'Tarefas'!$G$34:$G$333,"<>Concluída",'Tarefas'!$G$34:$G$333,"<>Cancelada")) | U26: =IF(C26="",0,IF(OR(E26="Pausada",E26="Abandonada"),0,1)) -> 0 | V26: =IF(U26=0,0,IF(OR(O26="✔ Concluída",O26="✔ No ritmo",O26="○ Sem prazo"),1,0)) -> 0 | W26: =IF(AND(U26=1,O26<>"✔ Concluída",G26<>""),G26+ROW()/100000,"")
... B74: =IF(C74="","",ROW()-14) | M74: =IF(C74="","",IF(E74="Concluída",1,IF(AND(ISNUMBER(I74),ISNUMBER(J74),ISNUMBER(K74),K74<>I74),MAX(0,MIN(1,(J74-I74)/(K74-I74))),IF(ISNUMBER(L74),MAX(0,MIN(1,L74)),0)))) | N74: =IF(OR(C74="",F74="",G74=""),"",IF(G74<=F74,1,MAX(0,MIN(1,(Hoje-F74)/(G74-F74))))) | O74: =IF(C74="","",IF(OR(E74="Concluída",M74>=1),"✔ Concluída",IF(E74="Pausada","‖ Pausada",IF(E74="Abandonada","– Abandonada",IF(N74="","○ Sem prazo",IF(G74<Hoje,"✖ Vencida",IF(M74>=N74-0.1,"✔ No ritmo",IF(M74>=N74-0.25,"▲ Atenção","✖ Atrasada")))))))) | P74: =IF(OR(C74="",G74="",O74="✔ Concluída"),"",G74-Hoje) | Q74: =IF(OR(C74="",G74=""),"",IF(G74-IF(F74="",Hoje,F74)<=183,"Curto",IF(G74-IF(F74="",Hoje,F74)<=731,"Médio","Longo"))) | R74: =IF(C74="","",COUNTIFS('Tarefas'!$I$34:$I$333,C74,'Tarefas'!$G$34:$G$333,"<>Concluída",'Tarefas'!$G$34:$G$333,"<>Cancelada")) | U74: =IF(C74="",0,IF(OR(E74="Pausada",E74="Abandonada"),0,1)) -> 0 | V74: =IF(U74=0,0,IF(OR(O74="✔ Concluída",O74="✔ No ritmo",O74="○ Sem prazo"),1,0)) -> 0 | W74: =IF(AND(U74=1,O74<>"✔ Concluída",G74<>""),G74+ROW()/100000,"")

Sheet Tarefas
B1: Tarefas & projetos | M1: ◀ Dashboard
B2: Projetos agrupam tarefas; tarefas podem apontar para uma meta. Alertas e prioridade (matriz de Eisenhower) são automáticos.
B3: Legenda: branco = você preenche · cinza = automático (não editar) · ✔ ok ▲ atenção ✖ crítico ○ sem dados
B5: TAREFAS ABERTAS | C5: ATRASADAS | E5: VENCEM EM ATÉ 7 DIAS | H5: CONCLUÍDAS NO MÊS | J5: ENTREGUES NO PRAZO (MÊS) | M5: PROJETOS EM ANDAMENTO
B6: =COUNTIFS($B$34:$B$333,"?*",$G$34:$G$333,"<>Concluída",$G$34:$G$333,"<>Cancelada") -> 0 | C6: =COUNTIF($K$34:$K$333,"✖*") -> 0 | E6: =COUNTIF($K$34:$K$333,"▲*") -> 0 | H6: =COUNTIFS($G$34:$G$333,"Concluída",$H$34:$H$333,">="&RefIni,$H$34:$H$333,"<="&RefFim) -> 0 | J6: =IFERROR(SUMPRODUCT(($G$34:$G$333="Concluída")*($H$34:$H$333>=RefIni)*($H$34:$H$333<=RefFim)*($F$34:$F$333<>"")*($H$34:$H$333<=$F$34:$F$333))/SUMPRODUCT(($G$34:$G$333="Concluída")*($H$34:$H$333>=RefIni)*($H$34:$H$333<=RefFim)*($F$34:$F$333<>"")),"–") -> – | M6: =COUNTIF($D$11:$D$30,"Em andamento") -> 0
B7: ="Alta prioridade: "&COUNTIFS($E$34:$E$333,"Alta",$K$34:$K$333,"<>✔*",$K$34:$K$333,"<>–*",$B$34:$B$333,"?*") -> Alta prioridade: 0 | C7: =IF(C6>0,"✖ resolva ou replaneje","✔ nada atrasado") -> ✔ nada atrasado | E7: ="inclui as que vencem hoje" -> inclui as que vencem hoje | H7: ="Mês: "&RotuloMes -> Mês: Outubro 2026 | J7: =IF(ISNUMBER(J6),IF(J6>=0.8,"✔ ","▲ ")&"das concluídas com prazo","○ Nenhuma concluída com prazo") -> ○ Nenhuma concluída com prazo | M7: ="Ideias guardadas: "&COUNTIF($D$11:$D$30,"Ideia") -> Ideias guardadas: 0
B9: PROJETOS · inclui o banco de ideias (status 'Ideia')
B10: Projeto | C10: Área da vida | D10: Status | E10: Início | F10: Prazo | G10: Tarefas | H10: Concluídas | I10: Meta vinculada | J10: % | K10: Atrasadas | L10: Próxima entrega | M10: Descrição / notas
G11: =IF(B11="","",COUNTIF($C$34:$C$333,B11)) | H11: =IF(B11="","",COUNTIFS($C$34:$C$333,B11,$G$34:$G$333,"Concluída")) | J11: =IF(B11="","",IF(D11="Concluído",1,IF(G11-COUNTIFS($C$34:$C$333,B11,$G$34:$G$333,"Cancelada")<=0,0,H11/(G11-COUNTIFS($C$34:$C$333,B11,$G$34:$G$333,"Cancelada"))))) | K11: =IF(B11="","",COUNTIFS($C$34:$C$333,B11,$K$34:$K$333,"✖*")) | L11: =IF(B11="","",IF(SUMPRODUCT(MIN((($C$34:$C$333=B11)*($G$34:$G$333<>"Concluída")*($G$34:$G$333<>"Cancelada")*($F$34:$F$333<>""))*$F$34:$F$333+(1-(($C$34:$C$333=B11)*($G$34:$G$333<>"Concluída")*($G$34:$G$333<>"Cancelada")*($F$34:$F$333<>"")))*99999))>=99999,"—",SUMPRODUCT(MIN((($C$34:$C$333=B11)*($G$34:$G$333<>"Concluída")*($G$34:$G$333<>"Cancelada")*($F$34:$F$333<>""))*$F$34:$F$333+(1-(($C$34:$C$333=B11)*($G$34:$G$333<>"Concluída")*($G$34:$G$333<>"Cancelada")*($F$34:$F$333<>"")))*99999))))
G12: =IF(B12="","",COUNTIF($C$34:$C$333,B12)) | H12: =IF(B12="","",COUNTIFS($C$34:$C$333,B12,$G$34:$G$333,"Concluída")) | J12: =IF(B12="","",IF(D12="Concluído",1,IF(G12-COUNTIFS($C$34:$C$333,B12,$G$34:$G$333,"Cancelada")<=0,0,H12/(G12-COUNTIFS($C$34:$C$333,B12,$G$34:$G$333,"Cancelada"))))) | K12: =IF(B12="","",COUNTIFS($C$34:$C$333,B12,$K$34:$K$333,"✖*")) | L12: =IF(B12="","",IF(SUMPRODUCT(MIN((($C$34:$C$333=B12)*($G$34:$G$333<>"Concluída")*($G$34:$G$333<>"Cancelada")*($F$34:$F$333<>""))*$F$34:$F$333+(1-(($C$34:$C$333=B12)*($G$34:$G$333<>"Concluída")*($G$34:$G$333<>"Cancelada")*($F$34:$F$333<>"")))*99999))>=99999,"—",SUMPRODUCT(MIN((($C$34:$C$333=B12)*($G$34:$G$333<>"Concluída")*($G$34:$G$333<>"Cancelada")*($F$34:$F$333<>""))*$F$34:$F$333+(1-(($C$34:$C$333=B12)*($G$34:$G$333<>"Concluída")*($G$34:$G$333<>"Cancelada")*($F$34:$F$333<>"")))*99999))))
G13: =IF(B13="","",COUNTIF($C$34:$C$333,B13)) | H13: =IF(B13="","",COUNTIFS($C$34:$C$333,B13,$G$34:$G$333,"Concluída")) | J13: =IF(B13="","",IF(D13="Concluído",1,IF(G13-COUNTIFS($C$34:$C$333,B13,$G$34:$G$333,"Cancelada")<=0,0,H13/(G13-COUNTIFS($C$34:$C$333,B13,$G$34:$G$333,"Cancelada"))))) | K13: =IF(B13="","",COUNTIFS($C$34:$C$333,B13,$K$34:$K$333,"✖*")) | L13: =IF(B13="","",IF(SUMPRODUCT(MIN((($C$34:$C$333=B13)*($G$34:$G$333<>"Concluída")*($G$34:$G$333<>"Cancelada")*($F$34:$F$333<>""))*$F$34:$F$333+(1-(($C$34:$C$333=B13)*($G$34:$G$333<>"Concluída")*($G$34:$G$333<>"Cancelada")*($F$34:$F$333<>"")))*99999))>=99999,"—",SUMPRODUCT(MIN((($C$34:$C$333=B13)*($G$34:$G$333<>"Concluída")*($G$34:$G$333<>"Cancelada")*($F$34:$F$333<>""))*$F$34:$F$333+(1-(($C$34:$C$333=B13)*($G$34:$G$333<>"Concluída")*($G$34:$G$333<>"Cancelada")*($F$34:$F$333<>"")))*99999))))
G14: =IF(B14="","",COUNTIF($C$34:$C$333,B14)) | H14: =IF(B14="","",COUNTIFS($C$34:$C$333,B14,$G$34:$G$333,"Concluída")) | J14: =IF(B14="","",IF(D14="Concluído",1,IF(G14-COUNTIFS($C$34:$C$333,B14,$G$34:$G$333,"Cancelada")<=0,0,H14/(G14-COUNTIFS($C$34:$C$333,B14,$G$34:$G$333,"Cancelada"))))) | K14: =IF(B14="","",COUNTIFS($C$34:$C$333,B14,$K$34:$K$333,"✖*")) | L14: =IF(B14="","",IF(SUMPRODUCT(MIN((($C$34:$C$333=B14)*($G$34:$G$333<>"Concluída")*($G$34:$G$333<>"Cancelada")*($F$34:$F$333<>""))*$F$34:$F$333+(1-(($C$34:$C$333=B14)*($G$34:$G$333<>"Concluída")*($G$34:$G$333<>"Cancelada")*($F$34:$F$333<>"")))*99999))>=99999,"—",SUMPRODUCT(MIN((($C$34:$C$333=B14)*($G$34:$G$333<>"Concluída")*($G$34:$G$333<>"Cancelada")*($F$34:$F$333<>""))*$F$34:$F$333+(1-(($C$34:$C$333=B14)*($G$34:$G$333<>"Concluída")*($G$34:$G$333<>"Cancelada")*($F$34:$F$333<>"")))*99999))))
G15: =IF(B15="","",COUNTIF($C$34:$C$333,B15)) | H15: =IF(B15="","",COUNTIFS($C$34:$C$333,B15,$G$34:$G$333,"Concluída")) | J15: =IF(B15="","",IF(D15="Concluído",1,IF(G15-COUNTIFS($C$34:$C$333,B15,$G$34:$G$333,"Cancelada")<=0,0,H15/(G15-COUNTIFS($C$34:$C$333,B15,$G$34:$G$333,"Cancelada"))))) | K15: =IF(B15="","",COUNTIFS($C$34:$C$333,B15,$K$34:$K$333,"✖*")) | L15: =IF(B15="","",IF(SUMPRODUCT(MIN((($C$34:$C$333=B15)*($G$34:$G$333<>"Concluída")*($G$34:$G$333<>"Cancelada")*($F$34:$F$333<>""))*$F$34:$F$333+(1-(($C$34:$C$333=B15)*($G$34:$G$333<>"Concluída")*($G$34:$G$333<>"Cancelada")*($F$34:$F$333<>"")))*99999))>=99999,"—",SUMPRODUCT(MIN((($C$34:$C$333=B15)*($G$34:$G$333<>"Concluída")*($G$34:$G$333<>"Cancelada")*($F$34:$F$333<>""))*$F$34:$F$333+(1-(($C$34:$C$333=B15)*($G$34:$G$333<>"Concluída")*($G$34:$G$333<>"Cancelada")*($F$34:$F$333<>"")))*99999))))
G16: =IF(B16="","",COUNTIF($C$34:$C$333,B16)) | H16: =IF(B16="","",COUNTIFS($C$34:$C$333,B16,$G$34:$G$333,"Concluída")) | J16: =IF(B16="","",IF(D16="Concluído",1,IF(G16-COUNTIFS($C$34:$C$333,B16,$G$34:$G$333,"Cancelada")<=0,0,H16/(G16-COUNTIFS($C$34:$C$333,B16,$G$34:$G$333,"Cancelada"))))) | K16: =IF(B16="","",COUNTIFS($C$34:$C$333,B16,$K$34:$K$333,"✖*")) | L16: =IF(B16="","",IF(SUMPRODUCT(MIN((($C$34:$C$333=B16)*($G$34:$G$333<>"Concluída")*($G$34:$G$333<>"Cancelada")*($F$34:$F$333<>""))*$F$34:$F$333+(1-(($C$34:$C$333=B16)*($G$34:$G$333<>"Concluída")*($G$34:$G$333<>"Cancelada")*($F$34:$F$333<>"")))*99999))>=99999,"—",SUMPRODUCT(MIN((($C$34:$C$333=B16)*($G$34:$G$333<>"Concluída")*($G$34:$G$333<>"Cancelada")*($F$34:$F$333<>""))*$F$34:$F$333+(1-(($C$34:$C$333=B16)*($G$34:$G$333<>"Concluída")*($G$34:$G$333<>"Cancelada")*($F$34:$F$333<>"")))*99999))))
G17: =IF(B17="","",COUNTIF($C$34:$C$333,B17)) | H17: =IF(B17="","",COUNTIFS($C$34:$C$333,B17,$G$34:$G$333,"Concluída")) | J17: =IF(B17="","",IF(D17="Concluído",1,IF(G17-COUNTIFS($C$34:$C$333,B17,$G$34:$G$333,"Cancelada")<=0,0,H17/(G17-COUNTIFS($C$34:$C$333,B17,$G$34:$G$333,"Cancelada"))))) | K17: =IF(B17="","",COUNTIFS($C$34:$C$333,B17,$K$34:$K$333,"✖*")) | L17: =IF(B17="","",IF(SUMPRODUCT(MIN((($C$34:$C$333=B17)*($G$34:$G$333<>"Concluída")*($G$34:$G$333<>"Cancelada")*($F$34:$F$333<>""))*$F$34:$F$333+(1-(($C$34:$C$333=B17)*($G$34:$G$333<>"Concluída")*($G$34:$G$333<>"Cancelada")*($F$34:$F$333<>"")))*99999))>=99999,"—",SUMPRODUCT(MIN((($C$34:$C$333=B17)*($G$34:$G$333<>"Concluída")*($G$34:$G$333<>"Cancelada")*($F$34:$F$333<>""))*$F$34:$F$333+(1-(($C$34:$C$333=B17)*($G$34:$G$333<>"Concluída")*($G$34:$G$333<>"Cancelada")*($F$34:$F$333<>"")))*99999))))
G18: =IF(B18="","",COUNTIF($C$34:$C$333,B18)) | H18: =IF(B18="","",COUNTIFS($C$34:$C$333,B18,$G$34:$G$333,"Concluída")) | J18: =IF(B18="","",IF(D18="Concluído",1,IF(G18-COUNTIFS($C$34:$C$333,B18,$G$34:$G$333,"Cancelada")<=0,0,H18/(G18-COUNTIFS($C$34:$C$333,B18,$G$34:$G$333,"Cancelada"))))) | K18: =IF(B18="","",COUNTIFS($C$34:$C$333,B18,$K$34:$K$333,"✖*")) | L18: =IF(B18="","",IF(SUMPRODUCT(MIN((($C$34:$C$333=B18)*($G$34:$G$333<>"Concluída")*($G$34:$G$333<>"Cancelada")*($F$34:$F$333<>""))*$F$34:$F$333+(1-(($C$34:$C$333=B18)*($G$34:$G$333<>"Concluída")*($G$34:$G$333<>"Cancelada")*($F$34:$F$333<>"")))*99999))>=99999,"—",SUMPRODUCT(MIN((($C$34:$C$333=B18)*($G$34:$G$333<>"Concluída")*($G$34:$G$333<>"Cancelada")*($F$34:$F$333<>""))*$F$34:$F$333+(1-(($C$34:$C$333=B18)*($G$34:$G$333<>"Concluída")*($G$34:$G$333<>"Cancelada")*($F$34:$F$333<>"")))*99999))))
G19: =IF(B19="","",COUNTIF($C$34:$C$333,B19)) | H19: =IF(B19="","",COUNTIFS($C$34:$C$333,B19,$G$34:$G$333,"Concluída")) | J19: =IF(B19="","",IF(D19="Concluído",1,IF(G19-COUNTIFS($C$34:$C$333,B19,$G$34:$G$333,"Cancelada")<=0,0,H19/(G19-COUNTIFS($C$34:$C$333,B19,$G$34:$G$333,"Cancelada"))))) | K19: =IF(B19="","",COUNTIFS($C$34:$C$333,B19,$K$34:$K$333,"✖*")) | L19: =IF(B19="","",IF(SUMPRODUCT(MIN((($C$34:$C$333=B19)*($G$34:$G$333<>"Concluída")*($G$34:$G$333<>"Cancelada")*($F$34:$F$333<>""))*$F$34:$F$333+(1-(($C$34:$C$333=B19)*($G$34:$G$333<>"Concluída")*($G$34:$G$333<>"Cancelada")*($F$34:$F$333<>"")))*99999))>=99999,"—",SUMPRODUCT(MIN((($C$34:$C$333=B19)*($G$34:$G$333<>"Concluída")*($G$34:$G$333<>"Cancelada")*($F$34:$F$333<>""))*$F$34:$F$333+(1-(($C$34:$C$333=B19)*($G$34:$G$333<>"Concluída")*($G$34:$G$333<>"Cancelada")*($F$34:$F$333<>"")))*99999))))
G20: =IF(B20="","",COUNTIF($C$34:$C$333,B20)) | H20: =IF(B20="","",COUNTIFS($C$34:$C$333,B20,$G$34:$G$333,"Concluída")) | J20: =IF(B20="","",IF(D20="Concluído",1,IF(G20-COUNTIFS($C$34:$C$333,B20,$G$34:$G$333,"Cancelada")<=0,0,H20/(G20-COUNTIFS($C$34:$C$333,B20,$G$34:$G$333,"Cancelada"))))) | K20: =IF(B20="","",COUNTIFS($C$34:$C$333,B20,$K$34:$K$333,"✖*")) | L20: =IF(B20="","",IF(SUMPRODUCT(MIN((($C$34:$C$333=B20)*($G$34:$G$333<>"Concluída")*($G$34:$G$333<>"Cancelada")*($F$34:$F$333<>""))*$F$34:$F$333+(1-(($C$34:$C$333=B20)*($G$34:$G$333<>"Concluída")*($G$34:$G$333<>"Cancelada")*($F$34:$F$333<>"")))*99999))>=99999,"—",SUMPRODUCT(MIN((($C$34:$C$333=B20)*($G$34:$G$333<>"Concluída")*($G$34:$G$333<>"Cancelada")*($F$34:$F$333<>""))*$F$34:$F$333+(1-(($C$34:$C$333=B20)*($G$34:$G$333<>"Concluída")*($G$34:$G$333<>"Cancelada")*($F$34:$F$333<>"")))*99999))))
G21: =IF(B21="","",COUNTIF($C$34:$C$333,B21)) | H21: =IF(B21="","",COUNTIFS($C$34:$C$333,B21,$G$34:$G$333,"Concluída")) | J21: =IF(B21="","",IF(D21="Concluído",1,IF(G21-COUNTIFS($C$34:$C$333,B21,$G$34:$G$333,"Cancelada")<=0,0,H21/(G21-COUNTIFS($C$34:$C$333,B21,$G$34:$G$333,"Cancelada"))))) | K21: =IF(B21="","",COUNTIFS($C$34:$C$333,B21,$K$34:$K$333,"✖*")) | L21: =IF(B21="","",IF(SUMPRODUCT(MIN((($C$34:$C$333=B21)*($G$34:$G$333<>"Concluída")*($G$34:$G$333<>"Cancelada")*($F$34:$F$333<>""))*$F$34:$F$333+(1-(($C$34:$C$333=B21)*($G$34:$G$333<>"Concluída")*($G$34:$G$333<>"Cancelada")*($F$34:$F$333<>"")))*99999))>=99999,"—",SUMPRODUCT(MIN((($C$34:$C$333=B21)*($G$34:$G$333<>"Concluída")*($G$34:$G$333<>"Cancelada")*($F$34:$F$333<>""))*$F$34:$F$333+(1-(($C$34:$C$333=B21)*($G$34:$G$333<>"Concluída")*($G$34:$G$333<>"Cancelada")*($F$34:$F$333<>"")))*99999))))
G22: =IF(B22="","",COUNTIF($C$34:$C$333,B22)) | H22: =IF(B22="","",COUNTIFS($C$34:$C$333,B22,$G$34:$G$333,"Concluída")) | J22: =IF(B22="","",IF(D22="Concluído",1,IF(G22-COUNTIFS($C$34:$C$333,B22,$G$34:$G$333,"Cancelada")<=0,0,H22/(G22-COUNTIFS($C$34:$C$333,B22,$G$34:$G$333,"Cancelada"))))) | K22: =IF(B22="","",COUNTIFS($C$34:$C$333,B22,$K$34:$K$333,"✖*")) | L22: =IF(B22="","",IF(SUMPRODUCT(MIN((($C$34:$C$333=B22)*($G$34:$G$333<>"Concluída")*($G$34:$G$333<>"Cancelada")*($F$34:$F$333<>""))*$F$34:$F$333+(1-(($C$34:$C$333=B22)*($G$34:$G$333<>"Concluída")*($G$34:$G$333<>"Cancelada")*($F$34:$F$333<>"")))*99999))>=99999,"—",SUMPRODUCT(MIN((($C$34:$C$333=B22)*($G$34:$G$333<>"Concluída")*($G$34:$G$333<>"Cancelada")*($F$34:$F$333<>""))*$F$34:$F$333+(1-(($C$34:$C$333=B22)*($G$34:$G$333<>"Concluída")*($G$34:$G$333<>"Cancelada")*($F$34:$F$333<>"")))*99999))))
... G30: =IF(B30="","",COUNTIF($C$34:$C$333,B30)) | H30: =IF(B30="","",COUNTIFS($C$34:$C$333,B30,$G$34:$G$333,"Concluída")) | J30: =IF(B30="","",IF(D30="Concluído",1,IF(G30-COUNTIFS($C$34:$C$333,B30,$G$34:$G$333,"Cancelada")<=0,0,H30/(G30-COUNTIFS($C$34:$C$333,B30,$G$34:$G$333,"Cancelada"))))) | K30: =IF(B30="","",COUNTIFS($C$34:$C$333,B30,$K$34:$K$333,"✖*")) | L30: =IF(B30="","",IF(SUMPRODUCT(MIN((($C$34:$C$333=B30)*($G$34:$G$333<>"Concluída")*($G$34:$G$333<>"Cancelada")*($F$34:$F$333<>""))*$F$34:$F$333+(1-(($C$34:$C$333=B30)*($G$34:$G$333<>"Concluída")*($G$34:$G$333<>"Cancelada")*($F$34:$F$333<>"")))*99999))>=99999,"—",SUMPRODUCT(MIN((($C$34:$C$333=B30)*($G$34:$G$333<>"Concluída")*($G$34:$G$333<>"Cancelada")*($F$34:$F$333<>""))*$F$34:$F$333+(1-(($C$34:$C$333=B30)*($G$34:$G$333<>"Concluída")*($G$34:$G$333<>"Cancelada")*($F$34:$F$333<>"")))*99999))))
B32: TAREFAS
B33: Tarefa | C33: Projeto | D33: Área da vida | E33: Prioridade | F33: Prazo | G33: Status | H33: Concluída em | I33: Meta vinculada | J33: Dias p/ prazo | K33: Alerta | L33: Quadrante | M33: Notas
J34: =IF(OR(B34="",F34="",G34="Concluída",G34="Cancelada"),"",F34-Hoje) | K34: =IF(B34="","",IF(G34="Concluída","✔ Feita",IF(G34="Cancelada","– Cancelada",IF(F34="","○ Sem prazo",IF(F34<Hoje,"✖ Atrasada",IF(F34=Hoje,"▲ Vence hoje",IF(F34-Hoje<=7,"▲ Próximos 7 dias","○ No prazo"))))))) | L34: =IF(OR(B34="",G34="Concluída",G34="Cancelada"),"",IF(E34="Alta",IF(AND(F34<>"",F34-Hoje<=3),"1 · Fazer já","2 · Agendar"),IF(AND(F34<>"",F34-Hoje<=3),"3 · Resolver rápido","4 · Depois"))) | N34: =IF(AND(B34<>"",G34<>"Concluída",G34<>"Cancelada",F34<>""),F34+ROW()/100000,"")
J35: =IF(OR(B35="",F35="",G35="Concluída",G35="Cancelada"),"",F35-Hoje) | K35: =IF(B35="","",IF(G35="Concluída","✔ Feita",IF(G35="Cancelada","– Cancelada",IF(F35="","○ Sem prazo",IF(F35<Hoje,"✖ Atrasada",IF(F35=Hoje,"▲ Vence hoje",IF(F35-Hoje<=7,"▲ Próximos 7 dias","○ No prazo"))))))) | L35: =IF(OR(B35="",G35="Concluída",G35="Cancelada"),"",IF(E35="Alta",IF(AND(F35<>"",F35-Hoje<=3),"1 · Fazer já","2 · Agendar"),IF(AND(F35<>"",F35-Hoje<=3),"3 · Resolver rápido","4 · Depois"))) | N35: =IF(AND(B35<>"",G35<>"Concluída",G35<>"Cancelada",F35<>""),F35+ROW()/100000,"")
J36: =IF(OR(B36="",F36="",G36="Concluída",G36="Cancelada"),"",F36-Hoje) | K36: =IF(B36="","",IF(G36="Concluída","✔ Feita",IF(G36="Cancelada","– Cancelada",IF(F36="","○ Sem prazo",IF(F36<Hoje,"✖ Atrasada",IF(F36=Hoje,"▲ Vence hoje",IF(F36-Hoje<=7,"▲ Próximos 7 dias","○ No prazo"))))))) | L36: =IF(OR(B36="",G36="Concluída",G36="Cancelada"),"",IF(E36="Alta",IF(AND(F36<>"",F36-Hoje<=3),"1 · Fazer já","2 · Agendar"),IF(AND(F36<>"",F36-Hoje<=3),"3 · Resolver rápido","4 · Depois"))) | N36: =IF(AND(B36<>"",G36<>"Concluída",G36<>"Cancelada",F36<>""),F36+ROW()/100000,"")
J37: =IF(OR(B37="",F37="",G37="Concluída",G37="Cancelada"),"",F37-Hoje) | K37: =IF(B37="","",IF(G37="Concluída","✔ Feita",IF(G37="Cancelada","– Cancelada",IF(F37="","○ Sem prazo",IF(F37<Hoje,"✖ Atrasada",IF(F37=Hoje,"▲ Vence hoje",IF(F37-Hoje<=7,"▲ Próximos 7 dias","○ No prazo"))))))) | L37: =IF(OR(B37="",G37="Concluída",G37="Cancelada"),"",IF(E37="Alta",IF(AND(F37<>"",F37-Hoje<=3),"1 · Fazer já","2 · Agendar"),IF(AND(F37<>"",F37-Hoje<=3),"3 · Resolver rápido","4 · Depois"))) | N37: =IF(AND(B37<>"",G37<>"Concluída",G37<>"Cancelada",F37<>""),F37+ROW()/100000,"")
J38: =IF(OR(B38="",F38="",G38="Concluída",G38="Cancelada"),"",F38-Hoje) | K38: =IF(B38="","",IF(G38="Concluída","✔ Feita",IF(G38="Cancelada","– Cancelada",IF(F38="","○ Sem prazo",IF(F38<Hoje,"✖ Atrasada",IF(F38=Hoje,"▲ Vence hoje",IF(F38-Hoje<=7,"▲ Próximos 7 dias","○ No prazo"))))))) | L38: =IF(OR(B38="",G38="Concluída",G38="Cancelada"),"",IF(E38="Alta",IF(AND(F38<>"",F38-Hoje<=3),"1 · Fazer já","2 · Agendar"),IF(AND(F38<>"",F38-Hoje<=3),"3 · Resolver rápido","4 · Depois"))) | N38: =IF(AND(B38<>"",G38<>"Concluída",G38<>"Cancelada",F38<>""),F38+ROW()/100000,"")
J39: =IF(OR(B39="",F39="",G39="Concluída",G39="Cancelada"),"",F39-Hoje) | K39: =IF(B39="","",IF(G39="Concluída","✔ Feita",IF(G39="Cancelada","– Cancelada",IF(F39="","○ Sem prazo",IF(F39<Hoje,"✖ Atrasada",IF(F39=Hoje,"▲ Vence hoje",IF(F39-Hoje<=7,"▲ Próximos 7 dias","○ No prazo"))))))) | L39: =IF(OR(B39="",G39="Concluída",G39="Cancelada"),"",IF(E39="Alta",IF(AND(F39<>"",F39-Hoje<=3),"1 · Fazer já","2 · Agendar"),IF(AND(F39<>"",F39-Hoje<=3),"3 · Resolver rápido","4 · Depois"))) | N39: =IF(AND(B39<>"",G39<>"Concluída",G39<>"Cancelada",F39<>""),F39+ROW()/100000,"")
J40: =IF(OR(B40="",F40="",G40="Concluída",G40="Cancelada"),"",F40-Hoje) | K40: =IF(B40="","",IF(G40="Concluída","✔ Feita",IF(G40="Cancelada","– Cancelada",IF(F40="","○ Sem prazo",IF(F40<Hoje,"✖ Atrasada",IF(F40=Hoje,"▲ Vence hoje",IF(F40-Hoje<=7,"▲ Próximos 7 dias","○ No prazo"))))))) | L40: =IF(OR(B40="",G40="Concluída",G40="Cancelada"),"",IF(E40="Alta",IF(AND(F40<>"",F40-Hoje<=3),"1 · Fazer já","2 · Agendar"),IF(AND(F40<>"",F40-Hoje<=3),"3 · Resolver rápido","4 · Depois"))) | N40: =IF(AND(B40<>"",G40<>"Concluída",G40<>"Cancelada",F40<>""),F40+ROW()/100000,"")
J41: =IF(OR(B41="",F41="",G41="Concluída",G41="Cancelada"),"",F41-Hoje) | K41: =IF(B41="","",IF(G41="Concluída","✔ Feita",IF(G41="Cancelada","– Cancelada",IF(F41="","○ Sem prazo",IF(F41<Hoje,"✖ Atrasada",IF(F41=Hoje,"▲ Vence hoje",IF(F41-Hoje<=7,"▲ Próximos 7 dias","○ No prazo"))))))) | L41: =IF(OR(B41="",G41="Concluída",G41="Cancelada"),"",IF(E41="Alta",IF(AND(F41<>"",F41-Hoje<=3),"1 · Fazer já","2 · Agendar"),IF(AND(F41<>"",F41-Hoje<=3),"3 · Resolver rápido","4 · Depois"))) | N41: =IF(AND(B41<>"",G41<>"Concluída",G41<>"Cancelada",F41<>""),F41+ROW()/100000,"")
J42: =IF(OR(B42="",F42="",G42="Concluída",G42="Cancelada"),"",F42-Hoje) | K42: =IF(B42="","",IF(G42="Concluída","✔ Feita",IF(G42="Cancelada","– Cancelada",IF(F42="","○ Sem prazo",IF(F42<Hoje,"✖ Atrasada",IF(F42=Hoje,"▲ Vence hoje",IF(F42-Hoje<=7,"▲ Próximos 7 dias","○ No prazo"))))))) | L42: =IF(OR(B42="",G42="Concluída",G42="Cancelada"),"",IF(E42="Alta",IF(AND(F42<>"",F42-Hoje<=3),"1 · Fazer já","2 · Agendar"),IF(AND(F42<>"",F42-Hoje<=3),"3 · Resolver rápido","4 · Depois"))) | N42: =IF(AND(B42<>"",G42<>"Concluída",G42<>"Cancelada",F42<>""),F42+ROW()/100000,"")
J43: =IF(OR(B43="",F43="",G43="Concluída",G43="Cancelada"),"",F43-Hoje) | K43: =IF(B43="","",IF(G43="Concluída","✔ Feita",IF(G43="Cancelada","– Cancelada",IF(F43="","○ Sem prazo",IF(F43<Hoje,"✖ Atrasada",IF(F43=Hoje,"▲ Vence hoje",IF(F43-Hoje<=7,"▲ Próximos 7 dias","○ No prazo"))))))) | L43: =IF(OR(B43="",G43="Concluída",G43="Cancelada"),"",IF(E43="Alta",IF(AND(F43<>"",F43-Hoje<=3),"1 · Fazer já","2 · Agendar"),IF(AND(F43<>"",F43-Hoje<=3),"3 · Resolver rápido","4 · Depois"))) | N43: =IF(AND(B43<>"",G43<>"Concluída",G43<>"Cancelada",F43<>""),F43+ROW()/100000,"")
J44: =IF(OR(B44="",F44="",G44="Concluída",G44="Cancelada"),"",F44-Hoje) | K44: =IF(B44="","",IF(G44="Concluída","✔ Feita",IF(G44="Cancelada","– Cancelada",IF(F44="","○ Sem prazo",IF(F44<Hoje,"✖ Atrasada",IF(F44=Hoje,"▲ Vence hoje",IF(F44-Hoje<=7,"▲ Próximos 7 dias","○ No prazo"))))))) | L44: =IF(OR(B44="",G44="Concluída",G44="Cancelada"),"",IF(E44="Alta",IF(AND(F44<>"",F44-Hoje<=3),"1 · Fazer já","2 · Agendar"),IF(AND(F44<>"",F44-Hoje<=3),"3 · Resolver rápido","4 · Depois"))) | N44: =IF(AND(B44<>"",G44<>"Concluída",G44<>"Cancelada",F44<>""),F44+ROW()/100000,"")
J45: =IF(OR(B45="",F45="",G45="Concluída",G45="Cancelada"),"",F45-Hoje) | K45: =IF(B45="","",IF(G45="Concluída","✔ Feita",IF(G45="Cancelada","– Cancelada",IF(F45="","○ Sem prazo",IF(F45<Hoje,"✖ Atrasada",IF(F45=Hoje,"▲ Vence hoje",IF(F45-Hoje<=7,"▲ Próximos 7 dias","○ No prazo"))))))) | L45: =IF(OR(B45="",G45="Concluída",G45="Cancelada"),"",IF(E45="Alta",IF(AND(F45<>"",F45-Hoje<=3),"1 · Fazer já","2 · Agendar"),IF(AND(F45<>"",F45-Hoje<=3),"3 · Resolver rápido","4 · Depois"))) | N45: =IF(AND(B45<>"",G45<>"Concluída",G45<>"Cancelada",F45<>""),F45+ROW()/100000,"")
... J333: =IF(OR(B333="",F333="",G333="Concluída",G333="Cancelada"),"",F333-Hoje) | K333: =IF(B333="","",IF(G333="Concluída","✔ Feita",IF(G333="Cancelada","– Cancelada",IF(F333="","○ Sem prazo",IF(F333<Hoje,"✖ Atrasada",IF(F333=Hoje,"▲ Vence hoje",IF(F333-Hoje<=7,"▲ Próximos 7 dias","○ No prazo"))))))) | L333: =IF(OR(B333="",G333="Concluída",G333="Cancelada"),"",IF(E333="Alta",IF(AND(F333<>"",F333-Hoje<=3),"1 · Fazer já","2 · Agendar"),IF(AND(F333<>"",F333-Hoje<=3),"3 · Resolver rápido","4 · Depois"))) | N333: =IF(AND(B333<>"",G333<>"Concluída",G333<>"Cancelada",F333<>""),F333+ROW()/100000,"")

Sheet Finanças
B1: Finanças · lançamentos | K1: ◀ Dashboard
B2: Registre cada receita, despesa e aporte. Orçamento, patrimônio e Dashboard se atualizam sozinhos.
B3: Legenda: branco = você preenche · cinza = automático (não editar) · ✔ ok ▲ atenção ✖ crítico ○ sem dados
B5: RECEITAS DO MÊS | D5: DESPESAS DO MÊS | E5: RESULTADO (RECEITAS − DESPESAS) | F5: APORTES (POUPANÇA / INVESTIMENTO) | H5: TAXA DE POUPANÇA | J5: LANÇAMENTOS NO MÊS
B6: =SUMIFS($F$10:$F$1509,$C$10:$C$1509,"Receita",$B$10:$B$1509,">="&RefIni,$B$10:$B$1509,"<="&RefFim) -> 0 | D6: =SUMIFS($F$10:$F$1509,$C$10:$C$1509,"Despesa",$B$10:$B$1509,">="&RefIni,$B$10:$B$1509,"<="&RefFim) -> 0 | E6: =B6-D6 -> 0 | F6: =SUMIFS($F$10:$F$1509,$C$10:$C$1509,"Aporte",$B$10:$B$1509,">="&RefIni,$B$10:$B$1509,"<="&RefFim) -> 0 | H6: =IF(B6>0,E6/B6,"–") -> – | J6: =COUNTIFS($B$10:$B$1509,">="&RefIni,$B$10:$B$1509,"<="&RefFim) -> 0
B7: ="Mês: "&RotuloMes -> Mês: Outubro 2026 | D7: =IF('Orçamento'!$D$43>0,IF(D6>'Orçamento'!$D$43,"✖ ","✔ ")&ROUND(D6/'Orçamento'!$D$43*100,0)&"% do orçamento","○ Orçamento não definido") -> ○ Orçamento não definido | E7: =IF(B6+D6=0,"○ Sem lançamentos",IF(E6>=0,"✔ Sobrou dinheiro","✖ Gastou mais do que ganhou")) -> ○ Sem lançamentos | F7: ="Saldo em caixa: € "&FIXED(E6-F6,0) -> Saldo em caixa: € 0 | H7: =IF(ISNUMBER(H6),IF(H6>=MetaPoup,"✔ ","▲ ")&"meta "&ROUND(MetaPoup*100,0)&"%","○ Sem receitas no mês") -> ○ Sem receitas no mês | J7: =IF(COUNTIF($K$10:$K$1509,"▲*")>0,"▲ "&COUNTIF($K$10:$K$1509,"▲*")&" linha(s) incompleta(s)","✔ Tudo completo") -> ✔ Tudo completo
B9: Data | C9: Tipo | D9: Categoria | E9: Descrição | F9: Valor (€) | G9: Conta / forma | H9: Fixo / variável | I9: Notas | J9: Grupo | K9: Verificação
J10: =IF(C10<>"Despesa","",IFERROR(INDEX('Config'!$J$6:$J$40,MATCH(D10,'Config'!$I$6:$I$40,0)),"—")) | K10: =IF(COUNTA(B10:F10)=0,"",IF(OR(B10="",C10="",D10="",F10=""),"▲ Completar","✔"))
J11: =IF(C11<>"Despesa","",IFERROR(INDEX('Config'!$J$6:$J$40,MATCH(D11,'Config'!$I$6:$I$40,0)),"—")) | K11: =IF(COUNTA(B11:F11)=0,"",IF(OR(B11="",C11="",D11="",F11=""),"▲ Completar","✔"))
J12: =IF(C12<>"Despesa","",IFERROR(INDEX('Config'!$J$6:$J$40,MATCH(D12,'Config'!$I$6:$I$40,0)),"—")) | K12: =IF(COUNTA(B12:F12)=0,"",IF(OR(B12="",C12="",D12="",F12=""),"▲ Completar","✔"))
J13: =IF(C13<>"Despesa","",IFERROR(INDEX('Config'!$J$6:$J$40,MATCH(D13,'Config'!$I$6:$I$40,0)),"—")) | K13: =IF(COUNTA(B13:F13)=0,"",IF(OR(B13="",C13="",D13="",F13=""),"▲ Completar","✔"))
J14: =IF(C14<>"Despesa","",IFERROR(INDEX('Config'!$J$6:$J$40,MATCH(D14,'Config'!$I$6:$I$40,0)),"—")) | K14: =IF(COUNTA(B14:F14)=0,"",IF(OR(B14="",C14="",D14="",F14=""),"▲ Completar","✔"))
J15: =IF(C15<>"Despesa","",IFERROR(INDEX('Config'!$J$6:$J$40,MATCH(D15,'Config'!$I$6:$I$40,0)),"—")) | K15: =IF(COUNTA(B15:F15)=0,"",IF(OR(B15="",C15="",D15="",F15=""),"▲ Completar","✔"))
J16: =IF(C16<>"Despesa","",IFERROR(INDEX('Config'!$J$6:$J$40,MATCH(D16,'Config'!$I$6:$I$40,0)),"—")) | K16: =IF(COUNTA(B16:F16)=0,"",IF(OR(B16="",C16="",D16="",F16=""),"▲ Completar","✔"))
J17: =IF(C17<>"Despesa","",IFERROR(INDEX('Config'!$J$6:$J$40,MATCH(D17,'Config'!$I$6:$I$40,0)),"—")) | K17: =IF(COUNTA(B17:F17)=0,"",IF(OR(B17="",C17="",D17="",F17=""),"▲ Completar","✔"))
J18: =IF(C18<>"Despesa","",IFERROR(INDEX('Config'!$J$6:$J$40,MATCH(D18,'Config'!$I$6:$I$40,0)),"—")) | K18: =IF(COUNTA(B18:F18)=0,"",IF(OR(B18="",C18="",D18="",F18=""),"▲ Completar","✔"))
J19: =IF(C19<>"Despesa","",IFERROR(INDEX('Config'!$J$6:$J$40,MATCH(D19,'Config'!$I$6:$I$40,0)),"—")) | K19: =IF(COUNTA(B19:F19)=0,"",IF(OR(B19="",C19="",D19="",F19=""),"▲ Completar","✔"))
J20: =IF(C20<>"Despesa","",IFERROR(INDEX('Config'!$J$6:$J$40,MATCH(D20,'Config'!$I$6:$I$40,0)),"—")) | K20: =IF(COUNTA(B20:F20)=0,"",IF(OR(B20="",C20="",D20="",F20=""),"▲ Completar","✔"))
J21: =IF(C21<>"Despesa","",IFERROR(INDEX('Config'!$J$6:$J$40,MATCH(D21,'Config'!$I$6:$I$40,0)),"—")) | K21: =IF(COUNTA(B21:F21)=0,"",IF(OR(B21="",C21="",D21="",F21=""),"▲ Completar","✔"))
... J1509: =IF(C1509<>"Despesa","",IFERROR(INDEX('Config'!$J$6:$J$40,MATCH(D1509,'Config'!$I$6:$I$40,0)),"—")) | K1509: =IF(COUNTA(B1509:F1509)=0,"",IF(OR(B1509="",C1509="",D1509="",F1509=""),"▲ Completar","✔"))

Sheet Orçamento
B1: Orçamento · planejado × realizado e patrimônio | U1: ◀ Dashboard
B2: Defina quanto quer gastar por categoria. O realizado vem de Finanças. No fim de cada mês, atualize o patrimônio.
B3: Legenda: branco = você preenche · cinza = automático (não editar) · ✔ ok ▲ atenção ✖ crítico ○ sem dados
B5: RESUMO MENSAL
B6: Indicador | D6: Plano / mês | E6: Jan | F6: Fev | G6: Mar | H6: Abr | I6: Mai | J6: Jun | K6: Jul | L6: Ago | M6: Set | N6: Out | O6: Nov | P6: Dez | Q6: Total ano | R6: Média/mês até a ref. | S6: Mês de referência | T6: % do plano | U6: Status no mês
B7: Receitas | D7: =D63 -> 0 | E7: =SUMIFS('Finanças'!$F$10:$F$1509,'Finanças'!$C$10:$C$1509,"Receita",'Finanças'!$B$10:$B$1509,">="&DATE(Ano,1,1),'Finanças'!$B$10:$B$1509,"<="&DATE(Ano,1+1,0)) -> 0 | F7: =SUMIFS('Finanças'!$F$10:$F$1509,'Finanças'!$C$10:$C$1509,"Receita",'Finanças'!$B$10:$B$1509,">="&DATE(Ano,2,1),'Finanças'!$B$10:$B$1509,"<="&DATE(Ano,2+1,0)) -> 0 | G7: =SUMIFS('Finanças'!$F$10:$F$1509,'Finanças'!$C$10:$C$1509,"Receita",'Finanças'!$B$10:$B$1509,">="&DATE(Ano,3,1),'Finanças'!$B$10:$B$1509,"<="&DATE(Ano,3+1,0)) -> 0 | H7: =SUMIFS('Finanças'!$F$10:$F$1509,'Finanças'!$C$10:$C$1509,"Receita",'Finanças'!$B$10:$B$1509,">="&DATE(Ano,4,1),'Finanças'!$B$10:$B$1509,"<="&DATE(Ano,4+1,0)) -> 0 | I7: =SUMIFS('Finanças'!$F$10:$F$1509,'Finanças'!$C$10:$C$1509,"Receita",'Finanças'!$B$10:$B$1509,">="&DATE(Ano,5,1),'Finanças'!$B$10:$B$1509,"<="&DATE(Ano,5+1,0)) -> 0 | J7: =SUMIFS('Finanças'!$F$10:$F$1509,'Finanças'!$C$10:$C$1509,"Receita",'Finanças'!$B$10:$B$1509,">="&DATE(Ano,6,1),'Finanças'!$B$10:$B$1509,"<="&DATE(Ano,6+1,0)) -> 0 | K7: =SUMIFS('Finanças'!$F$10:$F$1509,'Finanças'!$C$10:$C$1509,"Receita",'Finanças'!$B$10:$B$1509,">="&DATE(Ano,7,1),'Finanças'!$B$10:$B$1509,"<="&DATE(Ano,7+1,0)) -> 0 | L7: =SUMIFS('Finanças'!$F$10:$F$1509,'Finanças'!$C$10:$C$1509,"Receita",'Finanças'!$B$10:$B$1509,">="&DATE(Ano,8,1),'Finanças'!$B$10:$B$1509,"<="&DATE(Ano,8+1,0)) -> 0 | M7: =SUMIFS('Finanças'!$F$10:$F$1509,'Finanças'!$C$10:$C$1509,"Receita",'Finanças'!$B$10:$B$1509,">="&DATE(Ano,9,1),'Finanças'!$B$10:$B$1509,"<="&DATE(Ano,9+1,0)) -> 0 | N7: =SUMIFS('Finanças'!$F$10:$F$1509,'Finanças'!$C$10:$C$1509,"Receita",'Finanças'!$B$10:$B$1509,">="&DATE(Ano,10,1),'Finanças'!$B$10:$B$1509,"<="&DATE(Ano,10+1,0)) -> 0 | O7: =SUMIFS('Finanças'!$F$10:$F$1509,'Finanças'!$C$10:$C$1509,"Receita",'Finanças'!$B$10:$B$1509,">="&DATE(Ano,11,1),'Finanças'!$B$10:$B$1509,"<="&DATE(Ano,11+1,0)) -> 0 | P7: =SUMIFS('Finanças'!$F$10:$F$1509,'Finanças'!$C$10:$C$1509,"Receita",'Finanças'!$B$10:$B$1509,">="&DATE(Ano,12,1),'Finanças'!$B$10:$B$1509,"<="&DATE(Ano,12+1,0)) -> 0 | Q7: =SUM(E7:P7) -> 0 | R7: =SUMPRODUCT((COLUMN($E7:$P7)-COLUMN($E7)+1<=RefMes)*$E7:$P7)/RefMes -> 0 | S7: =INDEX(E7:P7,RefMes) -> 0 | T7: =IF(D7>0,S7/D7,"") | U7: =IF(T7="","",IF(T7>=1,"✔ Receita prevista atingida","▲ "&ROUND(T7*100,0)&"% do previsto"))
B8: Despesas | D8: =D43 -> 0 | E8: =SUMIFS('Finanças'!$F$10:$F$1509,'Finanças'!$C$10:$C$1509,"Despesa",'Finanças'!$B$10:$B$1509,">="&DATE(Ano,1,1),'Finanças'!$B$10:$B$1509,"<="&DATE(Ano,1+1,0)) -> 0 | F8: =SUMIFS('Finanças'!$F$10:$F$1509,'Finanças'!$C$10:$C$1509,"Despesa",'Finanças'!$B$10:$B$1509,">="&DATE(Ano,2,1),'Finanças'!$B$10:$B$1509,"<="&DATE(Ano,2+1,0)) -> 0 | G8: =SUMIFS('Finanças'!$F$10:$F$1509,'Finanças'!$C$10:$C$1509,"Despesa",'Finanças'!$B$10:$B$1509,">="&DATE(Ano,3,1),'Finanças'!$B$10:$B$1509,"<="&DATE(Ano,3+1,0)) -> 0 | H8: =SUMIFS('Finanças'!$F$10:$F$1509,'Finanças'!$C$10:$C$1509,"Despesa",'Finanças'!$B$10:$B$1509,">="&DATE(Ano,4,1),'Finanças'!$B$10:$B$1509,"<="&DATE(Ano,4+1,0)) -> 0 | I8: =SUMIFS('Finanças'!$F$10:$F$1509,'Finanças'!$C$10:$C$1509,"Despesa",'Finanças'!$B$10:$B$1509,">="&DATE(Ano,5,1),'Finanças'!$B$10:$B$1509,"<="&DATE(Ano,5+1,0)) -> 0 | J8: =SUMIFS('Finanças'!$F$10:$F$1509,'Finanças'!$C$10:$C$1509,"Despesa",'Finanças'!$B$10:$B$1509,">="&DATE(Ano,6,1),'Finanças'!$B$10:$B$1509,"<="&DATE(Ano,6+1,0)) -> 0 | K8: =SUMIFS('Finanças'!$F$10:$F$1509,'Finanças'!$C$10:$C$1509,"Despesa",'Finanças'!$B$10:$B$1509,">="&DATE(Ano,7,1),'Finanças'!$B$10:$B$1509,"<="&DATE(Ano,7+1,0)) -> 0 | L8: =SUMIFS('Finanças'!$F$10:$F$1509,'Finanças'!$C$10:$C$1509,"Despesa",'Finanças'!$B$10:$B$1509,">="&DATE(Ano,8,1),'Finanças'!$B$10:$B$1509,"<="&DATE(Ano,8+1,0)) -> 0 | M8: =SUMIFS('Finanças'!$F$10:$F$1509,'Finanças'!$C$10:$C$1509,"Despesa",'Finanças'!$B$10:$B$1509,">="&DATE(Ano,9,1),'Finanças'!$B$10:$B$1509,"<="&DATE(Ano,9+1,0)) -> 0 | N8: =SUMIFS('Finanças'!$F$10:$F$1509,'Finanças'!$C$10:$C$1509,"Despesa",'Finanças'!$B$10:$B$1509,">="&DATE(Ano,10,1),'Finanças'!$B$10:$B$1509,"<="&DATE(Ano,10+1,0)) -> 0 | O8: =SUMIFS('Finanças'!$F$10:$F$1509,'Finanças'!$C$10:$C$1509,"Despesa",'Finanças'!$B$10:$B$1509,">="&DATE(Ano,11,1),'Finanças'!$B$10:$B$1509,"<="&DATE(Ano,11+1,0)) -> 0 | P8: =SUMIFS('Finanças'!$F$10:$F$1509,'Finanças'!$C$10:$C$1509,"Despesa",'Finanças'!$B$10:$B$1509,">="&DATE(Ano,12,1),'Finanças'!$B$10:$B$1509,"<="&DATE(Ano,12+1,0)) -> 0 | Q8: =SUM(E8:P8) -> 0 | R8: =SUMPRODUCT((COLUMN($E8:$P8)-COLUMN($E8)+1<=RefMes)*$E8:$P8)/RefMes -> 0 | S8: =INDEX(E8:P8,RefMes) -> 0 | T8: =IF(D8>0,S8/D8,"") | U8: =IF(T8="","",IF(T8>1,"✖ Acima do orçamento",IF(T8>DiasRef/DiasMes+0.1,"▲ Gastando rápido","✔ Dentro do orçamento")))
B9: Resultado (receitas − despesas) | D9: =D7-D8 -> 0 | E9: =E7-E8 -> 0 | F9: =F7-F8 -> 0 | G9: =G7-G8 -> 0 | H9: =H7-H8 -> 0 | I9: =I7-I8 -> 0 | J9: =J7-J8 -> 0 | K9: =K7-K8 -> 0 | ... P9: =P7-P8 -> 0 | Q9: =SUM(E9:P9) -> 0 | R9: =SUMPRODUCT((COLUMN($E9:$P9)-COLUMN($E9)+1<=RefMes)*$E9:$P9)/RefMes -> 0 | S9: =INDEX(E9:P9,RefMes) -> 0
B10: Aportes (poupança / invest.) | E10: =SUMIFS('Finanças'!$F$10:$F$1509,'Finanças'!$C$10:$C$1509,"Aporte",'Finanças'!$B$10:$B$1509,">="&DATE(Ano,1,1),'Finanças'!$B$10:$B$1509,"<="&DATE(Ano,1+1,0)) -> 0 | F10: =SUMIFS('Finanças'!$F$10:$F$1509,'Finanças'!$C$10:$C$1509,"Aporte",'Finanças'!$B$10:$B$1509,">="&DATE(Ano,2,1),'Finanças'!$B$10:$B$1509,"<="&DATE(Ano,2+1,0)) -> 0 | G10: =SUMIFS('Finanças'!$F$10:$F$1509,'Finanças'!$C$10:$C$1509,"Aporte",'Finanças'!$B$10:$B$1509,">="&DATE(Ano,3,1),'Finanças'!$B$10:$B$1509,"<="&DATE(Ano,3+1,0)) -> 0 | H10: =SUMIFS('Finanças'!$F$10:$F$1509,'Finanças'!$C$10:$C$1509,"Aporte",'Finanças'!$B$10:$B$1509,">="&DATE(Ano,4,1),'Finanças'!$B$10:$B$1509,"<="&DATE(Ano,4+1,0)) -> 0 | I10: =SUMIFS('Finanças'!$F$10:$F$1509,'Finanças'!$C$10:$C$1509,"Aporte",'Finanças'!$B$10:$B$1509,">="&DATE(Ano,5,1),'Finanças'!$B$10:$B$1509,"<="&DATE(Ano,5+1,0)) -> 0 | J10: =SUMIFS('Finanças'!$F$10:$F$1509,'Finanças'!$C$10:$C$1509,"Aporte",'Finanças'!$B$10:$B$1509,">="&DATE(Ano,6,1),'Finanças'!$B$10:$B$1509,"<="&DATE(Ano,6+1,0)) -> 0 | K10: =SUMIFS('Finanças'!$F$10:$F$1509,'Finanças'!$C$10:$C$1509,"Aporte",'Finanças'!$B$10:$B$1509,">="&DATE(Ano,7,1),'Finanças'!$B$10:$B$1509,"<="&DATE(Ano,7+1,0)) -> 0 | L10: =SUMIFS('Finanças'!$F$10:$F$1509,'Finanças'!$C$10:$C$1509,"Aporte",'Finanças'!$B$10:$B$1509,">="&DATE(Ano,8,1),'Finanças'!$B$10:$B$1509,"<="&DATE(Ano,8+1,0)) -> 0 | M10: =SUMIFS('Finanças'!$F$10:$F$1509,'Finanças'!$C$10:$C$1509,"Aporte",'Finanças'!$B$10:$B$1509,">="&DATE(Ano,9,1),'Finanças'!$B$10:$B$1509,"<="&DATE(Ano,9+1,0)) -> 0 | N10: =SUMIFS('Finanças'!$F$10:$F$1509,'Finanças'!$C$10:$C$1509,"Aporte",'Finanças'!$B$10:$B$1509,">="&DATE(Ano,10,1),'Finanças'!$B$10:$B$1509,"<="&DATE(Ano,10+1,0)) -> 0 | O10: =SUMIFS('Finanças'!$F$10:$F$1509,'Finanças'!$C$10:$C$1509,"Aporte",'Finanças'!$B$10:$B$1509,">="&DATE(Ano,11,1),'Finanças'!$B$10:$B$1509,"<="&DATE(Ano,11+1,0)) -> 0 | P10: =SUMIFS('Finanças'!$F$10:$F$1509,'Finanças'!$C$10:$C$1509,"Aporte",'Finanças'!$B$10:$B$1509,">="&DATE(Ano,12,1),'Finanças'!$B$10:$B$1509,"<="&DATE(Ano,12+1,0)) -> 0 | Q10: =SUM(E10:P10) -> 0 | R10: =SUMPRODUCT((COLUMN($E10:$P10)-COLUMN($E10)+1<=RefMes)*$E10:$P10)/RefMes -> 0 | S10: =INDEX(E10:P10,RefMes) -> 0
B11: Saldo em caixa (resultado − aportes) | E11: =E9-E10 -> 0 | F11: =F9-F10 -> 0 | G11: =G9-G10 -> 0 | H11: =H9-H10 -> 0 | I11: =I9-I10 -> 0 | J11: =J9-J10 -> 0 | K11: =K9-K10 -> 0 | L11: =L9-L10 -> 0 | ... P11: =P9-P10 -> 0 | Q11: =SUM(E11:P11) -> 0 | R11: =SUMPRODUCT((COLUMN($E11:$P11)-COLUMN($E11)+1<=RefMes)*$E11:$P11)/RefMes -> 0 | S11: =INDEX(E11:P11,RefMes) -> 0
B12: Taxa de poupança | D12: =IF(D7>0,D9/D7,"") | E12: =IF(E7>0,E9/E7,"") | F12: =IF(F7>0,F9/F7,"") | G12: =IF(G7>0,G9/G7,"") | H12: =IF(H7>0,H9/H7,"") | I12: =IF(I7>0,I9/I7,"") | J12: =IF(J7>0,J9/J7,"") | K12: =IF(K7>0,K9/K7,"") | ... R12: =IF(R7>0,R9/R7,"") | S12: =INDEX(E12:P12,RefMes) | U12: =IF(S12="","",IF(S12>=MetaPoup,"✔ Meta de poupança atingida","▲ Abaixo da meta de "&ROUND(MetaPoup*100,0)&"%"))
B13: Orçamento de despesas | E13: =$D$43 -> 0 | F13: =$D$43 -> 0 | G13: =$D$43 -> 0 | H13: =$D$43 -> 0 | I13: =$D$43 -> 0 | J13: =$D$43 -> 0 | K13: =$D$43 -> 0 | L13: =$D$43 -> 0 | ... P13: =$D$43 -> 0 | Q13: =D8*12 -> 0 | S13: =D8 -> 0
B14: Desvio (real − orçado) | E14: =IF(E8=0,"",E8-E13) | F14: =IF(F8=0,"",F8-F13) | G14: =IF(G8=0,"",G8-G13) | H14: =IF(H8=0,"",H8-H13) | I14: =IF(I8=0,"",I8-I13) | J14: =IF(J8=0,"",J8-J13) | K14: =IF(K8=0,"",K8-K13) | L14: =IF(L8=0,"",L8-L13) | ... P14: =IF(P8=0,"",P8-P13) | Q14: =SUM(E14:P14) -> 0 | S14: =INDEX(E14:P14,RefMes)
B16: DESPESAS POR CATEGORIA
B17: Categoria | C17: Grupo | D17: Orçamento / mês | E17: Jan | F17: Fev | G17: Mar | H17: Abr | I17: Mai | J17: Jun | K17: Jul | L17: Ago | M17: Set | N17: Out | O17: Nov | P17: Dez | Q17: Total ano | R17: Média/mês até a ref. | S17: Mês de referência | T17: % do plano | U17: Status no mês
B18: =IF('Config'!$I$6="","",'Config'!$I$6) -> Moradia | C18: =IF(B18="","",'Config'!$J$6&"") -> Essencial | E18: =IF($B18="","",SUMIFS('Finanças'!$F$10:$F$1509,'Finanças'!$C$10:$C$1509,"Despesa",'Finanças'!$D$10:$D$1509,$B18,'Finanças'!$B$10:$B$1509,">="&DATE(Ano,1,1),'Finanças'!$B$10:$B$1509,"<="&DATE(Ano,1+1,0))) -> 0 | F18: =IF($B18="","",SUMIFS('Finanças'!$F$10:$F$1509,'Finanças'!$C$10:$C$1509,"Despesa",'Finanças'!$D$10:$D$1509,$B18,'Finanças'!$B$10:$B$1509,">="&DATE(Ano,2,1),'Finanças'!$B$10:$B$1509,"<="&DATE(Ano,2+1,0))) -> 0 | G18: =IF($B18="","",SUMIFS('Finanças'!$F$10:$F$1509,'Finanças'!$C$10:$C$1509,"Despesa",'Finanças'!$D$10:$D$1509,$B18,'Finanças'!$B$10:$B$1509,">="&DATE(Ano,3,1),'Finanças'!$B$10:$B$1509,"<="&DATE(Ano,3+1,0))) -> 0 | H18: =IF($B18="","",SUMIFS('Finanças'!$F$10:$F$1509,'Finanças'!$C$10:$C$1509,"Despesa",'Finanças'!$D$10:$D$1509,$B18,'Finanças'!$B$10:$B$1509,">="&DATE(Ano,4,1),'Finanças'!$B$10:$B$1509,"<="&DATE(Ano,4+1,0))) -> 0 | I18: =IF($B18="","",SUMIFS('Finanças'!$F$10:$F$1509,'Finanças'!$C$10:$C$1509,"Despesa",'Finanças'!$D$10:$D$1509,$B18,'Finanças'!$B$10:$B$1509,">="&DATE(Ano,5,1),'Finanças'!$B$10:$B$1509,"<="&DATE(Ano,5+1,0))) -> 0 | J18: =IF($B18="","",SUMIFS('Finanças'!$F$10:$F$1509,'Finanças'!$C$10:$C$1509,"Despesa",'Finanças'!$D$10:$D$1509,$B18,'Finanças'!$B$10:$B$1509,">="&DATE(Ano,6,1),'Finanças'!$B$10:$B$1509,"<="&DATE(Ano,6+1,0))) -> 0 | K18: =IF($B18="","",SUMIFS('Finanças'!$F$10:$F$1509,'Finanças'!$C$10:$C$1509,"Despesa",'Finanças'!$D$10:$D$1509,$B18,'Finanças'!$B$10:$B$1509,">="&DATE(Ano,7,1),'Finanças'!$B$10:$B$1509,"<="&DATE(Ano,7+1,0))) -> 0 | L18: =IF($B18="","",SUMIFS('Finanças'!$F$10:$F$1509,'Finanças'!$C$10:$C$1509,"Despesa",'Finanças'!$D$10:$D$1509,$B18,'Finanças'!$B$10:$B$1509,">="&DATE(Ano,8,1),'Finanças'!$B$10:$B$1509,"<="&DATE(Ano,8+1,0))) -> 0 | M18: =IF($B18="","",SUMIFS('Finanças'!$F$10:$F$1509,'Finanças'!$C$10:$C$1509,"Despesa",'Finanças'!$D$10:$D$1509,$B18,'Finanças'!$B$10:$B$1509,">="&DATE(Ano,9,1),'Finanças'!$B$10:$B$1509,"<="&DATE(Ano,9+1,0))) -> 0 | N18: =IF($B18="","",SUMIFS('Finanças'!$F$10:$F$1509,'Finanças'!$C$10:$C$1509,"Despesa",'Finanças'!$D$10:$D$1509,$B18,'Finanças'!$B$10:$B$1509,">="&DATE(Ano,10,1),'Finanças'!$B$10:$B$1509,"<="&DATE(Ano,10+1,0))) -> 0 | O18: =IF($B18="","",SUMIFS('Finanças'!$F$10:$F$1509,'Finanças'!$C$10:$C$1509,"Despesa",'Finanças'!$D$10:$D$1509,$B18,'Finanças'!$B$10:$B$1509,">="&DATE(Ano,11,1),'Finanças'!$B$10:$B$1509,"<="&DATE(Ano,11+1,0))) -> 0 | P18: =IF($B18="","",SUMIFS('Finanças'!$F$10:$F$1509,'Finanças'!$C$10:$C$1509,"Despesa",'Finanças'!$D$10:$D$1509,$B18,'Finanças'!$B$10:$B$1509,">="&DATE(Ano,12,1),'Finanças'!$B$10:$B$1509,"<="&DATE(Ano,12+1,0))) -> 0 | Q18: =IF(B18="","",SUM(E18:P18)) -> 0 | R18: =IF(B18="","",SUMPRODUCT((COLUMN($E18:$P18)-COLUMN($E18)+1<=RefMes)*$E18:$P18)/RefMes) -> 0 | S18: =IF(B18="","",INDEX(E18:P18,RefMes)) -> 0 | T18: =IF(OR(B18="",N(D18)=0),"",S18/D18) | U18: =IF(T18="",IF(AND(B18<>"",N(S18)>0),"○ Sem orçamento",""),IF(T18>1,"✖ Estourou",IF(T18>DiasRef/DiasMes+0.15,"▲ Ritmo alto","✔ OK")))
B19: =IF('Config'!$I$7="","",'Config'!$I$7) -> Contas da casa | C19: =IF(B19="","",'Config'!$J$7&"") -> Essencial | E19: =IF($B19="","",SUMIFS('Finanças'!$F$10:$F$1509,'Finanças'!$C$10:$C$1509,"Despesa",'Finanças'!$D$10:$D$1509,$B19,'Finanças'!$B$10:$B$1509,">="&DATE(Ano,1,1),'Finanças'!$B$10:$B$1509,"<="&DATE(Ano,1+1,0))) -> 0 | F19: =IF($B19="","",SUMIFS('Finanças'!$F$10:$F$1509,'Finanças'!$C$10:$C$1509,"Despesa",'Finanças'!$D$10:$D$1509,$B19,'Finanças'!$B$10:$B$1509,">="&DATE(Ano,2,1),'Finanças'!$B$10:$B$1509,"<="&DATE(Ano,2+1,0))) -> 0 | G19: =IF($B19="","",SUMIFS('Finanças'!$F$10:$F$1509,'Finanças'!$C$10:$C$1509,"Despesa",'Finanças'!$D$10:$D$1509,$B19,'Finanças'!$B$10:$B$1509,">="&DATE(Ano,3,1),'Finanças'!$B$10:$B$1509,"<="&DATE(Ano,3+1,0))) -> 0 | H19: =IF($B19="","",SUMIFS('Finanças'!$F$10:$F$1509,'Finanças'!$C$10:$C$1509,"Despesa",'Finanças'!$D$10:$D$1509,$B19,'Finanças'!$B$10:$B$1509,">="&DATE(Ano,4,1),'Finanças'!$B$10:$B$1509,"<="&DATE(Ano,4+1,0))) -> 0 | I19: =IF($B19="","",SUMIFS('Finanças'!$F$10:$F$1509,'Finanças'!$C$10:$C$1509,"Despesa",'Finanças'!$D$10:$D$1509,$B19,'Finanças'!$B$10:$B$1509,">="&DATE(Ano,5,1),'Finanças'!$B$10:$B$1509,"<="&DATE(Ano,5+1,0))) -> 0 | J19: =IF($B19="","",SUMIFS('Finanças'!$F$10:$F$1509,'Finanças'!$C$10:$C$1509,"Despesa",'Finanças'!$D$10:$D$1509,$B19,'Finanças'!$B$10:$B$1509,">="&DATE(Ano,6,1),'Finanças'!$B$10:$B$1509,"<="&DATE(Ano,6+1,0))) -> 0 | K19: =IF($B19="","",SUMIFS('Finanças'!$F$10:$F$1509,'Finanças'!$C$10:$C$1509,"Despesa",'Finanças'!$D$10:$D$1509,$B19,'Finanças'!$B$10:$B$1509,">="&DATE(Ano,7,1),'Finanças'!$B$10:$B$1509,"<="&DATE(Ano,7+1,0))) -> 0 | L19: =IF($B19="","",SUMIFS('Finanças'!$F$10:$F$1509,'Finanças'!$C$10:$C$1509,"Despesa",'Finanças'!$D$10:$D$1509,$B19,'Finanças'!$B$10:$B$1509,">="&DATE(Ano,8,1),'Finanças'!$B$10:$B$1509,"<="&DATE(Ano,8+1,0))) -> 0 | M19: =IF($B19="","",SUMIFS('Finanças'!$F$10:$F$1509,'Finanças'!$C$10:$C$1509,"Despesa",'Finanças'!$D$10:$D$1509,$B19,'Finanças'!$B$10:$B$1509,">="&DATE(Ano,9,1),'Finanças'!$B$10:$B$1509,"<="&DATE(Ano,9+1,0))) -> 0 | N19: =IF($B19="","",SUMIFS('Finanças'!$F$10:$F$1509,'Finanças'!$C$10:$C$1509,"Despesa",'Finanças'!$D$10:$D$1509,$B19,'Finanças'!$B$10:$B$1509,">="&DATE(Ano,10,1),'Finanças'!$B$10:$B$1509,"<="&DATE(Ano,10+1,0))) -> 0 | O19: =IF($B19="","",SUMIFS('Finanças'!$F$10:$F$1509,'Finanças'!$C$10:$C$1509,"Despesa",'Finanças'!$D$10:$D$1509,$B19,'Finanças'!$B$10:$B$1509,">="&DATE(Ano,11,1),'Finanças'!$B$10:$B$1509,"<="&DATE(Ano,11+1,0))) -> 0 | P19: =IF($B19="","",SUMIFS('Finanças'!$F$10:$F$1509,'Finanças'!$C$10:$C$1509,"Despesa",'Finanças'!$D$10:$D$1509,$B19,'Finanças'!$B$10:$B$1509,">="&DATE(Ano,12,1),'Finanças'!$B$10:$B$1509,"<="&DATE(Ano,12+1,0))) -> 0 | Q19: =IF(B19="","",SUM(E19:P19)) -> 0 | R19: =IF(B19="","",SUMPRODUCT((COLUMN($E19:$P19)-COLUMN($E19)+1<=RefMes)*$E19:$P19)/RefMes) -> 0 | S19: =IF(B19="","",INDEX(E19:P19,RefMes)) -> 0 | T19: =IF(OR(B19="",N(D19)=0),"",S19/D19) | U19: =IF(T19="",IF(AND(B19<>"",N(S19)>0),"○ Sem orçamento",""),IF(T19>1,"✖ Estourou",IF(T19>DiasRef/DiasMes+0.15,"▲ Ritmo alto","✔ OK")))
B20: =IF('Config'!$I$8="","",'Config'!$I$8) -> Mercado | C20: =IF(B20="","",'Config'!$J$8&"") -> Essencial | E20: =IF($B20="","",SUMIFS('Finanças'!$F$10:$F$1509,'Finanças'!$C$10:$C$1509,"Despesa",'Finanças'!$D$10:$D$1509,$B20,'Finanças'!$B$10:$B$1509,">="&DATE(Ano,1,1),'Finanças'!$B$10:$B$1509,"<="&DATE(Ano,1+1,0))) -> 0 | F20: =IF($B20="","",SUMIFS('Finanças'!$F$10:$F$1509,'Finanças'!$C$10:$C$1509,"Despesa",'Finanças'!$D$10:$D$1509,$B20,'Finanças'!$B$10:$B$1509,">="&DATE(Ano,2,1),'Finanças'!$B$10:$B$1509,"<="&DATE(Ano,2+1,0))) -> 0 | G20: =IF($B20="","",SUMIFS('Finanças'!$F$10:$F$1509,'Finanças'!$C$10:$C$1509,"Despesa",'Finanças'!$D$10:$D$1509,$B20,'Finanças'!$B$10:$B$1509,">="&DATE(Ano,3,1),'Finanças'!$B$10:$B$1509,"<="&DATE(Ano,3+1,0))) -> 0 | H20: =IF($B20="","",SUMIFS('Finanças'!$F$10:$F$1509,'Finanças'!$C$10:$C$1509,"Despesa",'Finanças'!$D$10:$D$1509,$B20,'Finanças'!$B$10:$B$1509,">="&DATE(Ano,4,1),'Finanças'!$B$10:$B$1509,"<="&DATE(Ano,4+1,0))) -> 0 | I20: =IF($B20="","",SUMIFS('Finanças'!$F$10:$F$1509,'Finanças'!$C$10:$C$1509,"Despesa",'Finanças'!$D$10:$D$1509,$B20,'Finanças'!$B$10:$B$1509,">="&DATE(Ano,5,1),'Finanças'!$B$10:$B$1509,"<="&DATE(Ano,5+1,0))) -> 0 | J20: =IF($B20="","",SUMIFS('Finanças'!$F$10:$F$1509,'Finanças'!$C$10:$C$1509,"Despesa",'Finanças'!$D$10:$D$1509,$B20,'Finanças'!$B$10:$B$1509,">="&DATE(Ano,6,1),'Finanças'!$B$10:$B$1509,"<="&DATE(Ano,6+1,0))) -> 0 | K20: =IF($B20="","",SUMIFS('Finanças'!$F$10:$F$1509,'Finanças'!$C$10:$C$1509,"Despesa",'Finanças'!$D$10:$D$1509,$B20,'Finanças'!$B$10:$B$1509,">="&DATE(Ano,7,1),'Finanças'!$B$10:$B$1509,"<="&DATE(Ano,7+1,0))) -> 0 | L20: =IF($B20="","",SUMIFS('Finanças'!$F$10:$F$1509,'Finanças'!$C$10:$C$1509,"Despesa",'Finanças'!$D$10:$D$1509,$B20,'Finanças'!$B$10:$B$1509,">="&DATE(Ano,8,1),'Finanças'!$B$10:$B$1509,"<="&DATE(Ano,8+1,0))) -> 0 | M20: =IF($B20="","",SUMIFS('Finanças'!$F$10:$F$1509,'Finanças'!$C$10:$C$1509,"Despesa",'Finanças'!$D$10:$D$1509,$B20,'Finanças'!$B$10:$B$1509,">="&DATE(Ano,9,1),'Finanças'!$B$10:$B$1509,"<="&DATE(Ano,9+1,0))) -> 0 | N20: =IF($B20="","",SUMIFS('Finanças'!$F$10:$F$1509,'Finanças'!$C$10:$C$1509,"Despesa",'Finanças'!$D$10:$D$1509,$B20,'Finanças'!$B$10:$B$1509,">="&DATE(Ano,10,1),'Finanças'!$B$10:$B$1509,"<="&DATE(Ano,10+1,0))) -> 0 | O20: =IF($B20="","",SUMIFS('Finanças'!$F$10:$F$1509,'Finanças'!$C$10:$C$1509,"Despesa",'Finanças'!$D$10:$D$1509,$B20,'Finanças'!$B$10:$B$1509,">="&DATE(Ano,11,1),'Finanças'!$B$10:$B$1509,"<="&DATE(Ano,11+1,0))) -> 0 | P20: =IF($B20="","",SUMIFS('Finanças'!$F$10:$F$1509,'Finanças'!$C$10:$C$1509,"Despesa",'Finanças'!$D$10:$D$1509,$B20,'Finanças'!$B$10:$B$1509,">="&DATE(Ano,12,1),'Finanças'!$B$10:$B$1509,"<="&DATE(Ano,12+1,0))) -> 0 | Q20: =IF(B20="","",SUM(E20:P20)) -> 0 | R20: =IF(B20="","",SUMPRODUCT((COLUMN($E20:$P20)-COLUMN($E20)+1<=RefMes)*$E20:$P20)/RefMes) -> 0 | S20: =IF(B20="","",INDEX(E20:P20,RefMes)) -> 0 | T20: =IF(OR(B20="",N(D20)=0),"",S20/D20) | U20: =IF(T20="",IF(AND(B20<>"",N(S20)>0),"○ Sem orçamento",""),IF(T20>1,"✖ Estourou",IF(T20>DiasRef/DiasMes+0.15,"▲ Ritmo alto","✔ OK")))
B21: =IF('Config'!$I$9="","",'Config'!$I$9) -> Transporte | C21: =IF(B21="","",'Config'!$J$9&"") -> Essencial | E21: =IF($B21="","",SUMIFS('Finanças'!$F$10:$F$1509,'Finanças'!$C$10:$C$1509,"Despesa",'Finanças'!$D$10:$D$1509,$B21,'Finanças'!$B$10:$B$1509,">="&DATE(Ano,1,1),'Finanças'!$B$10:$B$1509,"<="&DATE(Ano,1+1,0))) -> 0 | F21: =IF($B21="","",SUMIFS('Finanças'!$F$10:$F$1509,'Finanças'!$C$10:$C$1509,"Despesa",'Finanças'!$D$10:$D$1509,$B21,'Finanças'!$B$10:$B$1509,">="&DATE(Ano,2,1),'Finanças'!$B$10:$B$1509,"<="&DATE(Ano,2+1,0))) -> 0 | G21: =IF($B21="","",SUMIFS('Finanças'!$F$10:$F$1509,'Finanças'!$C$10:$C$1509,"Despesa",'Finanças'!$D$10:$D$1509,$B21,'Finanças'!$B$10:$B$1509,">="&DATE(Ano,3,1),'Finanças'!$B$10:$B$1509,"<="&DATE(Ano,3+1,0))) -> 0 | H21: =IF($B21="","",SUMIFS('Finanças'!$F$10:$F$1509,'Finanças'!$C$10:$C$1509,"Despesa",'Finanças'!$D$10:$D$1509,$B21,'Finanças'!$B$10:$B$1509,">="&DATE(Ano,4,1),'Finanças'!$B$10:$B$1509,"<="&DATE(Ano,4+1,0))) -> 0 | I21: =IF($B21="","",SUMIFS('Finanças'!$F$10:$F$1509,'Finanças'!$C$10:$C$1509,"Despesa",'Finanças'!$D$10:$D$1509,$B21,'Finanças'!$B$10:$B$1509,">="&DATE(Ano,5,1),'Finanças'!$B$10:$B$1509,"<="&DATE(Ano,5+1,0))) -> 0 | J21: =IF($B21="","",SUMIFS('Finanças'!$F$10:$F$1509,'Finanças'!$C$10:$C$1509,"Despesa",'Finanças'!$D$10:$D$1509,$B21,'Finanças'!$B$10:$B$1509,">="&DATE(Ano,6,1),'Finanças'!$B$10:$B$1509,"<="&DATE(Ano,6+1,0))) -> 0 | K21: =IF($B21="","",SUMIFS('Finanças'!$F$10:$F$1509,'Finanças'!$C$10:$C$1509,"Despesa",'Finanças'!$D$10:$D$1509,$B21,'Finanças'!$B$10:$B$1509,">="&DATE(Ano,7,1),'Finanças'!$B$10:$B$1509,"<="&DATE(Ano,7+1,0))) -> 0 | L21: =IF($B21="","",SUMIFS('Finanças'!$F$10:$F$1509,'Finanças'!$C$10:$C$1509,"Despesa",'Finanças'!$D$10:$D$1509,$B21,'Finanças'!$B$10:$B$1509,">="&DATE(Ano,8,1),'Finanças'!$B$10:$B$1509,"<="&DATE(Ano,8+1,0))) -> 0 | M21: =IF($B21="","",SUMIFS('Finanças'!$F$10:$F$1509,'Finanças'!$C$10:$C$1509,"Despesa",'Finanças'!$D$10:$D$1509,$B21,'Finanças'!$B$10:$B$1509,">="&DATE(Ano,9,1),'Finanças'!$B$10:$B$1509,"<="&DATE(Ano,9+1,0))) -> 0 | N21: =IF($B21="","",SUMIFS('Finanças'!$F$10:$F$1509,'Finanças'!$C$10:$C$1509,"Despesa",'Finanças'!$D$10:$D$1509,$B21,'Finanças'!$B$10:$B$1509,">="&DATE(Ano,10,1),'Finanças'!$B$10:$B$1509,"<="&DATE(Ano,10+1,0))) -> 0 | O21: =IF($B21="","",SUMIFS('Finanças'!$F$10:$F$1509,'Finanças'!$C$10:$C$1509,"Despesa",'Finanças'!$D$10:$D$1509,$B21,'Finanças'!$B$10:$B$1509,">="&DATE(Ano,11,1),'Finanças'!$B$10:$B$1509,"<="&DATE(Ano,11+1,0))) -> 0 | P21: =IF($B21="","",SUMIFS('Finanças'!$F$10:$F$1509,'Finanças'!$C$10:$C$1509,"Despesa",'Finanças'!$D$10:$D$1509,$B21,'Finanças'!$B$10:$B$1509,">="&DATE(Ano,12,1),'Finanças'!$B$10:$B$1509,"<="&DATE(Ano,12+1,0))) -> 0 | Q21: =IF(B21="","",SUM(E21:P21)) -> 0 | R21: =IF(B21="","",SUMPRODUCT((COLUMN($E21:$P21)-COLUMN($E21)+1<=RefMes)*$E21:$P21)/RefMes) -> 0 | S21: =IF(B21="","",INDEX(E21:P21,RefMes)) -> 0 | T21: =IF(OR(B21="",N(D21)=0),"",S21/D21) | U21: =IF(T21="",IF(AND(B21<>"",N(S21)>0),"○ Sem orçamento",""),IF(T21>1,"✖ Estourou",IF(T21>DiasRef/DiasMes+0.15,"▲ Ritmo alto","✔ OK")))
B22: =IF('Config'!$I$10="","",'Config'!$I$10) -> Saúde & bem-estar | C22: =IF(B22="","",'Config'!$J$10&"") -> Essencial | E22: =IF($B22="","",SUMIFS('Finanças'!$F$10:$F$1509,'Finanças'!$C$10:$C$1509,"Despesa",'Finanças'!$D$10:$D$1509,$B22,'Finanças'!$B$10:$B$1509,">="&DATE(Ano,1,1),'Finanças'!$B$10:$B$1509,"<="&DATE(Ano,1+1,0))) -> 0 | F22: =IF($B22="","",SUMIFS('Finanças'!$F$10:$F$1509,'Finanças'!$C$10:$C$1509,"Despesa",'Finanças'!$D$10:$D$1509,$B22,'Finanças'!$B$10:$B$1509,">="&DATE(Ano,2,1),'Finanças'!$B$10:$B$1509,"<="&DATE(Ano,2+1,0))) -> 0 | G22: =IF($B22="","",SUMIFS('Finanças'!$F$10:$F$1509,'Finanças'!$C$10:$C$1509,"Despesa",'Finanças'!$D$10:$D$1509,$B22,'Finanças'!$B$10:$B$1509,">="&DATE(Ano,3,1),'Finanças'!$B$10:$B$1509,"<="&DATE(Ano,3+1,0))) -> 0 | H22: =IF($B22="","",SUMIFS('Finanças'!$F$10:$F$1509,'Finanças'!$C$10:$C$1509,"Despesa",'Finanças'!$D$10:$D$1509,$B22,'Finanças'!$B$10:$B$1509,">="&DATE(Ano,4,1),'Finanças'!$B$10:$B$1509,"<="&DATE(Ano,4+1,0))) -> 0 | I22: =IF($B22="","",SUMIFS('Finanças'!$F$10:$F$1509,'Finanças'!$C$10:$C$1509,"Despesa",'Finanças'!$D$10:$D$1509,$B22,'Finanças'!$B$10:$B$1509,">="&DATE(Ano,5,1),'Finanças'!$B$10:$B$1509,"<="&DATE(Ano,5+1,0))) -> 0 | J22: =IF($B22="","",SUMIFS('Finanças'!$F$10:$F$1509,'Finanças'!$C$10:$C$1509,"Despesa",'Finanças'!$D$10:$D$1509,$B22,'Finanças'!$B$10:$B$1509,">="&DATE(Ano,6,1),'Finanças'!$B$10:$B$1509,"<="&DATE(Ano,6+1,0))) -> 0 | K22: =IF($B22="","",SUMIFS('Finanças'!$F$10:$F$1509,'Finanças'!$C$10:$C$1509,"Despesa",'Finanças'!$D$10:$D$1509,$B22,'Finanças'!$B$10:$B$1509,">="&DATE(Ano,7,1),'Finanças'!$B$10:$B$1509,"<="&DATE(Ano,7+1,0))) -> 0 | L22: =IF($B22="","",SUMIFS('Finanças'!$F$10:$F$1509,'Finanças'!$C$10:$C$1509,"Despesa",'Finanças'!$D$10:$D$1509,$B22,'Finanças'!$B$10:$B$1509,">="&DATE(Ano,8,1),'Finanças'!$B$10:$B$1509,"<="&DATE(Ano,8+1,0))) -> 0 | M22: =IF($B22="","",SUMIFS('Finanças'!$F$10:$F$1509,'Finanças'!$C$10:$C$1509,"Despesa",'Finanças'!$D$10:$D$1509,$B22,'Finanças'!$B$10:$B$1509,">="&DATE(Ano,9,1),'Finanças'!$B$10:$B$1509,"<="&DATE(Ano,9+1,0))) -> 0 | N22: =IF($B22="","",SUMIFS('Finanças'!$F$10:$F$1509,'Finanças'!$C$10:$C$1509,"Despesa",'Finanças'!$D$10:$D$1509,$B22,'Finanças'!$B$10:$B$1509,">="&DATE(Ano,10,1),'Finanças'!$B$10:$B$1509,"<="&DATE(Ano,10+1,0))) -> 0 | O22: =IF($B22="","",SUMIFS('Finanças'!$F$10:$F$1509,'Finanças'!$C$10:$C$1509,"Despesa",'Finanças'!$D$10:$D$1509,$B22,'Finanças'!$B$10:$B$1509,">="&DATE(Ano,11,1),'Finanças'!$B$10:$B$1509,"<="&DATE(Ano,11+1,0))) -> 0 | P22: =IF($B22="","",SUMIFS('Finanças'!$F$10:$F$1509,'Finanças'!$C$10:$C$1509,"Despesa",'Finanças'!$D$10:$D$1509,$B22,'Finanças'!$B$10:$B$1509,">="&DATE(Ano,12,1),'Finanças'!$B$10:$B$1509,"<="&DATE(Ano,12+1,0))) -> 0 | Q22: =IF(B22="","",SUM(E22:P22)) -> 0 | R22: =IF(B22="","",SUMPRODUCT((COLUMN($E22:$P22)-COLUMN($E22)+1<=RefMes)*$E22:$P22)/RefMes) -> 0 | S22: =IF(B22="","",INDEX(E22:P22,RefMes)) -> 0 | T22: =IF(OR(B22="",N(D22)=0),"",S22/D22) | U22: =IF(T22="",IF(AND(B22<>"",N(S22)>0),"○ Sem orçamento",""),IF(T22>1,"✖ Estourou",IF(T22>DiasRef/DiasMes+0.15,"▲ Ritmo alto","✔ OK")))
B23: =IF('Config'!$I$11="","",'Config'!$I$11) -> Dívidas & financiamentos | C23: =IF(B23="","",'Config'!$J$11&"") -> Essencial | E23: =IF($B23="","",SUMIFS('Finanças'!$F$10:$F$1509,'Finanças'!$C$10:$C$1509,"Despesa",'Finanças'!$D$10:$D$1509,$B23,'Finanças'!$B$10:$B$1509,">="&DATE(Ano,1,1),'Finanças'!$B$10:$B$1509,"<="&DATE(Ano,1+1,0))) -> 0 | F23: =IF($B23="","",SUMIFS('Finanças'!$F$10:$F$1509,'Finanças'!$C$10:$C$1509,"Despesa",'Finanças'!$D$10:$D$1509,$B23,'Finanças'!$B$10:$B$1509,">="&DATE(Ano,2,1),'Finanças'!$B$10:$B$1509,"<="&DATE(Ano,2+1,0))) -> 0 | G23: =IF($B23="","",SUMIFS('Finanças'!$F$10:$F$1509,'Finanças'!$C$10:$C$1509,"Despesa",'Finanças'!$D$10:$D$1509,$B23,'Finanças'!$B$10:$B$1509,">="&DATE(Ano,3,1),'Finanças'!$B$10:$B$1509,"<="&DATE(Ano,3+1,0))) -> 0 | H23: =IF($B23="","",SUMIFS('Finanças'!$F$10:$F$1509,'Finanças'!$C$10:$C$1509,"Despesa",'Finanças'!$D$10:$D$1509,$B23,'Finanças'!$B$10:$B$1509,">="&DATE(Ano,4,1),'Finanças'!$B$10:$B$1509,"<="&DATE(Ano,4+1,0))) -> 0 | I23: =IF($B23="","",SUMIFS('Finanças'!$F$10:$F$1509,'Finanças'!$C$10:$C$1509,"Despesa",'Finanças'!$D$10:$D$1509,$B23,'Finanças'!$B$10:$B$1509,">="&DATE(Ano,5,1),'Finanças'!$B$10:$B$1509,"<="&DATE(Ano,5+1,0))) -> 0 | J23: =IF($B23="","",SUMIFS('Finanças'!$F$10:$F$1509,'Finanças'!$C$10:$C$1509,"Despesa",'Finanças'!$D$10:$D$1509,$B23,'Finanças'!$B$10:$B$1509,">="&DATE(Ano,6,1),'Finanças'!$B$10:$B$1509,"<="&DATE(Ano,6+1,0))) -> 0 | K23: =IF($B23="","",SUMIFS('Finanças'!$F$10:$F$1509,'Finanças'!$C$10:$C$1509,"Despesa",'Finanças'!$D$10:$D$1509,$B23,'Finanças'!$B$10:$B$1509,">="&DATE(Ano,7,1),'Finanças'!$B$10:$B$1509,"<="&DATE(Ano,7+1,0))) -> 0 | L23: =IF($B23="","",SUMIFS('Finanças'!$F$10:$F$1509,'Finanças'!$C$10:$C$1509,"Despesa",'Finanças'!$D$10:$D$1509,$B23,'Finanças'!$B$10:$B$1509,">="&DATE(Ano,8,1),'Finanças'!$B$10:$B$1509,"<="&DATE(Ano,8+1,0))) -> 0 | M23: =IF($B23="","",SUMIFS('Finanças'!$F$10:$F$1509,'Finanças'!$C$10:$C$1509,"Despesa",'Finanças'!$D$10:$D$1509,$B23,'Finanças'!$B$10:$B$1509,">="&DATE(Ano,9,1),'Finanças'!$B$10:$B$1509,"<="&DATE(Ano,9+1,0))) -> 0 | N23: =IF($B23="","",SUMIFS('Finanças'!$F$10:$F$1509,'Finanças'!$C$10:$C$1509,"Despesa",'Finanças'!$D$10:$D$1509,$B23,'Finanças'!$B$10:$B$1509,">="&DATE(Ano,10,1),'Finanças'!$B$10:$B$1509,"<="&DATE(Ano,10+1,0))) -> 0 | O23: =IF($B23="","",SUMIFS('Finanças'!$F$10:$F$1509,'Finanças'!$C$10:$C$1509,"Despesa",'Finanças'!$D$10:$D$1509,$B23,'Finanças'!$B$10:$B$1509,">="&DATE(Ano,11,1),'Finanças'!$B$10:$B$1509,"<="&DATE(Ano,11+1,0))) -> 0 | P23: =IF($B23="","",SUMIFS('Finanças'!$F$10:$F$1509,'Finanças'!$C$10:$C$1509,"Despesa",'Finanças'!$D$10:$D$1509,$B23,'Finanças'!$B$10:$B$1509,">="&DATE(Ano,12,1),'Finanças'!$B$10:$B$1509,"<="&DATE(Ano,12+1,0))) -> 0 | Q23: =IF(B23="","",SUM(E23:P23)) -> 0 | R23: =IF(B23="","",SUMPRODUCT((COLUMN($E23:$P23)-COLUMN($E23)+1<=RefMes)*$E23:$P23)/RefMes) -> 0 | S23: =IF(B23="","",INDEX(E23:P23,RefMes)) -> 0 | T23: =IF(OR(B23="",N(D23)=0),"",S23/D23) | U23: =IF(T23="",IF(AND(B23<>"",N(S23)>0),"○ Sem orçamento",""),IF(T23>1,"✖ Estourou",IF(T23>DiasRef/DiasMes+0.15,"▲ Ritmo alto","✔ OK")))
B24: =IF('Config'!$I$12="","",'Config'!$I$12) -> Impostos & taxas | C24: =IF(B24="","",'Config'!$J$12&"") -> Essencial | E24: =IF($B24="","",SUMIFS('Finanças'!$F$10:$F$1509,'Finanças'!$C$10:$C$1509,"Despesa",'Finanças'!$D$10:$D$1509,$B24,'Finanças'!$B$10:$B$1509,">="&DATE(Ano,1,1),'Finanças'!$B$10:$B$1509,"<="&DATE(Ano,1+1,0))) -> 0 | F24: =IF($B24="","",SUMIFS('Finanças'!$F$10:$F$1509,'Finanças'!$C$10:$C$1509,"Despesa",'Finanças'!$D$10:$D$1509,$B24,'Finanças'!$B$10:$B$1509,">="&DATE(Ano,2,1),'Finanças'!$B$10:$B$1509,"<="&DATE(Ano,2+1,0))) -> 0 | G24: =IF($B24="","",SUMIFS('Finanças'!$F$10:$F$1509,'Finanças'!$C$10:$C$1509,"Despesa",'Finanças'!$D$10:$D$1509,$B24,'Finanças'!$B$10:$B$1509,">="&DATE(Ano,3,1),'Finanças'!$B$10:$B$1509,"<="&DATE(Ano,3+1,0))) -> 0 | H24: =IF($B24="","",SUMIFS('Finanças'!$F$10:$F$1509,'Finanças'!$C$10:$C$1509,"Despesa",'Finanças'!$D$10:$D$1509,$B24,'Finanças'!$B$10:$B$1509,">="&DATE(Ano,4,1),'Finanças'!$B$10:$B$1509,"<="&DATE(Ano,4+1,0))) -> 0 | I24: =IF($B24="","",SUMIFS('Finanças'!$F$10:$F$1509,'Finanças'!$C$10:$C$1509,"Despesa",'Finanças'!$D$10:$D$1509,$B24,'Finanças'!$B$10:$B$1509,">="&DATE(Ano,5,1),'Finanças'!$B$10:$B$1509,"<="&DATE(Ano,5+1,0))) -> 0 | J24: =IF($B24="","",SUMIFS('Finanças'!$F$10:$F$1509,'Finanças'!$C$10:$C$1509,"Despesa",'Finanças'!$D$10:$D$1509,$B24,'Finanças'!$B$10:$B$1509,">="&DATE(Ano,6,1),'Finanças'!$B$10:$B$1509,"<="&DATE(Ano,6+1,0))) -> 0 | K24: =IF($B24="","",SUMIFS('Finanças'!$F$10:$F$1509,'Finanças'!$C$10:$C$1509,"Despesa",'Finanças'!$D$10:$D$1509,$B24,'Finanças'!$B$10:$B$1509,">="&DATE(Ano,7,1),'Finanças'!$B$10:$B$1509,"<="&DATE(Ano,7+1,0))) -> 0 | L24: =IF($B24="","",SUMIFS('Finanças'!$F$10:$F$1509,'Finanças'!$C$10:$C$1509,"Despesa",'Finanças'!$D$10:$D$1509,$B24,'Finanças'!$B$10:$B$1509,">="&DATE(Ano,8,1),'Finanças'!$B$10:$B$1509,"<="&DATE(Ano,8+1,0))) -> 0 | M24: =IF($B24="","",SUMIFS('Finanças'!$F$10:$F$1509,'Finanças'!$C$10:$C$1509,"Despesa",'Finanças'!$D$10:$D$1509,$B24,'Finanças'!$B$10:$B$1509,">="&DATE(Ano,9,1),'Finanças'!$B$10:$B$1509,"<="&DATE(Ano,9+1,0))) -> 0 | N24: =IF($B24="","",SUMIFS('Finanças'!$F$10:$F$1509,'Finanças'!$C$10:$C$1509,"Despesa",'Finanças'!$D$10:$D$1509,$B24,'Finanças'!$B$10:$B$1509,">="&DATE(Ano,10,1),'Finanças'!$B$10:$B$1509,"<="&DATE(Ano,10+1,0))) -> 0 | O24: =IF($B24="","",SUMIFS('Finanças'!$F$10:$F$1509,'Finanças'!$C$10:$C$1509,"Despesa",'Finanças'!$D$10:$D$1509,$B24,'Finanças'!$B$10:$B$1509,">="&DATE(Ano,11,1),'Finanças'!$B$10:$B$1509,"<="&DATE(Ano,11+1,0))) -> 0 | P24: =IF($B24="","",SUMIFS('Finanças'!$F$10:$F$1509,'Finanças'!$C$10:$C$1509,"Despesa",'Finanças'!$D$10:$D$1509,$B24,'Finanças'!$B$10:$B$1509,">="&DATE(Ano,12,1),'Finanças'!$B$10:$B$1509,"<="&DATE(Ano,12+1,0))) -> 0 | Q24: =IF(B24="","",SUM(E24:P24)) -> 0 | R24: =IF(B24="","",SUMPRODUCT((COLUMN($E24:$P24)-COLUMN($E24)+1<=RefMes)*$E24:$P24)/RefMes) -> 0 | S24: =IF(B24="","",INDEX(E24:P24,RefMes)) -> 0 | T24: =IF(OR(B24="",N(D24)=0),"",S24/D24) | U24: =IF(T24="",IF(AND(B24<>"",N(S24)>0),"○ Sem orçamento",""),IF(T24>1,"✖ Estourou",IF(T24>DiasRef/DiasMes+0.15,"▲ Ritmo alto","✔ OK")))
B25: =IF('Config'!$I$13="","",'Config'!$I$13) -> Família & ajudas | C25: =IF(B25="","",'Config'!$J$13&"") -> Essencial | E25: =IF($B25="","",SUMIFS('Finanças'!$F$10:$F$1509,'Finanças'!$C$10:$C$1509,"Despesa",'Finanças'!$D$10:$D$1509,$B25,'Finanças'!$B$10:$B$1509,">="&DATE(Ano,1,1),'Finanças'!$B$10:$B$1509,"<="&DATE(Ano,1+1,0))) -> 0 | F25: =IF($B25="","",SUMIFS('Finanças'!$F$10:$F$1509,'Finanças'!$C$10:$C$1509,"Despesa",'Finanças'!$D$10:$D$1509,$B25,'Finanças'!$B$10:$B$1509,">="&DATE(Ano,2,1),'Finanças'!$B$10:$B$1509,"<="&DATE(Ano,2+1,0))) -> 0 | G25: =IF($B25="","",SUMIFS('Finanças'!$F$10:$F$1509,'Finanças'!$C$10:$C$1509,"Despesa",'Finanças'!$D$10:$D$1509,$B25,'Finanças'!$B$10:$B$1509,">="&DATE(Ano,3,1),'Finanças'!$B$10:$B$1509,"<="&DATE(Ano,3+1,0))) -> 0 | H25: =IF($B25="","",SUMIFS('Finanças'!$F$10:$F$1509,'Finanças'!$C$10:$C$1509,"Despesa",'Finanças'!$D$10:$D$1509,$B25,'Finanças'!$B$10:$B$1509,">="&DATE(Ano,4,1),'Finanças'!$B$10:$B$1509,"<="&DATE(Ano,4+1,0))) -> 0 | I25: =IF($B25="","",SUMIFS('Finanças'!$F$10:$F$1509,'Finanças'!$C$10:$C$1509,"Despesa",'Finanças'!$D$10:$D$1509,$B25,'Finanças'!$B$10:$B$1509,">="&DATE(Ano,5,1),'Finanças'!$B$10:$B$1509,"<="&DATE(Ano,5+1,0))) -> 0 | J25: =IF($B25="","",SUMIFS('Finanças'!$F$10:$F$1509,'Finanças'!$C$10:$C$1509,"Despesa",'Finanças'!$D$10:$D$1509,$B25,'Finanças'!$B$10:$B$1509,">="&DATE(Ano,6,1),'Finanças'!$B$10:$B$1509,"<="&DATE(Ano,6+1,0))) -> 0 | K25: =IF($B25="","",SUMIFS('Finanças'!$F$10:$F$1509,'Finanças'!$C$10:$C$1509,"Despesa",'Finanças'!$D$10:$D$1509,$B25,'Finanças'!$B$10:$B$1509,">="&DATE(Ano,7,1),'Finanças'!$B$10:$B$1509,"<="&DATE(Ano,7+1,0))) -> 0 | L25: =IF($B25="","",SUMIFS('Finanças'!$F$10:$F$1509,'Finanças'!$C$10:$C$1509,"Despesa",'Finanças'!$D$10:$D$1509,$B25,'Finanças'!$B$10:$B$1509,">="&DATE(Ano,8,1),'Finanças'!$B$10:$B$1509,"<="&DATE(Ano,8+1,0))) -> 0 | M25: =IF($B25="","",SUMIFS('Finanças'!$F$10:$F$1509,'Finanças'!$C$10:$C$1509,"Despesa",'Finanças'!$D$10:$D$1509,$B25,'Finanças'!$B$10:$B$1509,">="&DATE(Ano,9,1),'Finanças'!$B$10:$B$1509,"<="&DATE(Ano,9+1,0))) -> 0 | N25: =IF($B25="","",SUMIFS('Finanças'!$F$10:$F$1509,'Finanças'!$C$10:$C$1509,"Despesa",'Finanças'!$D$10:$D$1509,$B25,'Finanças'!$B$10:$B$1509,">="&DATE(Ano,10,1),'Finanças'!$B$10:$B$1509,"<="&DATE(Ano,10+1,0))) -> 0 | O25: =IF($B25="","",SUMIFS('Finanças'!$F$10:$F$1509,'Finanças'!$C$10:$C$1509,"Despesa",'Finanças'!$D$10:$D$1509,$B25,'Finanças'!$B$10:$B$1509,">="&DATE(Ano,11,1),'Finanças'!$B$10:$B$1509,"<="&DATE(Ano,11+1,0))) -> 0 | P25: =IF($B25="","",SUMIFS('Finanças'!$F$10:$F$1509,'Finanças'!$C$10:$C$1509,"Despesa",'Finanças'!$D$10:$D$1509,$B25,'Finanças'!$B$10:$B$1509,">="&DATE(Ano,12,1),'Finanças'!$B$10:$B$1509,"<="&DATE(Ano,12+1,0))) -> 0 | Q25: =IF(B25="","",SUM(E25:P25)) -> 0 | R25: =IF(B25="","",SUMPRODUCT((COLUMN($E25:$P25)-COLUMN($E25)+1<=RefMes)*$E25:$P25)/RefMes) -> 0 | S25: =IF(B25="","",INDEX(E25:P25,RefMes)) -> 0 | T25: =IF(OR(B25="",N(D25)=0),"",S25/D25) | U25: =IF(T25="",IF(AND(B25<>"",N(S25)>0),"○ Sem orçamento",""),IF(T25>1,"✖ Estourou",IF(T25>DiasRef/DiasMes+0.15,"▲ Ritmo alto","✔ OK")))
B26: =IF('Config'!$I$14="","",'Config'!$I$14) -> Restaurantes & cafés | C26: =IF(B26="","",'Config'!$J$14&"") -> Estilo de vida | E26: =IF($B26="","",SUMIFS('Finanças'!$F$10:$F$1509,'Finanças'!$C$10:$C$1509,"Despesa",'Finanças'!$D$10:$D$1509,$B26,'Finanças'!$B$10:$B$1509,">="&DATE(Ano,1,1),'Finanças'!$B$10:$B$1509,"<="&DATE(Ano,1+1,0))) -> 0 | F26: =IF($B26="","",SUMIFS('Finanças'!$F$10:$F$1509,'Finanças'!$C$10:$C$1509,"Despesa",'Finanças'!$D$10:$D$1509,$B26,'Finanças'!$B$10:$B$1509,">="&DATE(Ano,2,1),'Finanças'!$B$10:$B$1509,"<="&DATE(Ano,2+1,0))) -> 0 | G26: =IF($B26="","",SUMIFS('Finanças'!$F$10:$F$1509,'Finanças'!$C$10:$C$1509,"Despesa",'Finanças'!$D$10:$D$1509,$B26,'Finanças'!$B$10:$B$1509,">="&DATE(Ano,3,1),'Finanças'!$B$10:$B$1509,"<="&DATE(Ano,3+1,0))) -> 0 | H26: =IF($B26="","",SUMIFS('Finanças'!$F$10:$F$1509,'Finanças'!$C$10:$C$1509,"Despesa",'Finanças'!$D$10:$D$1509,$B26,'Finanças'!$B$10:$B$1509,">="&DATE(Ano,4,1),'Finanças'!$B$10:$B$1509,"<="&DATE(Ano,4+1,0))) -> 0 | I26: =IF($B26="","",SUMIFS('Finanças'!$F$10:$F$1509,'Finanças'!$C$10:$C$1509,"Despesa",'Finanças'!$D$10:$D$1509,$B26,'Finanças'!$B$10:$B$1509,">="&DATE(Ano,5,1),'Finanças'!$B$10:$B$1509,"<="&DATE(Ano,5+1,0))) -> 0 | J26: =IF($B26="","",SUMIFS('Finanças'!$F$10:$F$1509,'Finanças'!$C$10:$C$1509,"Despesa",'Finanças'!$D$10:$D$1509,$B26,'Finanças'!$B$10:$B$1509,">="&DATE(Ano,6,1),'Finanças'!$B$10:$B$1509,"<="&DATE(Ano,6+1,0))) -> 0 | K26: =IF($B26="","",SUMIFS('Finanças'!$F$10:$F$1509,'Finanças'!$C$10:$C$1509,"Despesa",'Finanças'!$D$10:$D$1509,$B26,'Finanças'!$B$10:$B$1509,">="&DATE(Ano,7,1),'Finanças'!$B$10:$B$1509,"<="&DATE(Ano,7+1,0))) -> 0 | L26: =IF($B26="","",SUMIFS('Finanças'!$F$10:$F$1509,'Finanças'!$C$10:$C$1509,"Despesa",'Finanças'!$D$10:$D$1509,$B26,'Finanças'!$B$10:$B$1509,">="&DATE(Ano,8,1),'Finanças'!$B$10:$B$1509,"<="&DATE(Ano,8+1,0))) -> 0 | M26: =IF($B26="","",SUMIFS('Finanças'!$F$10:$F$1509,'Finanças'!$C$10:$C$1509,"Despesa",'Finanças'!$D$10:$D$1509,$B26,'Finanças'!$B$10:$B$1509,">="&DATE(Ano,9,1),'Finanças'!$B$10:$B$1509,"<="&DATE(Ano,9+1,0))) -> 0 | N26: =IF($B26="","",SUMIFS('Finanças'!$F$10:$F$1509,'Finanças'!$C$10:$C$1509,"Despesa",'Finanças'!$D$10:$D$1509,$B26,'Finanças'!$B$10:$B$1509,">="&DATE(Ano,10,1),'Finanças'!$B$10:$B$1509,"<="&DATE(Ano,10+1,0))) -> 0 | O26: =IF($B26="","",SUMIFS('Finanças'!$F$10:$F$1509,'Finanças'!$C$10:$C$1509,"Despesa",'Finanças'!$D$10:$D$1509,$B26,'Finanças'!$B$10:$B$1509,">="&DATE(Ano,11,1),'Finanças'!$B$10:$B$1509,"<="&DATE(Ano,11+1,0))) -> 0 | P26: =IF($B26="","",SUMIFS('Finanças'!$F$10:$F$1509,'Finanças'!$C$10:$C$1509,"Despesa",'Finanças'!$D$10:$D$1509,$B26,'Finanças'!$B$10:$B$1509,">="&DATE(Ano,12,1),'Finanças'!$B$10:$B$1509,"<="&DATE(Ano,12+1,0))) -> 0 | Q26: =IF(B26="","",SUM(E26:P26)) -> 0 | R26: =IF(B26="","",SUMPRODUCT((COLUMN($E26:$P26)-COLUMN($E26)+1<=RefMes)*$E26:$P26)/RefMes) -> 0 | S26: =IF(B26="","",INDEX(E26:P26,RefMes)) -> 0 | T26: =IF(OR(B26="",N(D26)=0),"",S26/D26) | U26: =IF(T26="",IF(AND(B26<>"",N(S26)>0),"○ Sem orçamento",""),IF(T26>1,"✖ Estourou",IF(T26>DiasRef/DiasMes+0.15,"▲ Ritmo alto","✔ OK")))
B27: =IF('Config'!$I$15="","",'Config'!$I$15) -> Assinaturas | C27: =IF(B27="","",'Config'!$J$15&"") -> Estilo de vida | E27: =IF($B27="","",SUMIFS('Finanças'!$F$10:$F$1509,'Finanças'!$C$10:$C$1509,"Despesa",'Finanças'!$D$10:$D$1509,$B27,'Finanças'!$B$10:$B$1509,">="&DATE(Ano,1,1),'Finanças'!$B$10:$B$1509,"<="&DATE(Ano,1+1,0))) -> 0 | F27: =IF($B27="","",SUMIFS('Finanças'!$F$10:$F$1509,'Finanças'!$C$10:$C$1509,"Despesa",'Finanças'!$D$10:$D$1509,$B27,'Finanças'!$B$10:$B$1509,">="&DATE(Ano,2,1),'Finanças'!$B$10:$B$1509,"<="&DATE(Ano,2+1,0))) -> 0 | G27: =IF($B27="","",SUMIFS('Finanças'!$F$10:$F$1509,'Finanças'!$C$10:$C$1509,"Despesa",'Finanças'!$D$10:$D$1509,$B27,'Finanças'!$B$10:$B$1509,">="&DATE(Ano,3,1),'Finanças'!$B$10:$B$1509,"<="&DATE(Ano,3+1,0))) -> 0 | H27: =IF($B27="","",SUMIFS('Finanças'!$F$10:$F$1509,'Finanças'!$C$10:$C$1509,"Despesa",'Finanças'!$D$10:$D$1509,$B27,'Finanças'!$B$10:$B$1509,">="&DATE(Ano,4,1),'Finanças'!$B$10:$B$1509,"<="&DATE(Ano,4+1,0))) -> 0 | I27: =IF($B27="","",SUMIFS('Finanças'!$F$10:$F$1509,'Finanças'!$C$10:$C$1509,"Despesa",'Finanças'!$D$10:$D$1509,$B27,'Finanças'!$B$10:$B$1509,">="&DATE(Ano,5,1),'Finanças'!$B$10:$B$1509,"<="&DATE(Ano,5+1,0))) -> 0 | J27: =IF($B27="","",SUMIFS('Finanças'!$F$10:$F$1509,'Finanças'!$C$10:$C$1509,"Despesa",'Finanças'!$D$10:$D$1509,$B27,'Finanças'!$B$10:$B$1509,">="&DATE(Ano,6,1),'Finanças'!$B$10:$B$1509,"<="&DATE(Ano,6+1,0))) -> 0 | K27: =IF($B27="","",SUMIFS('Finanças'!$F$10:$F$1509,'Finanças'!$C$10:$C$1509,"Despesa",'Finanças'!$D$10:$D$1509,$B27,'Finanças'!$B$10:$B$1509,">="&DATE(Ano,7,1),'Finanças'!$B$10:$B$1509,"<="&DATE(Ano,7+1,0))) -> 0 | L27: =IF($B27="","",SUMIFS('Finanças'!$F$10:$F$1509,'Finanças'!$C$10:$C$1509,"Despesa",'Finanças'!$D$10:$D$1509,$B27,'Finanças'!$B$10:$B$1509,">="&DATE(Ano,8,1),'Finanças'!$B$10:$B$1509,"<="&DATE(Ano,8+1,0))) -> 0 | M27: =IF($B27="","",SUMIFS('Finanças'!$F$10:$F$1509,'Finanças'!$C$10:$C$1509,"Despesa",'Finanças'!$D$10:$D$1509,$B27,'Finanças'!$B$10:$B$1509,">="&DATE(Ano,9,1),'Finanças'!$B$10:$B$1509,"<="&DATE(Ano,9+1,0))) -> 0 | N27: =IF($B27="","",SUMIFS('Finanças'!$F$10:$F$1509,'Finanças'!$C$10:$C$1509,"Despesa",'Finanças'!$D$10:$D$1509,$B27,'Finanças'!$B$10:$B$1509,">="&DATE(Ano,10,1),'Finanças'!$B$10:$B$1509,"<="&DATE(Ano,10+1,0))) -> 0 | O27: =IF($B27="","",SUMIFS('Finanças'!$F$10:$F$1509,'Finanças'!$C$10:$C$1509,"Despesa",'Finanças'!$D$10:$D$1509,$B27,'Finanças'!$B$10:$B$1509,">="&DATE(Ano,11,1),'Finanças'!$B$10:$B$1509,"<="&DATE(Ano,11+1,0))) -> 0 | P27: =IF($B27="","",SUMIFS('Finanças'!$F$10:$F$1509,'Finanças'!$C$10:$C$1509,"Despesa",'Finanças'!$D$10:$D$1509,$B27,'Finanças'!$B$10:$B$1509,">="&DATE(Ano,12,1),'Finanças'!$B$10:$B$1509,"<="&DATE(Ano,12+1,0))) -> 0 | Q27: =IF(B27="","",SUM(E27:P27)) -> 0 | R27: =IF(B27="","",SUMPRODUCT((COLUMN($E27:$P27)-COLUMN($E27)+1<=RefMes)*$E27:$P27)/RefMes) -> 0 | S27: =IF(B27="","",INDEX(E27:P27,RefMes)) -> 0 | T27: =IF(OR(B27="",N(D27)=0),"",S27/D27) | U27: =IF(T27="",IF(AND(B27<>"",N(S27)>0),"○ Sem orçamento",""),IF(T27>1,"✖ Estourou",IF(T27>DiasRef/DiasMes+0.15,"▲ Ritmo alto","✔ OK")))
B28: =IF('Config'!$I$16="","",'Config'!$I$16) -> Cuidados pessoais | C28: =IF(B28="","",'Config'!$J$16&"") -> Estilo de vida | E28: =IF($B28="","",SUMIFS('Finanças'!$F$10:$F$1509,'Finanças'!$C$10:$C$1509,"Despesa",'Finanças'!$D$10:$D$1509,$B28,'Finanças'!$B$10:$B$1509,">="&DATE(Ano,1,1),'Finanças'!$B$10:$B$1509,"<="&DATE(Ano,1+1,0))) -> 0 | F28: =IF($B28="","",SUMIFS('Finanças'!$F$10:$F$1509,'Finanças'!$C$10:$C$1509,"Despesa",'Finanças'!$D$10:$D$1509,$B28,'Finanças'!$B$10:$B$1509,">="&DATE(Ano,2,1),'Finanças'!$B$10:$B$1509,"<="&DATE(Ano,2+1,0))) -> 0 | G28: =IF($B28="","",SUMIFS('Finanças'!$F$10:$F$1509,'Finanças'!$C$10:$C$1509,"Despesa",'Finanças'!$D$10:$D$1509,$B28,'Finanças'!$B$10:$B$1509,">="&DATE(Ano,3,1),'Finanças'!$B$10:$B$1509,"<="&DATE(Ano,3+1,0))) -> 0 | H28: =IF($B28="","",SUMIFS('Finanças'!$F$10:$F$1509,'Finanças'!$C$10:$C$1509,"Despesa",'Finanças'!$D$10:$D$1509,$B28,'Finanças'!$B$10:$B$1509,">="&DATE(Ano,4,1),'Finanças'!$B$10:$B$1509,"<="&DATE(Ano,4+1,0))) -> 0 | I28: =IF($B28="","",SUMIFS('Finanças'!$F$10:$F$1509,'Finanças'!$C$10:$C$1509,"Despesa",'Finanças'!$D$10:$D$1509,$B28,'Finanças'!$B$10:$B$1509,">="&DATE(Ano,5,1),'Finanças'!$B$10:$B$1509,"<="&DATE(Ano,5+1,0))) -> 0 | J28: =IF($B28="","",SUMIFS('Finanças'!$F$10:$F$1509,'Finanças'!$C$10:$C$1509,"Despesa",'Finanças'!$D$10:$D$1509,$B28,'Finanças'!$B$10:$B$1509,">="&DATE(Ano,6,1),'Finanças'!$B$10:$B$1509,"<="&DATE(Ano,6+1,0))) -> 0 | K28: =IF($B28="","",SUMIFS('Finanças'!$F$10:$F$1509,'Finanças'!$C$10:$C$1509,"Despesa",'Finanças'!$D$10:$D$1509,$B28,'Finanças'!$B$10:$B$1509,">="&DATE(Ano,7,1),'Finanças'!$B$10:$B$1509,"<="&DATE(Ano,7+1,0))) -> 0 | L28: =IF($B28="","",SUMIFS('Finanças'!$F$10:$F$1509,'Finanças'!$C$10:$C$1509,"Despesa",'Finanças'!$D$10:$D$1509,$B28,'Finanças'!$B$10:$B$1509,">="&DATE(Ano,8,1),'Finanças'!$B$10:$B$1509,"<="&DATE(Ano,8+1,0))) -> 0 | M28: =IF($B28="","",SUMIFS('Finanças'!$F$10:$F$1509,'Finanças'!$C$10:$C$1509,"Despesa",'Finanças'!$D$10:$D$1509,$B28,'Finanças'!$B$10:$B$1509,">="&DATE(Ano,9,1),'Finanças'!$B$10:$B$1509,"<="&DATE(Ano,9+1,0))) -> 0 | N28: =IF($B28="","",SUMIFS('Finanças'!$F$10:$F$1509,'Finanças'!$C$10:$C$1509,"Despesa",'Finanças'!$D$10:$D$1509,$B28,'Finanças'!$B$10:$B$1509,">="&DATE(Ano,10,1),'Finanças'!$B$10:$B$1509,"<="&DATE(Ano,10+1,0))) -> 0 | O28: =IF($B28="","",SUMIFS('Finanças'!$F$10:$F$1509,'Finanças'!$C$10:$C$1509,"Despesa",'Finanças'!$D$10:$D$1509,$B28,'Finanças'!$B$10:$B$1509,">="&DATE(Ano,11,1),'Finanças'!$B$10:$B$1509,"<="&DATE(Ano,11+1,0))) -> 0 | P28: =IF($B28="","",SUMIFS('Finanças'!$F$10:$F$1509,'Finanças'!$C$10:$C$1509,"Despesa",'Finanças'!$D$10:$D$1509,$B28,'Finanças'!$B$10:$B$1509,">="&DATE(Ano,12,1),'Finanças'!$B$10:$B$1509,"<="&DATE(Ano,12+1,0))) -> 0 | Q28: =IF(B28="","",SUM(E28:P28)) -> 0 | R28: =IF(B28="","",SUMPRODUCT((COLUMN($E28:$P28)-COLUMN($E28)+1<=RefMes)*$E28:$P28)/RefMes) -> 0 | S28: =IF(B28="","",INDEX(E28:P28,RefMes)) -> 0 | T28: =IF(OR(B28="",N(D28)=0),"",S28/D28) | U28: =IF(T28="",IF(AND(B28<>"",N(S28)>0),"○ Sem orçamento",""),IF(T28>1,"✖ Estourou",IF(T28>DiasRef/DiasMes+0.15,"▲ Ritmo alto","✔ OK")))
B29: =IF('Config'!$I$17="","",'Config'!$I$17) -> Lazer & passeios | C29: =IF(B29="","",'Config'!$J$17&"") -> Estilo de vida | E29: =IF($B29="","",SUMIFS('Finanças'!$F$10:$F$1509,'Finanças'!$C$10:$C$1509,"Despesa",'Finanças'!$D$10:$D$1509,$B29,'Finanças'!$B$10:$B$1509,">="&DATE(Ano,1,1),'Finanças'!$B$10:$B$1509,"<="&DATE(Ano,1+1,0))) -> 0 | F29: =IF($B29="","",SUMIFS('Finanças'!$F$10:$F$1509,'Finanças'!$C$10:$C$1509,"Despesa",'Finanças'!$D$10:$D$1509,$B29,'Finanças'!$B$10:$B$1509,">="&DATE(Ano,2,1),'Finanças'!$B$10:$B$1509,"<="&DATE(Ano,2+1,0))) -> 0 | G29: =IF($B29="","",SUMIFS('Finanças'!$F$10:$F$1509,'Finanças'!$C$10:$C$1509,"Despesa",'Finanças'!$D$10:$D$1509,$B29,'Finanças'!$B$10:$B$1509,">="&DATE(Ano,3,1),'Finanças'!$B$10:$B$1509,"<="&DATE(Ano,3+1,0))) -> 0 | H29: =IF($B29="","",SUMIFS('Finanças'!$F$10:$F$1509,'Finanças'!$C$10:$C$1509,"Despesa",'Finanças'!$D$10:$D$1509,$B29,'Finanças'!$B$10:$B$1509,">="&DATE(Ano,4,1),'Finanças'!$B$10:$B$1509,"<="&DATE(Ano,4+1,0))) -> 0 | I29: =IF($B29="","",SUMIFS('Finanças'!$F$10:$F$1509,'Finanças'!$C$10:$C$1509,"Despesa",'Finanças'!$D$10:$D$1509,$B29,'Finanças'!$B$10:$B$1509,">="&DATE(Ano,5,1),'Finanças'!$B$10:$B$1509,"<="&DATE(Ano,5+1,0))) -> 0 | J29: =IF($B29="","",SUMIFS('Finanças'!$F$10:$F$1509,'Finanças'!$C$10:$C$1509,"Despesa",'Finanças'!$D$10:$D$1509,$B29,'Finanças'!$B$10:$B$1509,">="&DATE(Ano,6,1),'Finanças'!$B$10:$B$1509,"<="&DATE(Ano,6+1,0))) -> 0 | K29: =IF($B29="","",SUMIFS('Finanças'!$F$10:$F$1509,'Finanças'!$C$10:$C$1509,"Despesa",'Finanças'!$D$10:$D$1509,$B29,'Finanças'!$B$10:$B$1509,">="&DATE(Ano,7,1),'Finanças'!$B$10:$B$1509,"<="&DATE(Ano,7+1,0))) -> 0 | L29: =IF($B29="","",SUMIFS('Finanças'!$F$10:$F$1509,'Finanças'!$C$10:$C$1509,"Despesa",'Finanças'!$D$10:$D$1509,$B29,'Finanças'!$B$10:$B$1509,">="&DATE(Ano,8,1),'Finanças'!$B$10:$B$1509,"<="&DATE(Ano,8+1,0))) -> 0 | M29: =IF($B29="","",SUMIFS('Finanças'!$F$10:$F$1509,'Finanças'!$C$10:$C$1509,"Despesa",'Finanças'!$D$10:$D$1509,$B29,'Finanças'!$B$10:$B$1509,">="&DATE(Ano,9,1),'Finanças'!$B$10:$B$1509,"<="&DATE(Ano,9+1,0))) -> 0 | N29: =IF($B29="","",SUMIFS('Finanças'!$F$10:$F$1509,'Finanças'!$C$10:$C$1509,"Despesa",'Finanças'!$D$10:$D$1509,$B29,'Finanças'!$B$10:$B$1509,">="&DATE(Ano,10,1),'Finanças'!$B$10:$B$1509,"<="&DATE(Ano,10+1,0))) -> 0 | O29: =IF($B29="","",SUMIFS('Finanças'!$F$10:$F$1509,'Finanças'!$C$10:$C$1509,"Despesa",'Finanças'!$D$10:$D$1509,$B29,'Finanças'!$B$10:$B$1509,">="&DATE(Ano,11,1),'Finanças'!$B$10:$B$1509,"<="&DATE(Ano,11+1,0))) -> 0 | P29: =IF($B29="","",SUMIFS('Finanças'!$F$10:$F$1509,'Finanças'!$C$10:$C$1509,"Despesa",'Finanças'!$D$10:$D$1509,$B29,'Finanças'!$B$10:$B$1509,">="&DATE(Ano,12,1),'Finanças'!$B$10:$B$1509,"<="&DATE(Ano,12+1,0))) -> 0 | Q29: =IF(B29="","",SUM(E29:P29)) -> 0 | R29: =IF(B29="","",SUMPRODUCT((COLUMN($E29:$P29)-COLUMN($E29)+1<=RefMes)*$E29:$P29)/RefMes) -> 0 | S29: =IF(B29="","",INDEX(E29:P29,RefMes)) -> 0 | T29: =IF(OR(B29="",N(D29)=0),"",S29/D29) | U29: =IF(T29="",IF(AND(B29<>"",N(S29)>0),"○ Sem orçamento",""),IF(T29>1,"✖ Estourou",IF(T29>DiasRef/DiasMes+0.15,"▲ Ritmo alto","✔ OK")))
B30: =IF('Config'!$I$18="","",'Config'!$I$18) -> Viagens | C30: =IF(B30="","",'Config'!$J$18&"") -> Estilo de vida | E30: =IF($B30="","",SUMIFS('Finanças'!$F$10:$F$1509,'Finanças'!$C$10:$C$1509,"Despesa",'Finanças'!$D$10:$D$1509,$B30,'Finanças'!$B$10:$B$1509,">="&DATE(Ano,1,1),'Finanças'!$B$10:$B$1509,"<="&DATE(Ano,1+1,0))) -> 0 | F30: =IF($B30="","",SUMIFS('Finanças'!$F$10:$F$1509,'Finanças'!$C$10:$C$1509,"Despesa",'Finanças'!$D$10:$D$1509,$B30,'Finanças'!$B$10:$B$1509,">="&DATE(Ano,2,1),'Finanças'!$B$10:$B$1509,"<="&DATE(Ano,2+1,0))) -> 0 | G30: =IF($B30="","",SUMIFS('Finanças'!$F$10:$F$1509,'Finanças'!$C$10:$C$1509,"Despesa",'Finanças'!$D$10:$D$1509,$B30,'Finanças'!$B$10:$B$1509,">="&DATE(Ano,3,1),'Finanças'!$B$10:$B$1509,"<="&DATE(Ano,3+1,0))) -> 0 | H30: =IF($B30="","",SUMIFS('Finanças'!$F$10:$F$1509,'Finanças'!$C$10:$C$1509,"Despesa",'Finanças'!$D$10:$D$1509,$B30,'Finanças'!$B$10:$B$1509,">="&DATE(Ano,4,1),'Finanças'!$B$10:$B$1509,"<="&DATE(Ano,4+1,0))) -> 0 | I30: =IF($B30="","",SUMIFS('Finanças'!$F$10:$F$1509,'Finanças'!$C$10:$C$1509,"Despesa",'Finanças'!$D$10:$D$1509,$B30,'Finanças'!$B$10:$B$1509,">="&DATE(Ano,5,1),'Finanças'!$B$10:$B$1509,"<="&DATE(Ano,5+1,0))) -> 0 | J30: =IF($B30="","",SUMIFS('Finanças'!$F$10:$F$1509,'Finanças'!$C$10:$C$1509,"Despesa",'Finanças'!$D$10:$D$1509,$B30,'Finanças'!$B$10:$B$1509,">="&DATE(Ano,6,1),'Finanças'!$B$10:$B$1509,"<="&DATE(Ano,6+1,0))) -> 0 | K30: =IF($B30="","",SUMIFS('Finanças'!$F$10:$F$1509,'Finanças'!$C$10:$C$1509,"Despesa",'Finanças'!$D$10:$D$1509,$B30,'Finanças'!$B$10:$B$1509,">="&DATE(Ano,7,1),'Finanças'!$B$10:$B$1509,"<="&DATE(Ano,7+1,0))) -> 0 | L30: =IF($B30="","",SUMIFS('Finanças'!$F$10:$F$1509,'Finanças'!$C$10:$C$1509,"Despesa",'Finanças'!$D$10:$D$1509,$B30,'Finanças'!$B$10:$B$1509,">="&DATE(Ano,8,1),'Finanças'!$B$10:$B$1509,"<="&DATE(Ano,8+1,0))) -> 0 | M30: =IF($B30="","",SUMIFS('Finanças'!$F$10:$F$1509,'Finanças'!$C$10:$C$1509,"Despesa",'Finanças'!$D$10:$D$1509,$B30,'Finanças'!$B$10:$B$1509,">="&DATE(Ano,9,1),'Finanças'!$B$10:$B$1509,"<="&DATE(Ano,9+1,0))) -> 0 | N30: =IF($B30="","",SUMIFS('Finanças'!$F$10:$F$1509,'Finanças'!$C$10:$C$1509,"Despesa",'Finanças'!$D$10:$D$1509,$B30,'Finanças'!$B$10:$B$1509,">="&DATE(Ano,10,1),'Finanças'!$B$10:$B$1509,"<="&DATE(Ano,10+1,0))) -> 0 | O30: =IF($B30="","",SUMIFS('Finanças'!$F$10:$F$1509,'Finanças'!$C$10:$C$1509,"Despesa",'Finanças'!$D$10:$D$1509,$B30,'Finanças'!$B$10:$B$1509,">="&DATE(Ano,11,1),'Finanças'!$B$10:$B$1509,"<="&DATE(Ano,11+1,0))) -> 0 | P30: =IF($B30="","",SUMIFS('Finanças'!$F$10:$F$1509,'Finanças'!$C$10:$C$1509,"Despesa",'Finanças'!$D$10:$D$1509,$B30,'Finanças'!$B$10:$B$1509,">="&DATE(Ano,12,1),'Finanças'!$B$10:$B$1509,"<="&DATE(Ano,12+1,0))) -> 0 | Q30: =IF(B30="","",SUM(E30:P30)) -> 0 | R30: =IF(B30="","",SUMPRODUCT((COLUMN($E30:$P30)-COLUMN($E30)+1<=RefMes)*$E30:$P30)/RefMes) -> 0 | S30: =IF(B30="","",INDEX(E30:P30,RefMes)) -> 0 | T30: =IF(OR(B30="",N(D30)=0),"",S30/D30) | U30: =IF(T30="",IF(AND(B30<>"",N(S30)>0),"○ Sem orçamento",""),IF(T30>1,"✖ Estourou",IF(T30>DiasRef/DiasMes+0.15,"▲ Ritmo alto","✔ OK")))
B31: =IF('Config'!$I$19="","",'Config'!$I$19) -> Roupas | C31: =IF(B31="","",'Config'!$J$19&"") -> Estilo de vida | E31: =IF($B31="","",SUMIFS('Finanças'!$F$10:$F$1509,'Finanças'!$C$10:$C$1509,"Despesa",'Finanças'!$D$10:$D$1509,$B31,'Finanças'!$B$10:$B$1509,">="&DATE(Ano,1,1),'Finanças'!$B$10:$B$1509,"<="&DATE(Ano,1+1,0))) -> 0 | F31: =IF($B31="","",SUMIFS('Finanças'!$F$10:$F$1509,'Finanças'!$C$10:$C$1509,"Despesa",'Finanças'!$D$10:$D$1509,$B31,'Finanças'!$B$10:$B$1509,">="&DATE(Ano,2,1),'Finanças'!$B$10:$B$1509,"<="&DATE(Ano,2+1,0))) -> 0 | G31: =IF($B31="","",SUMIFS('Finanças'!$F$10:$F$1509,'Finanças'!$C$10:$C$1509,"Despesa",'Finanças'!$D$10:$D$1509,$B31,'Finanças'!$B$10:$B$1509,">="&DATE(Ano,3,1),'Finanças'!$B$10:$B$1509,"<="&DATE(Ano,3+1,0))) -> 0 | H31: =IF($B31="","",SUMIFS('Finanças'!$F$10:$F$1509,'Finanças'!$C$10:$C$1509,"Despesa",'Finanças'!$D$10:$D$1509,$B31,'Finanças'!$B$10:$B$1509,">="&DATE(Ano,4,1),'Finanças'!$B$10:$B$1509,"<="&DATE(Ano,4+1,0))) -> 0 | I31: =IF($B31="","",SUMIFS('Finanças'!$F$10:$F$1509,'Finanças'!$C$10:$C$1509,"Despesa",'Finanças'!$D$10:$D$1509,$B31,'Finanças'!$B$10:$B$1509,">="&DATE(Ano,5,1),'Finanças'!$B$10:$B$1509,"<="&DATE(Ano,5+1,0))) -> 0 | J31: =IF($B31="","",SUMIFS('Finanças'!$F$10:$F$1509,'Finanças'!$C$10:$C$1509,"Despesa",'Finanças'!$D$10:$D$1509,$B31,'Finanças'!$B$10:$B$1509,">="&DATE(Ano,6,1),'Finanças'!$B$10:$B$1509,"<="&DATE(Ano,6+1,0))) -> 0 | K31: =IF($B31="","",SUMIFS('Finanças'!$F$10:$F$1509,'Finanças'!$C$10:$C$1509,"Despesa",'Finanças'!$D$10:$D$1509,$B31,'Finanças'!$B$10:$B$1509,">="&DATE(Ano,7,1),'Finanças'!$B$10:$B$1509,"<="&DATE(Ano,7+1,0))) -> 0 | L31: =IF($B31="","",SUMIFS('Finanças'!$F$10:$F$1509,'Finanças'!$C$10:$C$1509,"Despesa",'Finanças'!$D$10:$D$1509,$B31,'Finanças'!$B$10:$B$1509,">="&DATE(Ano,8,1),'Finanças'!$B$10:$B$1509,"<="&DATE(Ano,8+1,0))) -> 0 | M31: =IF($B31="","",SUMIFS('Finanças'!$F$10:$F$1509,'Finanças'!$C$10:$C$1509,"Despesa",'Finanças'!$D$10:$D$1509,$B31,'Finanças'!$B$10:$B$1509,">="&DATE(Ano,9,1),'Finanças'!$B$10:$B$1509,"<="&DATE(Ano,9+1,0))) -> 0 | N31: =IF($B31="","",SUMIFS('Finanças'!$F$10:$F$1509,'Finanças'!$C$10:$C$1509,"Despesa",'Finanças'!$D$10:$D$1509,$B31,'Finanças'!$B$10:$B$1509,">="&DATE(Ano,10,1),'Finanças'!$B$10:$B$1509,"<="&DATE(Ano,10+1,0))) -> 0 | O31: =IF($B31="","",SUMIFS('Finanças'!$F$10:$F$1509,'Finanças'!$C$10:$C$1509,"Despesa",'Finanças'!$D$10:$D$1509,$B31,'Finanças'!$B$10:$B$1509,">="&DATE(Ano,11,1),'Finanças'!$B$10:$B$1509,"<="&DATE(Ano,11+1,0))) -> 0 | P31: =IF($B31="","",SUMIFS('Finanças'!$F$10:$F$1509,'Finanças'!$C$10:$C$1509,"Despesa",'Finanças'!$D$10:$D$1509,$B31,'Finanças'!$B$10:$B$1509,">="&DATE(Ano,12,1),'Finanças'!$B$10:$B$1509,"<="&DATE(Ano,12+1,0))) -> 0 | Q31: =IF(B31="","",SUM(E31:P31)) -> 0 | R31: =IF(B31="","",SUMPRODUCT((COLUMN($E31:$P31)-COLUMN($E31)+1<=RefMes)*$E31:$P31)/RefMes) -> 0 | S31: =IF(B31="","",INDEX(E31:P31,RefMes)) -> 0 | T31: =IF(OR(B31="",N(D31)=0),"",S31/D31) | U31: =IF(T31="",IF(AND(B31<>"",N(S31)>0),"○ Sem orçamento",""),IF(T31>1,"✖ Estourou",IF(T31>DiasRef/DiasMes+0.15,"▲ Ritmo alto","✔ OK")))
B32: =IF('Config'!$I$20="","",'Config'!$I$20) -> Casa & utensílios | C32: =IF(B32="","",'Config'!$J$20&"") -> Estilo de vida | E32: =IF($B32="","",SUMIFS('Finanças'!$F$10:$F$1509,'Finanças'!$C$10:$C$1509,"Despesa",'Finanças'!$D$10:$D$1509,$B32,'Finanças'!$B$10:$B$1509,">="&DATE(Ano,1,1),'Finanças'!$B$10:$B$1509,"<="&DATE(Ano,1+1,0))) -> 0 | F32: =IF($B32="","",SUMIFS('Finanças'!$F$10:$F$1509,'Finanças'!$C$10:$C$1509,"Despesa",'Finanças'!$D$10:$D$1509,$B32,'Finanças'!$B$10:$B$1509,">="&DATE(Ano,2,1),'Finanças'!$B$10:$B$1509,"<="&DATE(Ano,2+1,0))) -> 0 | G32: =IF($B32="","",SUMIFS('Finanças'!$F$10:$F$1509,'Finanças'!$C$10:$C$1509,"Despesa",'Finanças'!$D$10:$D$1509,$B32,'Finanças'!$B$10:$B$1509,">="&DATE(Ano,3,1),'Finanças'!$B$10:$B$1509,"<="&DATE(Ano,3+1,0))) -> 0 | H32: =IF($B32="","",SUMIFS('Finanças'!$F$10:$F$1509,'Finanças'!$C$10:$C$1509,"Despesa",'Finanças'!$D$10:$D$1509,$B32,'Finanças'!$B$10:$B$1509,">="&DATE(Ano,4,1),'Finanças'!$B$10:$B$1509,"<="&DATE(Ano,4+1,0))) -> 0 | I32: =IF($B32="","",SUMIFS('Finanças'!$F$10:$F$1509,'Finanças'!$C$10:$C$1509,"Despesa",'Finanças'!$D$10:$D$1509,$B32,'Finanças'!$B$10:$B$1509,">="&DATE(Ano,5,1),'Finanças'!$B$10:$B$1509,"<="&DATE(Ano,5+1,0))) -> 0 | J32: =IF($B32="","",SUMIFS('Finanças'!$F$10:$F$1509,'Finanças'!$C$10:$C$1509,"Despesa",'Finanças'!$D$10:$D$1509,$B32,'Finanças'!$B$10:$B$1509,">="&DATE(Ano,6,1),'Finanças'!$B$10:$B$1509,"<="&DATE(Ano,6+1,0))) -> 0 | K32: =IF($B32="","",SUMIFS('Finanças'!$F$10:$F$1509,'Finanças'!$C$10:$C$1509,"Despesa",'Finanças'!$D$10:$D$1509,$B32,'Finanças'!$B$10:$B$1509,">="&DATE(Ano,7,1),'Finanças'!$B$10:$B$1509,"<="&DATE(Ano,7+1,0))) -> 0 | L32: =IF($B32="","",SUMIFS('Finanças'!$F$10:$F$1509,'Finanças'!$C$10:$C$1509,"Despesa",'Finanças'!$D$10:$D$1509,$B32,'Finanças'!$B$10:$B$1509,">="&DATE(Ano,8,1),'Finanças'!$B$10:$B$1509,"<="&DATE(Ano,8+1,0))) -> 0 | M32: =IF($B32="","",SUMIFS('Finanças'!$F$10:$F$1509,'Finanças'!$C$10:$C$1509,"Despesa",'Finanças'!$D$10:$D$1509,$B32,'Finanças'!$B$10:$B$1509,">="&DATE(Ano,9,1),'Finanças'!$B$10:$B$1509,"<="&DATE(Ano,9+1,0))) -> 0 | N32: =IF($B32="","",SUMIFS('Finanças'!$F$10:$F$1509,'Finanças'!$C$10:$C$1509,"Despesa",'Finanças'!$D$10:$D$1509,$B32,'Finanças'!$B$10:$B$1509,">="&DATE(Ano,10,1),'Finanças'!$B$10:$B$1509,"<="&DATE(Ano,10+1,0))) -> 0 | O32: =IF($B32="","",SUMIFS('Finanças'!$F$10:$F$1509,'Finanças'!$C$10:$C$1509,"Despesa",'Finanças'!$D$10:$D$1509,$B32,'Finanças'!$B$10:$B$1509,">="&DATE(Ano,11,1),'Finanças'!$B$10:$B$1509,"<="&DATE(Ano,11+1,0))) -> 0 | P32: =IF($B32="","",SUMIFS('Finanças'!$F$10:$F$1509,'Finanças'!$C$10:$C$1509,"Despesa",'Finanças'!$D$10:$D$1509,$B32,'Finanças'!$B$10:$B$1509,">="&DATE(Ano,12,1),'Finanças'!$B$10:$B$1509,"<="&DATE(Ano,12+1,0))) -> 0 | Q32: =IF(B32="","",SUM(E32:P32)) -> 0 | R32: =IF(B32="","",SUMPRODUCT((COLUMN($E32:$P32)-COLUMN($E32)+1<=RefMes)*$E32:$P32)/RefMes) -> 0 | S32: =IF(B32="","",INDEX(E32:P32,RefMes)) -> 0 | T32: =IF(OR(B32="",N(D32)=0),"",S32/D32) | U32: =IF(T32="",IF(AND(B32<>"",N(S32)>0),"○ Sem orçamento",""),IF(T32>1,"✖ Estourou",IF(T32>DiasRef/DiasMes+0.15,"▲ Ritmo alto","✔ OK")))
B33: =IF('Config'!$I$21="","",'Config'!$I$21) -> Presentes & doações | C33: =IF(B33="","",'Config'!$J$21&"") -> Estilo de vida | E33: =IF($B33="","",SUMIFS('Finanças'!$F$10:$F$1509,'Finanças'!$C$10:$C$1509,"Despesa",'Finanças'!$D$10:$D$1509,$B33,'Finanças'!$B$10:$B$1509,">="&DATE(Ano,1,1),'Finanças'!$B$10:$B$1509,"<="&DATE(Ano,1+1,0))) -> 0 | F33: =IF($B33="","",SUMIFS('Finanças'!$F$10:$F$1509,'Finanças'!$C$10:$C$1509,"Despesa",'Finanças'!$D$10:$D$1509,$B33,'Finanças'!$B$10:$B$1509,">="&DATE(Ano,2,1),'Finanças'!$B$10:$B$1509,"<="&DATE(Ano,2+1,0))) -> 0 | G33: =IF($B33="","",SUMIFS('Finanças'!$F$10:$F$1509,'Finanças'!$C$10:$C$1509,"Despesa",'Finanças'!$D$10:$D$1509,$B33,'Finanças'!$B$10:$B$1509,">="&DATE(Ano,3,1),'Finanças'!$B$10:$B$1509,"<="&DATE(Ano,3+1,0))) -> 0 | H33: =IF($B33="","",SUMIFS('Finanças'!$F$10:$F$1509,'Finanças'!$C$10:$C$1509,"Despesa",'Finanças'!$D$10:$D$1509,$B33,'Finanças'!$B$10:$B$1509,">="&DATE(Ano,4,1),'Finanças'!$B$10:$B$1509,"<="&DATE(Ano,4+1,0))) -> 0 | I33: =IF($B33="","",SUMIFS('Finanças'!$F$10:$F$1509,'Finanças'!$C$10:$C$1509,"Despesa",'Finanças'!$D$10:$D$1509,$B33,'Finanças'!$B$10:$B$1509,">="&DATE(Ano,5,1),'Finanças'!$B$10:$B$1509,"<="&DATE(Ano,5+1,0))) -> 0 | J33: =IF($B33="","",SUMIFS('Finanças'!$F$10:$F$1509,'Finanças'!$C$10:$C$1509,"Despesa",'Finanças'!$D$10:$D$1509,$B33,'Finanças'!$B$10:$B$1509,">="&DATE(Ano,6,1),'Finanças'!$B$10:$B$1509,"<="&DATE(Ano,6+1,0))) -> 0 | K33: =IF($B33="","",SUMIFS('Finanças'!$F$10:$F$1509,'Finanças'!$C$10:$C$1509,"Despesa",'Finanças'!$D$10:$D$1509,$B33,'Finanças'!$B$10:$B$1509,">="&DATE(Ano,7,1),'Finanças'!$B$10:$B$1509,"<="&DATE(Ano,7+1,0))) -> 0 | L33: =IF($B33="","",SUMIFS('Finanças'!$F$10:$F$1509,'Finanças'!$C$10:$C$1509,"Despesa",'Finanças'!$D$10:$D$1509,$B33,'Finanças'!$B$10:$B$1509,">="&DATE(Ano,8,1),'Finanças'!$B$10:$B$1509,"<="&DATE(Ano,8+1,0))) -> 0 | M33: =IF($B33="","",SUMIFS('Finanças'!$F$10:$F$1509,'Finanças'!$C$10:$C$1509,"Despesa",'Finanças'!$D$10:$D$1509,$B33,'Finanças'!$B$10:$B$1509,">="&DATE(Ano,9,1),'Finanças'!$B$10:$B$1509,"<="&DATE(Ano,9+1,0))) -> 0 | N33: =IF($B33="","",SUMIFS('Finanças'!$F$10:$F$1509,'Finanças'!$C$10:$C$1509,"Despesa",'Finanças'!$D$10:$D$1509,$B33,'Finanças'!$B$10:$B$1509,">="&DATE(Ano,10,1),'Finanças'!$B$10:$B$1509,"<="&DATE(Ano,10+1,0))) -> 0 | O33: =IF($B33="","",SUMIFS('Finanças'!$F$10:$F$1509,'Finanças'!$C$10:$C$1509,"Despesa",'Finanças'!$D$10:$D$1509,$B33,'Finanças'!$B$10:$B$1509,">="&DATE(Ano,11,1),'Finanças'!$B$10:$B$1509,"<="&DATE(Ano,11+1,0))) -> 0 | P33: =IF($B33="","",SUMIFS('Finanças'!$F$10:$F$1509,'Finanças'!$C$10:$C$1509,"Despesa",'Finanças'!$D$10:$D$1509,$B33,'Finanças'!$B$10:$B$1509,">="&DATE(Ano,12,1),'Finanças'!$B$10:$B$1509,"<="&DATE(Ano,12+1,0))) -> 0 | Q33: =IF(B33="","",SUM(E33:P33)) -> 0 | R33: =IF(B33="","",SUMPRODUCT((COLUMN($E33:$P33)-COLUMN($E33)+1<=RefMes)*$E33:$P33)/RefMes) -> 0 | S33: =IF(B33="","",INDEX(E33:P33,RefMes)) -> 0 | T33: =IF(OR(B33="",N(D33)=0),"",S33/D33) | U33: =IF(T33="",IF(AND(B33<>"",N(S33)>0),"○ Sem orçamento",""),IF(T33>1,"✖ Estourou",IF(T33>DiasRef/DiasMes+0.15,"▲ Ritmo alto","✔ OK")))
B34: =IF('Config'!$I$22="","",'Config'!$I$22) -> Educação & cursos | C34: =IF(B34="","",'Config'!$J$22&"") -> Crescimento | E34: =IF($B34="","",SUMIFS('Finanças'!$F$10:$F$1509,'Finanças'!$C$10:$C$1509,"Despesa",'Finanças'!$D$10:$D$1509,$B34,'Finanças'!$B$10:$B$1509,">="&DATE(Ano,1,1),'Finanças'!$B$10:$B$1509,"<="&DATE(Ano,1+1,0))) -> 0 | F34: =IF($B34="","",SUMIFS('Finanças'!$F$10:$F$1509,'Finanças'!$C$10:$C$1509,"Despesa",'Finanças'!$D$10:$D$1509,$B34,'Finanças'!$B$10:$B$1509,">="&DATE(Ano,2,1),'Finanças'!$B$10:$B$1509,"<="&DATE(Ano,2+1,0))) -> 0 | G34: =IF($B34="","",SUMIFS('Finanças'!$F$10:$F$1509,'Finanças'!$C$10:$C$1509,"Despesa",'Finanças'!$D$10:$D$1509,$B34,'Finanças'!$B$10:$B$1509,">="&DATE(Ano,3,1),'Finanças'!$B$10:$B$1509,"<="&DATE(Ano,3+1,0))) -> 0 | H34: =IF($B34="","",SUMIFS('Finanças'!$F$10:$F$1509,'Finanças'!$C$10:$C$1509,"Despesa",'Finanças'!$D$10:$D$1509,$B34,'Finanças'!$B$10:$B$1509,">="&DATE(Ano,4,1),'Finanças'!$B$10:$B$1509,"<="&DATE(Ano,4+1,0))) -> 0 | I34: =IF($B34="","",SUMIFS('Finanças'!$F$10:$F$1509,'Finanças'!$C$10:$C$1509,"Despesa",'Finanças'!$D$10:$D$1509,$B34,'Finanças'!$B$10:$B$1509,">="&DATE(Ano,5,1),'Finanças'!$B$10:$B$1509,"<="&DATE(Ano,5+1,0))) -> 0 | J34: =IF($B34="","",SUMIFS('Finanças'!$F$10:$F$1509,'Finanças'!$C$10:$C$1509,"Despesa",'Finanças'!$D$10:$D$1509,$B34,'Finanças'!$B$10:$B$1509,">="&DATE(Ano,6,1),'Finanças'!$B$10:$B$1509,"<="&DATE(Ano,6+1,0))) -> 0 | K34: =IF($B34="","",SUMIFS('Finanças'!$F$10:$F$1509,'Finanças'!$C$10:$C$1509,"Despesa",'Finanças'!$D$10:$D$1509,$B34,'Finanças'!$B$10:$B$1509,">="&DATE(Ano,7,1),'Finanças'!$B$10:$B$1509,"<="&DATE(Ano,7+1,0))) -> 0 | L34: =IF($B34="","",SUMIFS('Finanças'!$F$10:$F$1509,'Finanças'!$C$10:$C$1509,"Despesa",'Finanças'!$D$10:$D$1509,$B34,'Finanças'!$B$10:$B$1509,">="&DATE(Ano,8,1),'Finanças'!$B$10:$B$1509,"<="&DATE(Ano,8+1,0))) -> 0 | M34: =IF($B34="","",SUMIFS('Finanças'!$F$10:$F$1509,'Finanças'!$C$10:$C$1509,"Despesa",'Finanças'!$D$10:$D$1509,$B34,'Finanças'!$B$10:$B$1509,">="&DATE(Ano,9,1),'Finanças'!$B$10:$B$1509,"<="&DATE(Ano,9+1,0))) -> 0 | N34: =IF($B34="","",SUMIFS('Finanças'!$F$10:$F$1509,'Finanças'!$C$10:$C$1509,"Despesa",'Finanças'!$D$10:$D$1509,$B34,'Finanças'!$B$10:$B$1509,">="&DATE(Ano,10,1),'Finanças'!$B$10:$B$1509,"<="&DATE(Ano,10+1,0))) -> 0 | O34: =IF($B34="","",SUMIFS('Finanças'!$F$10:$F$1509,'Finanças'!$C$10:$C$1509,"Despesa",'Finanças'!$D$10:$D$1509,$B34,'Finanças'!$B$10:$B$1509,">="&DATE(Ano,11,1),'Finanças'!$B$10:$B$1509,"<="&DATE(Ano,11+1,0))) -> 0 | P34: =IF($B34="","",SUMIFS('Finanças'!$F$10:$F$1509,'Finanças'!$C$10:$C$1509,"Despesa",'Finanças'!$D$10:$D$1509,$B34,'Finanças'!$B$10:$B$1509,">="&DATE(Ano,12,1),'Finanças'!$B$10:$B$1509,"<="&DATE(Ano,12+1,0))) -> 0 | Q34: =IF(B34="","",SUM(E34:P34)) -> 0 | R34: =IF(B34="","",SUMPRODUCT((COLUMN($E34:$P34)-COLUMN($E34)+1<=RefMes)*$E34:$P34)/RefMes) -> 0 | S34: =IF(B34="","",INDEX(E34:P34,RefMes)) -> 0 | T34: =IF(OR(B34="",N(D34)=0),"",S34/D34) | U34: =IF(T34="",IF(AND(B34<>"",N(S34)>0),"○ Sem orçamento",""),IF(T34>1,"✖ Estourou",IF(T34>DiasRef/DiasMes+0.15,"▲ Ritmo alto","✔ OK")))
B35: =IF('Config'!$I$23="","",'Config'!$I$23) -> Livros & materiais | C35: =IF(B35="","",'Config'!$J$23&"") -> Crescimento | E35: =IF($B35="","",SUMIFS('Finanças'!$F$10:$F$1509,'Finanças'!$C$10:$C$1509,"Despesa",'Finanças'!$D$10:$D$1509,$B35,'Finanças'!$B$10:$B$1509,">="&DATE(Ano,1,1),'Finanças'!$B$10:$B$1509,"<="&DATE(Ano,1+1,0))) -> 0 | F35: =IF($B35="","",SUMIFS('Finanças'!$F$10:$F$1509,'Finanças'!$C$10:$C$1509,"Despesa",'Finanças'!$D$10:$D$1509,$B35,'Finanças'!$B$10:$B$1509,">="&DATE(Ano,2,1),'Finanças'!$B$10:$B$1509,"<="&DATE(Ano,2+1,0))) -> 0 | G35: =IF($B35="","",SUMIFS('Finanças'!$F$10:$F$1509,'Finanças'!$C$10:$C$1509,"Despesa",'Finanças'!$D$10:$D$1509,$B35,'Finanças'!$B$10:$B$1509,">="&DATE(Ano,3,1),'Finanças'!$B$10:$B$1509,"<="&DATE(Ano,3+1,0))) -> 0 | H35: =IF($B35="","",SUMIFS('Finanças'!$F$10:$F$1509,'Finanças'!$C$10:$C$1509,"Despesa",'Finanças'!$D$10:$D$1509,$B35,'Finanças'!$B$10:$B$1509,">="&DATE(Ano,4,1),'Finanças'!$B$10:$B$1509,"<="&DATE(Ano,4+1,0))) -> 0 | I35: =IF($B35="","",SUMIFS('Finanças'!$F$10:$F$1509,'Finanças'!$C$10:$C$1509,"Despesa",'Finanças'!$D$10:$D$1509,$B35,'Finanças'!$B$10:$B$1509,">="&DATE(Ano,5,1),'Finanças'!$B$10:$B$1509,"<="&DATE(Ano,5+1,0))) -> 0 | J35: =IF($B35="","",SUMIFS('Finanças'!$F$10:$F$1509,'Finanças'!$C$10:$C$1509,"Despesa",'Finanças'!$D$10:$D$1509,$B35,'Finanças'!$B$10:$B$1509,">="&DATE(Ano,6,1),'Finanças'!$B$10:$B$1509,"<="&DATE(Ano,6+1,0))) -> 0 | K35: =IF($B35="","",SUMIFS('Finanças'!$F$10:$F$1509,'Finanças'!$C$10:$C$1509,"Despesa",'Finanças'!$D$10:$D$1509,$B35,'Finanças'!$B$10:$B$1509,">="&DATE(Ano,7,1),'Finanças'!$B$10:$B$1509,"<="&DATE(Ano,7+1,0))) -> 0 | L35: =IF($B35="","",SUMIFS('Finanças'!$F$10:$F$1509,'Finanças'!$C$10:$C$1509,"Despesa",'Finanças'!$D$10:$D$1509,$B35,'Finanças'!$B$10:$B$1509,">="&DATE(Ano,8,1),'Finanças'!$B$10:$B$1509,"<="&DATE(Ano,8+1,0))) -> 0 | M35: =IF($B35="","",SUMIFS('Finanças'!$F$10:$F$1509,'Finanças'!$C$10:$C$1509,"Despesa",'Finanças'!$D$10:$D$1509,$B35,'Finanças'!$B$10:$B$1509,">="&DATE(Ano,9,1),'Finanças'!$B$10:$B$1509,"<="&DATE(Ano,9+1,0))) -> 0 | N35: =IF($B35="","",SUMIFS('Finanças'!$F$10:$F$1509,'Finanças'!$C$10:$C$1509,"Despesa",'Finanças'!$D$10:$D$1509,$B35,'Finanças'!$B$10:$B$1509,">="&DATE(Ano,10,1),'Finanças'!$B$10:$B$1509,"<="&DATE(Ano,10+1,0))) -> 0 | O35: =IF($B35="","",SUMIFS('Finanças'!$F$10:$F$1509,'Finanças'!$C$10:$C$1509,"Despesa",'Finanças'!$D$10:$D$1509,$B35,'Finanças'!$B$10:$B$1509,">="&DATE(Ano,11,1),'Finanças'!$B$10:$B$1509,"<="&DATE(Ano,11+1,0))) -> 0 | P35: =IF($B35="","",SUMIFS('Finanças'!$F$10:$F$1509,'Finanças'!$C$10:$C$1509,"Despesa",'Finanças'!$D$10:$D$1509,$B35,'Finanças'!$B$10:$B$1509,">="&DATE(Ano,12,1),'Finanças'!$B$10:$B$1509,"<="&DATE(Ano,12+1,0))) -> 0 | Q35: =IF(B35="","",SUM(E35:P35)) -> 0 | R35: =IF(B35="","",SUMPRODUCT((COLUMN($E35:$P35)-COLUMN($E35)+1<=RefMes)*$E35:$P35)/RefMes) -> 0 | S35: =IF(B35="","",INDEX(E35:P35,RefMes)) -> 0 | T35: =IF(OR(B35="",N(D35)=0),"",S35/D35) | U35: =IF(T35="",IF(AND(B35<>"",N(S35)>0),"○ Sem orçamento",""),IF(T35>1,"✖ Estourou",IF(T35>DiasRef/DiasMes+0.15,"▲ Ritmo alto","✔ OK")))
B36: =IF('Config'!$I$24="","",'Config'!$I$24) -> Outros | C36: =IF(B36="","",'Config'!$J$24&"") -> Estilo de vida | E36: =IF($B36="","",SUMIFS('Finanças'!$F$10:$F$1509,'Finanças'!$C$10:$C$1509,"Despesa",'Finanças'!$D$10:$D$1509,$B36,'Finanças'!$B$10:$B$1509,">="&DATE(Ano,1,1),'Finanças'!$B$10:$B$1509,"<="&DATE(Ano,1+1,0))) -> 0 | F36: =IF($B36="","",SUMIFS('Finanças'!$F$10:$F$1509,'Finanças'!$C$10:$C$1509,"Despesa",'Finanças'!$D$10:$D$1509,$B36,'Finanças'!$B$10:$B$1509,">="&DATE(Ano,2,1),'Finanças'!$B$10:$B$1509,"<="&DATE(Ano,2+1,0))) -> 0 | G36: =IF($B36="","",SUMIFS('Finanças'!$F$10:$F$1509,'Finanças'!$C$10:$C$1509,"Despesa",'Finanças'!$D$10:$D$1509,$B36,'Finanças'!$B$10:$B$1509,">="&DATE(Ano,3,1),'Finanças'!$B$10:$B$1509,"<="&DATE(Ano,3+1,0))) -> 0 | H36: =IF($B36="","",SUMIFS('Finanças'!$F$10:$F$1509,'Finanças'!$C$10:$C$1509,"Despesa",'Finanças'!$D$10:$D$1509,$B36,'Finanças'!$B$10:$B$1509,">="&DATE(Ano,4,1),'Finanças'!$B$10:$B$1509,"<="&DATE(Ano,4+1,0))) -> 0 | I36: =IF($B36="","",SUMIFS('Finanças'!$F$10:$F$1509,'Finanças'!$C$10:$C$1509,"Despesa",'Finanças'!$D$10:$D$1509,$B36,'Finanças'!$B$10:$B$1509,">="&DATE(Ano,5,1),'Finanças'!$B$10:$B$1509,"<="&DATE(Ano,5+1,0))) -> 0 | J36: =IF($B36="","",SUMIFS('Finanças'!$F$10:$F$1509,'Finanças'!$C$10:$C$1509,"Despesa",'Finanças'!$D$10:$D$1509,$B36,'Finanças'!$B$10:$B$1509,">="&DATE(Ano,6,1),'Finanças'!$B$10:$B$1509,"<="&DATE(Ano,6+1,0))) -> 0 | K36: =IF($B36="","",SUMIFS('Finanças'!$F$10:$F$1509,'Finanças'!$C$10:$C$1509,"Despesa",'Finanças'!$D$10:$D$1509,$B36,'Finanças'!$B$10:$B$1509,">="&DATE(Ano,7,1),'Finanças'!$B$10:$B$1509,"<="&DATE(Ano,7+1,0))) -> 0 | L36: =IF($B36="","",SUMIFS('Finanças'!$F$10:$F$1509,'Finanças'!$C$10:$C$1509,"Despesa",'Finanças'!$D$10:$D$1509,$B36,'Finanças'!$B$10:$B$1509,">="&DATE(Ano,8,1),'Finanças'!$B$10:$B$1509,"<="&DATE(Ano,8+1,0))) -> 0 | M36: =IF($B36="","",SUMIFS('Finanças'!$F$10:$F$1509,'Finanças'!$C$10:$C$1509,"Despesa",'Finanças'!$D$10:$D$1509,$B36,'Finanças'!$B$10:$B$1509,">="&DATE(Ano,9,1),'Finanças'!$B$10:$B$1509,"<="&DATE(Ano,9+1,0))) -> 0 | N36: =IF($B36="","",SUMIFS('Finanças'!$F$10:$F$1509,'Finanças'!$C$10:$C$1509,"Despesa",'Finanças'!$D$10:$D$1509,$B36,'Finanças'!$B$10:$B$1509,">="&DATE(Ano,10,1),'Finanças'!$B$10:$B$1509,"<="&DATE(Ano,10+1,0))) -> 0 | O36: =IF($B36="","",SUMIFS('Finanças'!$F$10:$F$1509,'Finanças'!$C$10:$C$1509,"Despesa",'Finanças'!$D$10:$D$1509,$B36,'Finanças'!$B$10:$B$1509,">="&DATE(Ano,11,1),'Finanças'!$B$10:$B$1509,"<="&DATE(Ano,11+1,0))) -> 0 | P36: =IF($B36="","",SUMIFS('Finanças'!$F$10:$F$1509,'Finanças'!$C$10:$C$1509,"Despesa",'Finanças'!$D$10:$D$1509,$B36,'Finanças'!$B$10:$B$1509,">="&DATE(Ano,12,1),'Finanças'!$B$10:$B$1509,"<="&DATE(Ano,12+1,0))) -> 0 | Q36: =IF(B36="","",SUM(E36:P36)) -> 0 | R36: =IF(B36="","",SUMPRODUCT((COLUMN($E36:$P36)-COLUMN($E36)+1<=RefMes)*$E36:$P36)/RefMes) -> 0 | S36: =IF(B36="","",INDEX(E36:P36,RefMes)) -> 0 | T36: =IF(OR(B36="",N(D36)=0),"",S36/D36) | U36: =IF(T36="",IF(AND(B36<>"",N(S36)>0),"○ Sem orçamento",""),IF(T36>1,"✖ Estourou",IF(T36>DiasRef/DiasMes+0.15,"▲ Ritmo alto","✔ OK")))
B37: =IF('Config'!$I$25="","",'Config'!$I$25) | C37: =IF(B37="","",'Config'!$J$25&"") | E37: =IF($B37="","",SUMIFS('Finanças'!$F$10:$F$1509,'Finanças'!$C$10:$C$1509,"Despesa",'Finanças'!$D$10:$D$1509,$B37,'Finanças'!$B$10:$B$1509,">="&DATE(Ano,1,1),'Finanças'!$B$10:$B$1509,"<="&DATE(Ano,1+1,0))) | F37: =IF($B37="","",SUMIFS('Finanças'!$F$10:$F$1509,'Finanças'!$C$10:$C$1509,"Despesa",'Finanças'!$D$10:$D$1509,$B37,'Finanças'!$B$10:$B$1509,">="&DATE(Ano,2,1),'Finanças'!$B$10:$B$1509,"<="&DATE(Ano,2+1,0))) | G37: =IF($B37="","",SUMIFS('Finanças'!$F$10:$F$1509,'Finanças'!$C$10:$C$1509,"Despesa",'Finanças'!$D$10:$D$1509,$B37,'Finanças'!$B$10:$B$1509,">="&DATE(Ano,3,1),'Finanças'!$B$10:$B$1509,"<="&DATE(Ano,3+1,0))) | H37: =IF($B37="","",SUMIFS('Finanças'!$F$10:$F$1509,'Finanças'!$C$10:$C$1509,"Despesa",'Finanças'!$D$10:$D$1509,$B37,'Finanças'!$B$10:$B$1509,">="&DATE(Ano,4,1),'Finanças'!$B$10:$B$1509,"<="&DATE(Ano,4+1,0))) | I37: =IF($B37="","",SUMIFS('Finanças'!$F$10:$F$1509,'Finanças'!$C$10:$C$1509,"Despesa",'Finanças'!$D$10:$D$1509,$B37,'Finanças'!$B$10:$B$1509,">="&DATE(Ano,5,1),'Finanças'!$B$10:$B$1509,"<="&DATE(Ano,5+1,0))) | J37: =IF($B37="","",SUMIFS('Finanças'!$F$10:$F$1509,'Finanças'!$C$10:$C$1509,"Despesa",'Finanças'!$D$10:$D$1509,$B37,'Finanças'!$B$10:$B$1509,">="&DATE(Ano,6,1),'Finanças'!$B$10:$B$1509,"<="&DATE(Ano,6+1,0))) | K37: =IF($B37="","",SUMIFS('Finanças'!$F$10:$F$1509,'Finanças'!$C$10:$C$1509,"Despesa",'Finanças'!$D$10:$D$1509,$B37,'Finanças'!$B$10:$B$1509,">="&DATE(Ano,7,1),'Finanças'!$B$10:$B$1509,"<="&DATE(Ano,7+1,0))) | L37: =IF($B37="","",SUMIFS('Finanças'!$F$10:$F$1509,'Finanças'!$C$10:$C$1509,"Despesa",'Finanças'!$D$10:$D$1509,$B37,'Finanças'!$B$10:$B$1509,">="&DATE(Ano,8,1),'Finanças'!$B$10:$B$1509,"<="&DATE(Ano,8+1,0))) | M37: =IF($B37="","",SUMIFS('Finanças'!$F$10:$F$1509,'Finanças'!$C$10:$C$1509,"Despesa",'Finanças'!$D$10:$D$1509,$B37,'Finanças'!$B$10:$B$1509,">="&DATE(Ano,9,1),'Finanças'!$B$10:$B$1509,"<="&DATE(Ano,9+1,0))) | N37: =IF($B37="","",SUMIFS('Finanças'!$F$10:$F$1509,'Finanças'!$C$10:$C$1509,"Despesa",'Finanças'!$D$10:$D$1509,$B37,'Finanças'!$B$10:$B$1509,">="&DATE(Ano,10,1),'Finanças'!$B$10:$B$1509,"<="&DATE(Ano,10+1,0))) | O37: =IF($B37="","",SUMIFS('Finanças'!$F$10:$F$1509,'Finanças'!$C$10:$C$1509,"Despesa",'Finanças'!$D$10:$D$1509,$B37,'Finanças'!$B$10:$B$1509,">="&DATE(Ano,11,1),'Finanças'!$B$10:$B$1509,"<="&DATE(Ano,11+1,0))) | P37: =IF($B37="","",SUMIFS('Finanças'!$F$10:$F$1509,'Finanças'!$C$10:$C$1509,"Despesa",'Finanças'!$D$10:$D$1509,$B37,'Finanças'!$B$10:$B$1509,">="&DATE(Ano,12,1),'Finanças'!$B$10:$B$1509,"<="&DATE(Ano,12+1,0))) | Q37: =IF(B37="","",SUM(E37:P37)) | R37: =IF(B37="","",SUMPRODUCT((COLUMN($E37:$P37)-COLUMN($E37)+1<=RefMes)*$E37:$P37)/RefMes) | S37: =IF(B37="","",INDEX(E37:P37,RefMes)) | T37: =IF(OR(B37="",N(D37)=0),"",S37/D37) | U37: =IF(T37="",IF(AND(B37<>"",N(S37)>0),"○ Sem orçamento",""),IF(T37>1,"✖ Estourou",IF(T37>DiasRef/DiasMes+0.15,"▲ Ritmo alto","✔ OK")))
B38: =IF('Config'!$I$26="","",'Config'!$I$26) | C38: =IF(B38="","",'Config'!$J$26&"") | E38: =IF($B38="","",SUMIFS('Finanças'!$F$10:$F$1509,'Finanças'!$C$10:$C$1509,"Despesa",'Finanças'!$D$10:$D$1509,$B38,'Finanças'!$B$10:$B$1509,">="&DATE(Ano,1,1),'Finanças'!$B$10:$B$1509,"<="&DATE(Ano,1+1,0))) | F38: =IF($B38="","",SUMIFS('Finanças'!$F$10:$F$1509,'Finanças'!$C$10:$C$1509,"Despesa",'Finanças'!$D$10:$D$1509,$B38,'Finanças'!$B$10:$B$1509,">="&DATE(Ano,2,1),'Finanças'!$B$10:$B$1509,"<="&DATE(Ano,2+1,0))) | G38: =IF($B38="","",SUMIFS('Finanças'!$F$10:$F$1509,'Finanças'!$C$10:$C$1509,"Despesa",'Finanças'!$D$10:$D$1509,$B38,'Finanças'!$B$10:$B$1509,">="&DATE(Ano,3,1),'Finanças'!$B$10:$B$1509,"<="&DATE(Ano,3+1,0))) | H38: =IF($B38="","",SUMIFS('Finanças'!$F$10:$F$1509,'Finanças'!$C$10:$C$1509,"Despesa",'Finanças'!$D$10:$D$1509,$B38,'Finanças'!$B$10:$B$1509,">="&DATE(Ano,4,1),'Finanças'!$B$10:$B$1509,"<="&DATE(Ano,4+1,0))) | I38: =IF($B38="","",SUMIFS('Finanças'!$F$10:$F$1509,'Finanças'!$C$10:$C$1509,"Despesa",'Finanças'!$D$10:$D$1509,$B38,'Finanças'!$B$10:$B$1509,">="&DATE(Ano,5,1),'Finanças'!$B$10:$B$1509,"<="&DATE(Ano,5+1,0))) | J38: =IF($B38="","",SUMIFS('Finanças'!$F$10:$F$1509,'Finanças'!$C$10:$C$1509,"Despesa",'Finanças'!$D$10:$D$1509,$B38,'Finanças'!$B$10:$B$1509,">="&DATE(Ano,6,1),'Finanças'!$B$10:$B$1509,"<="&DATE(Ano,6+1,0))) | K38: =IF($B38="","",SUMIFS('Finanças'!$F$10:$F$1509,'Finanças'!$C$10:$C$1509,"Despesa",'Finanças'!$D$10:$D$1509,$B38,'Finanças'!$B$10:$B$1509,">="&DATE(Ano,7,1),'Finanças'!$B$10:$B$1509,"<="&DATE(Ano,7+1,0))) | L38: =IF($B38="","",SUMIFS('Finanças'!$F$10:$F$1509,'Finanças'!$C$10:$C$1509,"Despesa",'Finanças'!$D$10:$D$1509,$B38,'Finanças'!$B$10:$B$1509,">="&DATE(Ano,8,1),'Finanças'!$B$10:$B$1509,"<="&DATE(Ano,8+1,0))) | M38: =IF($B38="","",SUMIFS('Finanças'!$F$10:$F$1509,'Finanças'!$C$10:$C$1509,"Despesa",'Finanças'!$D$10:$D$1509,$B38,'Finanças'!$B$10:$B$1509,">="&DATE(Ano,9,1),'Finanças'!$B$10:$B$1509,"<="&DATE(Ano,9+1,0))) | N38: =IF($B38="","",SUMIFS('Finanças'!$F$10:$F$1509,'Finanças'!$C$10:$C$1509,"Despesa",'Finanças'!$D$10:$D$1509,$B38,'Finanças'!$B$10:$B$1509,">="&DATE(Ano,10,1),'Finanças'!$B$10:$B$1509,"<="&DATE(Ano,10+1,0))) | O38: =IF($B38="","",SUMIFS('Finanças'!$F$10:$F$1509,'Finanças'!$C$10:$C$1509,"Despesa",'Finanças'!$D$10:$D$1509,$B38,'Finanças'!$B$10:$B$1509,">="&DATE(Ano,11,1),'Finanças'!$B$10:$B$1509,"<="&DATE(Ano,11+1,0))) | P38: =IF($B38="","",SUMIFS('Finanças'!$F$10:$F$1509,'Finanças'!$C$10:$C$1509,"Despesa",'Finanças'!$D$10:$D$1509,$B38,'Finanças'!$B$10:$B$1509,">="&DATE(Ano,12,1),'Finanças'!$B$10:$B$1509,"<="&DATE(Ano,12+1,0))) | Q38: =IF(B38="","",SUM(E38:P38)) | R38: =IF(B38="","",SUMPRODUCT((COLUMN($E38:$P38)-COLUMN($E38)+1<=RefMes)*$E38:$P38)/RefMes) | S38: =IF(B38="","",INDEX(E38:P38,RefMes)) | T38: =IF(OR(B38="",N(D38)=0),"",S38/D38) | U38: =IF(T38="",IF(AND(B38<>"",N(S38)>0),"○ Sem orçamento",""),IF(T38>1,"✖ Estourou",IF(T38>DiasRef/DiasMes+0.15,"▲ Ritmo alto","✔ OK")))
B39: =IF('Config'!$I$27="","",'Config'!$I$27) | C39: =IF(B39="","",'Config'!$J$27&"") | E39: =IF($B39="","",SUMIFS('Finanças'!$F$10:$F$1509,'Finanças'!$C$10:$C$1509,"Despesa",'Finanças'!$D$10:$D$1509,$B39,'Finanças'!$B$10:$B$1509,">="&DATE(Ano,1,1),'Finanças'!$B$10:$B$1509,"<="&DATE(Ano,1+1,0))) | F39: =IF($B39="","",SUMIFS('Finanças'!$F$10:$F$1509,'Finanças'!$C$10:$C$1509,"Despesa",'Finanças'!$D$10:$D$1509,$B39,'Finanças'!$B$10:$B$1509,">="&DATE(Ano,2,1),'Finanças'!$B$10:$B$1509,"<="&DATE(Ano,2+1,0))) | G39: =IF($B39="","",SUMIFS('Finanças'!$F$10:$F$1509,'Finanças'!$C$10:$C$1509,"Despesa",'Finanças'!$D$10:$D$1509,$B39,'Finanças'!$B$10:$B$1509,">="&DATE(Ano,3,1),'Finanças'!$B$10:$B$1509,"<="&DATE(Ano,3+1,0))) | H39: =IF($B39="","",SUMIFS('Finanças'!$F$10:$F$1509,'Finanças'!$C$10:$C$1509,"Despesa",'Finanças'!$D$10:$D$1509,$B39,'Finanças'!$B$10:$B$1509,">="&DATE(Ano,4,1),'Finanças'!$B$10:$B$1509,"<="&DATE(Ano,4+1,0))) | I39: =IF($B39="","",SUMIFS('Finanças'!$F$10:$F$1509,'Finanças'!$C$10:$C$1509,"Despesa",'Finanças'!$D$10:$D$1509,$B39,'Finanças'!$B$10:$B$1509,">="&DATE(Ano,5,1),'Finanças'!$B$10:$B$1509,"<="&DATE(Ano,5+1,0))) | J39: =IF($B39="","",SUMIFS('Finanças'!$F$10:$F$1509,'Finanças'!$C$10:$C$1509,"Despesa",'Finanças'!$D$10:$D$1509,$B39,'Finanças'!$B$10:$B$1509,">="&DATE(Ano,6,1),'Finanças'!$B$10:$B$1509,"<="&DATE(Ano,6+1,0))) | K39: =IF($B39="","",SUMIFS('Finanças'!$F$10:$F$1509,'Finanças'!$C$10:$C$1509,"Despesa",'Finanças'!$D$10:$D$1509,$B39,'Finanças'!$B$10:$B$1509,">="&DATE(Ano,7,1),'Finanças'!$B$10:$B$1509,"<="&DATE(Ano,7+1,0))) | L39: =IF($B39="","",SUMIFS('Finanças'!$F$10:$F$1509,'Finanças'!$C$10:$C$1509,"Despesa",'Finanças'!$D$10:$D$1509,$B39,'Finanças'!$B$10:$B$1509,">="&DATE(Ano,8,1),'Finanças'!$B$10:$B$1509,"<="&DATE(Ano,8+1,0))) | M39: =IF($B39="","",SUMIFS('Finanças'!$F$10:$F$1509,'Finanças'!$C$10:$C$1509,"Despesa",'Finanças'!$D$10:$D$1509,$B39,'Finanças'!$B$10:$B$1509,">="&DATE(Ano,9,1),'Finanças'!$B$10:$B$1509,"<="&DATE(Ano,9+1,0))) | N39: =IF($B39="","",SUMIFS('Finanças'!$F$10:$F$1509,'Finanças'!$C$10:$C$1509,"Despesa",'Finanças'!$D$10:$D$1509,$B39,'Finanças'!$B$10:$B$1509,">="&DATE(Ano,10,1),'Finanças'!$B$10:$B$1509,"<="&DATE(Ano,10+1,0))) | O39: =IF($B39="","",SUMIFS('Finanças'!$F$10:$F$1509,'Finanças'!$C$10:$C$1509,"Despesa",'Finanças'!$D$10:$D$1509,$B39,'Finanças'!$B$10:$B$1509,">="&DATE(Ano,11,1),'Finanças'!$B$10:$B$1509,"<="&DATE(Ano,11+1,0))) | P39: =IF($B39="","",SUMIFS('Finanças'!$F$10:$F$1509,'Finanças'!$C$10:$C$1509,"Despesa",'Finanças'!$D$10:$D$1509,$B39,'Finanças'!$B$10:$B$1509,">="&DATE(Ano,12,1),'Finanças'!$B$10:$B$1509,"<="&DATE(Ano,12+1,0))) | Q39: =IF(B39="","",SUM(E39:P39)) | R39: =IF(B39="","",SUMPRODUCT((COLUMN($E39:$P39)-COLUMN($E39)+1<=RefMes)*$E39:$P39)/RefMes) | S39: =IF(B39="","",INDEX(E39:P39,RefMes)) | T39: =IF(OR(B39="",N(D39)=0),"",S39/D39) | U39: =IF(T39="",IF(AND(B39<>"",N(S39)>0),"○ Sem orçamento",""),IF(T39>1,"✖ Estourou",IF(T39>DiasRef/DiasMes+0.15,"▲ Ritmo alto","✔ OK")))
B40: =IF('Config'!$I$28="","",'Config'!$I$28) | C40: =IF(B40="","",'Config'!$J$28&"") | E40: =IF($B40="","",SUMIFS('Finanças'!$F$10:$F$1509,'Finanças'!$C$10:$C$1509,"Despesa",'Finanças'!$D$10:$D$1509,$B40,'Finanças'!$B$10:$B$1509,">="&DATE(Ano,1,1),'Finanças'!$B$10:$B$1509,"<="&DATE(Ano,1+1,0))) | F40: =IF($B40="","",SUMIFS('Finanças'!$F$10:$F$1509,'Finanças'!$C$10:$C$1509,"Despesa",'Finanças'!$D$10:$D$1509,$B40,'Finanças'!$B$10:$B$1509,">="&DATE(Ano,2,1),'Finanças'!$B$10:$B$1509,"<="&DATE(Ano,2+1,0))) | G40: =IF($B40="","",SUMIFS('Finanças'!$F$10:$F$1509,'Finanças'!$C$10:$C$1509,"Despesa",'Finanças'!$D$10:$D$1509,$B40,'Finanças'!$B$10:$B$1509,">="&DATE(Ano,3,1),'Finanças'!$B$10:$B$1509,"<="&DATE(Ano,3+1,0))) | H40: =IF($B40="","",SUMIFS('Finanças'!$F$10:$F$1509,'Finanças'!$C$10:$C$1509,"Despesa",'Finanças'!$D$10:$D$1509,$B40,'Finanças'!$B$10:$B$1509,">="&DATE(Ano,4,1),'Finanças'!$B$10:$B$1509,"<="&DATE(Ano,4+1,0))) | I40: =IF($B40="","",SUMIFS('Finanças'!$F$10:$F$1509,'Finanças'!$C$10:$C$1509,"Despesa",'Finanças'!$D$10:$D$1509,$B40,'Finanças'!$B$10:$B$1509,">="&DATE(Ano,5,1),'Finanças'!$B$10:$B$1509,"<="&DATE(Ano,5+1,0))) | J40: =IF($B40="","",SUMIFS('Finanças'!$F$10:$F$1509,'Finanças'!$C$10:$C$1509,"Despesa",'Finanças'!$D$10:$D$1509,$B40,'Finanças'!$B$10:$B$1509,">="&DATE(Ano,6,1),'Finanças'!$B$10:$B$1509,"<="&DATE(Ano,6+1,0))) | K40: =IF($B40="","",SUMIFS('Finanças'!$F$10:$F$1509,'Finanças'!$C$10:$C$1509,"Despesa",'Finanças'!$D$10:$D$1509,$B40,'Finanças'!$B$10:$B$1509,">="&DATE(Ano,7,1),'Finanças'!$B$10:$B$1509,"<="&DATE(Ano,7+1,0))) | L40: =IF($B40="","",SUMIFS('Finanças'!$F$10:$F$1509,'Finanças'!$C$10:$C$1509,"Despesa",'Finanças'!$D$10:$D$1509,$B40,'Finanças'!$B$10:$B$1509,">="&DATE(Ano,8,1),'Finanças'!$B$10:$B$1509,"<="&DATE(Ano,8+1,0))) | M40: =IF($B40="","",SUMIFS('Finanças'!$F$10:$F$1509,'Finanças'!$C$10:$C$1509,"Despesa",'Finanças'!$D$10:$D$1509,$B40,'Finanças'!$B$10:$B$1509,">="&DATE(Ano,9,1),'Finanças'!$B$10:$B$1509,"<="&DATE(Ano,9+1,0))) | N40: =IF($B40="","",SUMIFS('Finanças'!$F$10:$F$1509,'Finanças'!$C$10:$C$1509,"Despesa",'Finanças'!$D$10:$D$1509,$B40,'Finanças'!$B$10:$B$1509,">="&DATE(Ano,10,1),'Finanças'!$B$10:$B$1509,"<="&DATE(Ano,10+1,0))) | O40: =IF($B40="","",SUMIFS('Finanças'!$F$10:$F$1509,'Finanças'!$C$10:$C$1509,"Despesa",'Finanças'!$D$10:$D$1509,$B40,'Finanças'!$B$10:$B$1509,">="&DATE(Ano,11,1),'Finanças'!$B$10:$B$1509,"<="&DATE(Ano,11+1,0))) | P40: =IF($B40="","",SUMIFS('Finanças'!$F$10:$F$1509,'Finanças'!$C$10:$C$1509,"Despesa",'Finanças'!$D$10:$D$1509,$B40,'Finanças'!$B$10:$B$1509,">="&DATE(Ano,12,1),'Finanças'!$B$10:$B$1509,"<="&DATE(Ano,12+1,0))) | Q40: =IF(B40="","",SUM(E40:P40)) | R40: =IF(B40="","",SUMPRODUCT((COLUMN($E40:$P40)-COLUMN($E40)+1<=RefMes)*$E40:$P40)/RefMes) | S40: =IF(B40="","",INDEX(E40:P40,RefMes)) | T40: =IF(OR(B40="",N(D40)=0),"",S40/D40) | U40: =IF(T40="",IF(AND(B40<>"",N(S40)>0),"○ Sem orçamento",""),IF(T40>1,"✖ Estourou",IF(T40>DiasRef/DiasMes+0.15,"▲ Ritmo alto","✔ OK")))
B41: =IF('Config'!$I$29="","",'Config'!$I$29) | C41: =IF(B41="","",'Config'!$J$29&"") | E41: =IF($B41="","",SUMIFS('Finanças'!$F$10:$F$1509,'Finanças'!$C$10:$C$1509,"Despesa",'Finanças'!$D$10:$D$1509,$B41,'Finanças'!$B$10:$B$1509,">="&DATE(Ano,1,1),'Finanças'!$B$10:$B$1509,"<="&DATE(Ano,1+1,0))) | F41: =IF($B41="","",SUMIFS('Finanças'!$F$10:$F$1509,'Finanças'!$C$10:$C$1509,"Despesa",'Finanças'!$D$10:$D$1509,$B41,'Finanças'!$B$10:$B$1509,">="&DATE(Ano,2,1),'Finanças'!$B$10:$B$1509,"<="&DATE(Ano,2+1,0))) | G41: =IF($B41="","",SUMIFS('Finanças'!$F$10:$F$1509,'Finanças'!$C$10:$C$1509,"Despesa",'Finanças'!$D$10:$D$1509,$B41,'Finanças'!$B$10:$B$1509,">="&DATE(Ano,3,1),'Finanças'!$B$10:$B$1509,"<="&DATE(Ano,3+1,0))) | H41: =IF($B41="","",SUMIFS('Finanças'!$F$10:$F$1509,'Finanças'!$C$10:$C$1509,"Despesa",'Finanças'!$D$10:$D$1509,$B41,'Finanças'!$B$10:$B$1509,">="&DATE(Ano,4,1),'Finanças'!$B$10:$B$1509,"<="&DATE(Ano,4+1,0))) | I41: =IF($B41="","",SUMIFS('Finanças'!$F$10:$F$1509,'Finanças'!$C$10:$C$1509,"Despesa",'Finanças'!$D$10:$D$1509,$B41,'Finanças'!$B$10:$B$1509,">="&DATE(Ano,5,1),'Finanças'!$B$10:$B$1509,"<="&DATE(Ano,5+1,0))) | J41: =IF($B41="","",SUMIFS('Finanças'!$F$10:$F$1509,'Finanças'!$C$10:$C$1509,"Despesa",'Finanças'!$D$10:$D$1509,$B41,'Finanças'!$B$10:$B$1509,">="&DATE(Ano,6,1),'Finanças'!$B$10:$B$1509,"<="&DATE(Ano,6+1,0))) | K41: =IF($B41="","",SUMIFS('Finanças'!$F$10:$F$1509,'Finanças'!$C$10:$C$1509,"Despesa",'Finanças'!$D$10:$D$1509,$B41,'Finanças'!$B$10:$B$1509,">="&DATE(Ano,7,1),'Finanças'!$B$10:$B$1509,"<="&DATE(Ano,7+1,0))) | L41: =IF($B41="","",SUMIFS('Finanças'!$F$10:$F$1509,'Finanças'!$C$10:$C$1509,"Despesa",'Finanças'!$D$10:$D$1509,$B41,'Finanças'!$B$10:$B$1509,">="&DATE(Ano,8,1),'Finanças'!$B$10:$B$1509,"<="&DATE(Ano,8+1,0))) | M41: =IF($B41="","",SUMIFS('Finanças'!$F$10:$F$1509,'Finanças'!$C$10:$C$1509,"Despesa",'Finanças'!$D$10:$D$1509,$B41,'Finanças'!$B$10:$B$1509,">="&DATE(Ano,9,1),'Finanças'!$B$10:$B$1509,"<="&DATE(Ano,9+1,0))) | N41: =IF($B41="","",SUMIFS('Finanças'!$F$10:$F$1509,'Finanças'!$C$10:$C$1509,"Despesa",'Finanças'!$D$10:$D$1509,$B41,'Finanças'!$B$10:$B$1509,">="&DATE(Ano,10,1),'Finanças'!$B$10:$B$1509,"<="&DATE(Ano,10+1,0))) | O41: =IF($B41="","",SUMIFS('Finanças'!$F$10:$F$1509,'Finanças'!$C$10:$C$1509,"Despesa",'Finanças'!$D$10:$D$1509,$B41,'Finanças'!$B$10:$B$1509,">="&DATE(Ano,11,1),'Finanças'!$B$10:$B$1509,"<="&DATE(Ano,11+1,0))) | P41: =IF($B41="","",SUMIFS('Finanças'!$F$10:$F$1509,'Finanças'!$C$10:$C$1509,"Despesa",'Finanças'!$D$10:$D$1509,$B41,'Finanças'!$B$10:$B$1509,">="&DATE(Ano,12,1),'Finanças'!$B$10:$B$1509,"<="&DATE(Ano,12+1,0))) | Q41: =IF(B41="","",SUM(E41:P41)) | R41: =IF(B41="","",SUMPRODUCT((COLUMN($E41:$P41)-COLUMN($E41)+1<=RefMes)*$E41:$P41)/RefMes) | S41: =IF(B41="","",INDEX(E41:P41,RefMes)) | T41: =IF(OR(B41="",N(D41)=0),"",S41/D41) | U41: =IF(T41="",IF(AND(B41<>"",N(S41)>0),"○ Sem orçamento",""),IF(T41>1,"✖ Estourou",IF(T41>DiasRef/DiasMes+0.15,"▲ Ritmo alto","✔ OK")))
B42: =IF('Config'!$I$30="","",'Config'!$I$30) | C42: =IF(B42="","",'Config'!$J$30&"") | E42: =IF($B42="","",SUMIFS('Finanças'!$F$10:$F$1509,'Finanças'!$C$10:$C$1509,"Despesa",'Finanças'!$D$10:$D$1509,$B42,'Finanças'!$B$10:$B$1509,">="&DATE(Ano,1,1),'Finanças'!$B$10:$B$1509,"<="&DATE(Ano,1+1,0))) | F42: =IF($B42="","",SUMIFS('Finanças'!$F$10:$F$1509,'Finanças'!$C$10:$C$1509,"Despesa",'Finanças'!$D$10:$D$1509,$B42,'Finanças'!$B$10:$B$1509,">="&DATE(Ano,2,1),'Finanças'!$B$10:$B$1509,"<="&DATE(Ano,2+1,0))) | G42: =IF($B42="","",SUMIFS('Finanças'!$F$10:$F$1509,'Finanças'!$C$10:$C$1509,"Despesa",'Finanças'!$D$10:$D$1509,$B42,'Finanças'!$B$10:$B$1509,">="&DATE(Ano,3,1),'Finanças'!$B$10:$B$1509,"<="&DATE(Ano,3+1,0))) | H42: =IF($B42="","",SUMIFS('Finanças'!$F$10:$F$1509,'Finanças'!$C$10:$C$1509,"Despesa",'Finanças'!$D$10:$D$1509,$B42,'Finanças'!$B$10:$B$1509,">="&DATE(Ano,4,1),'Finanças'!$B$10:$B$1509,"<="&DATE(Ano,4+1,0))) | I42: =IF($B42="","",SUMIFS('Finanças'!$F$10:$F$1509,'Finanças'!$C$10:$C$1509,"Despesa",'Finanças'!$D$10:$D$1509,$B42,'Finanças'!$B$10:$B$1509,">="&DATE(Ano,5,1),'Finanças'!$B$10:$B$1509,"<="&DATE(Ano,5+1,0))) | J42: =IF($B42="","",SUMIFS('Finanças'!$F$10:$F$1509,'Finanças'!$C$10:$C$1509,"Despesa",'Finanças'!$D$10:$D$1509,$B42,'Finanças'!$B$10:$B$1509,">="&DATE(Ano,6,1),'Finanças'!$B$10:$B$1509,"<="&DATE(Ano,6+1,0))) | K42: =IF($B42="","",SUMIFS('Finanças'!$F$10:$F$1509,'Finanças'!$C$10:$C$1509,"Despesa",'Finanças'!$D$10:$D$1509,$B42,'Finanças'!$B$10:$B$1509,">="&DATE(Ano,7,1),'Finanças'!$B$10:$B$1509,"<="&DATE(Ano,7+1,0))) | L42: =IF($B42="","",SUMIFS('Finanças'!$F$10:$F$1509,'Finanças'!$C$10:$C$1509,"Despesa",'Finanças'!$D$10:$D$1509,$B42,'Finanças'!$B$10:$B$1509,">="&DATE(Ano,8,1),'Finanças'!$B$10:$B$1509,"<="&DATE(Ano,8+1,0))) | M42: =IF($B42="","",SUMIFS('Finanças'!$F$10:$F$1509,'Finanças'!$C$10:$C$1509,"Despesa",'Finanças'!$D$10:$D$1509,$B42,'Finanças'!$B$10:$B$1509,">="&DATE(Ano,9,1),'Finanças'!$B$10:$B$1509,"<="&DATE(Ano,9+1,0))) | N42: =IF($B42="","",SUMIFS('Finanças'!$F$10:$F$1509,'Finanças'!$C$10:$C$1509,"Despesa",'Finanças'!$D$10:$D$1509,$B42,'Finanças'!$B$10:$B$1509,">="&DATE(Ano,10,1),'Finanças'!$B$10:$B$1509,"<="&DATE(Ano,10+1,0))) | O42: =IF($B42="","",SUMIFS('Finanças'!$F$10:$F$1509,'Finanças'!$C$10:$C$1509,"Despesa",'Finanças'!$D$10:$D$1509,$B42,'Finanças'!$B$10:$B$1509,">="&DATE(Ano,11,1),'Finanças'!$B$10:$B$1509,"<="&DATE(Ano,11+1,0))) | P42: =IF($B42="","",SUMIFS('Finanças'!$F$10:$F$1509,'Finanças'!$C$10:$C$1509,"Despesa",'Finanças'!$D$10:$D$1509,$B42,'Finanças'!$B$10:$B$1509,">="&DATE(Ano,12,1),'Finanças'!$B$10:$B$1509,"<="&DATE(Ano,12+1,0))) | Q42: =IF(B42="","",SUM(E42:P42)) | R42: =IF(B42="","",SUMPRODUCT((COLUMN($E42:$P42)-COLUMN($E42)+1<=RefMes)*$E42:$P42)/RefMes) | S42: =IF(B42="","",INDEX(E42:P42,RefMes)) | T42: =IF(OR(B42="",N(D42)=0),"",S42/D42) | U42: =IF(T42="",IF(AND(B42<>"",N(S42)>0),"○ Sem orçamento",""),IF(T42>1,"✖ Estourou",IF(T42>DiasRef/DiasMes+0.15,"▲ Ritmo alto","✔ OK")))
B43: TOTAL | D43: =SUM(D18:D42) -> 0 | E43: =SUM(E18:E42) -> 0 | F43: =SUM(F18:F42) -> 0 | G43: =SUM(G18:G42) -> 0 | H43: =SUM(H18:H42) -> 0 | I43: =SUM(I18:I42) -> 0 | J43: =SUM(J18:J42) -> 0 | K43: =SUM(K18:K42) -> 0 | ... S43: =SUM(S18:S42) -> 0 | T43: =IF(D43>0,S43/D43,"")
B44: Fora da lista de categorias | E44: =E8-E43 -> 0 | F44: =F8-F43 -> 0 | G44: =G8-G43 -> 0 | H44: =H8-H43 -> 0 | I44: =I8-I43 -> 0 | J44: =J8-J43 -> 0 | K44: =K8-K43 -> 0 | L44: =L8-L43 -> 0 | ... P44: =P8-P43 -> 0 | Q44: =SUM(E44:P44) -> 0 | S44: =INDEX(E44:P44,RefMes) -> 0 | U44: ← deveria ser zero
B46: RECEITAS POR CATEGORIA
B47: Categoria | D47: Previsto / mês | E47: Jan | F47: Fev | G47: Mar | H47: Abr | I47: Mai | J47: Jun | K47: Jul | L47: Ago | M47: Set | N47: Out | O47: Nov | P47: Dez | Q47: Total ano | R47: Média/mês até a ref. | S47: Mês de referência | T47: % do plano | U47: Status no mês
B48: =IF('Config'!$K$6="","",'Config'!$K$6) -> Salário | E48: =IF($B48="","",SUMIFS('Finanças'!$F$10:$F$1509,'Finanças'!$C$10:$C$1509,"Receita",'Finanças'!$D$10:$D$1509,$B48,'Finanças'!$B$10:$B$1509,">="&DATE(Ano,1,1),'Finanças'!$B$10:$B$1509,"<="&DATE(Ano,1+1,0))) -> 0 | F48: =IF($B48="","",SUMIFS('Finanças'!$F$10:$F$1509,'Finanças'!$C$10:$C$1509,"Receita",'Finanças'!$D$10:$D$1509,$B48,'Finanças'!$B$10:$B$1509,">="&DATE(Ano,2,1),'Finanças'!$B$10:$B$1509,"<="&DATE(Ano,2+1,0))) -> 0 | G48: =IF($B48="","",SUMIFS('Finanças'!$F$10:$F$1509,'Finanças'!$C$10:$C$1509,"Receita",'Finanças'!$D$10:$D$1509,$B48,'Finanças'!$B$10:$B$1509,">="&DATE(Ano,3,1),'Finanças'!$B$10:$B$1509,"<="&DATE(Ano,3+1,0))) -> 0 | H48: =IF($B48="","",SUMIFS('Finanças'!$F$10:$F$1509,'Finanças'!$C$10:$C$1509,"Receita",'Finanças'!$D$10:$D$1509,$B48,'Finanças'!$B$10:$B$1509,">="&DATE(Ano,4,1),'Finanças'!$B$10:$B$1509,"<="&DATE(Ano,4+1,0))) -> 0 | I48: =IF($B48="","",SUMIFS('Finanças'!$F$10:$F$1509,'Finanças'!$C$10:$C$1509,"Receita",'Finanças'!$D$10:$D$1509,$B48,'Finanças'!$B$10:$B$1509,">="&DATE(Ano,5,1),'Finanças'!$B$10:$B$1509,"<="&DATE(Ano,5+1,0))) -> 0 | J48: =IF($B48="","",SUMIFS('Finanças'!$F$10:$F$1509,'Finanças'!$C$10:$C$1509,"Receita",'Finanças'!$D$10:$D$1509,$B48,'Finanças'!$B$10:$B$1509,">="&DATE(Ano,6,1),'Finanças'!$B$10:$B$1509,"<="&DATE(Ano,6+1,0))) -> 0 | K48: =IF($B48="","",SUMIFS('Finanças'!$F$10:$F$1509,'Finanças'!$C$10:$C$1509,"Receita",'Finanças'!$D$10:$D$1509,$B48,'Finanças'!$B$10:$B$1509,">="&DATE(Ano,7,1),'Finanças'!$B$10:$B$1509,"<="&DATE(Ano,7+1,0))) -> 0 | L48: =IF($B48="","",SUMIFS('Finanças'!$F$10:$F$1509,'Finanças'!$C$10:$C$1509,"Receita",'Finanças'!$D$10:$D$1509,$B48,'Finanças'!$B$10:$B$1509,">="&DATE(Ano,8,1),'Finanças'!$B$10:$B$1509,"<="&DATE(Ano,8+1,0))) -> 0 | M48: =IF($B48="","",SUMIFS('Finanças'!$F$10:$F$1509,'Finanças'!$C$10:$C$1509,"Receita",'Finanças'!$D$10:$D$1509,$B48,'Finanças'!$B$10:$B$1509,">="&DATE(Ano,9,1),'Finanças'!$B$10:$B$1509,"<="&DATE(Ano,9+1,0))) -> 0 | N48: =IF($B48="","",SUMIFS('Finanças'!$F$10:$F$1509,'Finanças'!$C$10:$C$1509,"Receita",'Finanças'!$D$10:$D$1509,$B48,'Finanças'!$B$10:$B$1509,">="&DATE(Ano,10,1),'Finanças'!$B$10:$B$1509,"<="&DATE(Ano,10+1,0))) -> 0 | O48: =IF($B48="","",SUMIFS('Finanças'!$F$10:$F$1509,'Finanças'!$C$10:$C$1509,"Receita",'Finanças'!$D$10:$D$1509,$B48,'Finanças'!$B$10:$B$1509,">="&DATE(Ano,11,1),'Finanças'!$B$10:$B$1509,"<="&DATE(Ano,11+1,0))) -> 0 | P48: =IF($B48="","",SUMIFS('Finanças'!$F$10:$F$1509,'Finanças'!$C$10:$C$1509,"Receita",'Finanças'!$D$10:$D$1509,$B48,'Finanças'!$B$10:$B$1509,">="&DATE(Ano,12,1),'Finanças'!$B$10:$B$1509,"<="&DATE(Ano,12+1,0))) -> 0 | Q48: =IF(B48="","",SUM(E48:P48)) -> 0 | R48: =IF(B48="","",SUMPRODUCT((COLUMN($E48:$P48)-COLUMN($E48)+1<=RefMes)*$E48:$P48)/RefMes) -> 0 | S48: =IF(B48="","",INDEX(E48:P48,RefMes)) -> 0 | T48: =IF(OR(B48="",N(D48)=0),"",S48/D48) | U48: =IF(T48="","",IF(T48>=1,"✔ Atingido","▲ "&ROUND(T48*100,0)&"%"))
B49: =IF('Config'!$K$7="","",'Config'!$K$7) -> Renda extra / freelance | E49: =IF($B49="","",SUMIFS('Finanças'!$F$10:$F$1509,'Finanças'!$C$10:$C$1509,"Receita",'Finanças'!$D$10:$D$1509,$B49,'Finanças'!$B$10:$B$1509,">="&DATE(Ano,1,1),'Finanças'!$B$10:$B$1509,"<="&DATE(Ano,1+1,0))) -> 0 | F49: =IF($B49="","",SUMIFS('Finanças'!$F$10:$F$1509,'Finanças'!$C$10:$C$1509,"Receita",'Finanças'!$D$10:$D$1509,$B49,'Finanças'!$B$10:$B$1509,">="&DATE(Ano,2,1),'Finanças'!$B$10:$B$1509,"<="&DATE(Ano,2+1,0))) -> 0 | G49: =IF($B49="","",SUMIFS('Finanças'!$F$10:$F$1509,'Finanças'!$C$10:$C$1509,"Receita",'Finanças'!$D$10:$D$1509,$B49,'Finanças'!$B$10:$B$1509,">="&DATE(Ano,3,1),'Finanças'!$B$10:$B$1509,"<="&DATE(Ano,3+1,0))) -> 0 | H49: =IF($B49="","",SUMIFS('Finanças'!$F$10:$F$1509,'Finanças'!$C$10:$C$1509,"Receita",'Finanças'!$D$10:$D$1509,$B49,'Finanças'!$B$10:$B$1509,">="&DATE(Ano,4,1),'Finanças'!$B$10:$B$1509,"<="&DATE(Ano,4+1,0))) -> 0 | I49: =IF($B49="","",SUMIFS('Finanças'!$F$10:$F$1509,'Finanças'!$C$10:$C$1509,"Receita",'Finanças'!$D$10:$D$1509,$B49,'Finanças'!$B$10:$B$1509,">="&DATE(Ano,5,1),'Finanças'!$B$10:$B$1509,"<="&DATE(Ano,5+1,0))) -> 0 | J49: =IF($B49="","",SUMIFS('Finanças'!$F$10:$F$1509,'Finanças'!$C$10:$C$1509,"Receita",'Finanças'!$D$10:$D$1509,$B49,'Finanças'!$B$10:$B$1509,">="&DATE(Ano,6,1),'Finanças'!$B$10:$B$1509,"<="&DATE(Ano,6+1,0))) -> 0 | K49: =IF($B49="","",SUMIFS('Finanças'!$F$10:$F$1509,'Finanças'!$C$10:$C$1509,"Receita",'Finanças'!$D$10:$D$1509,$B49,'Finanças'!$B$10:$B$1509,">="&DATE(Ano,7,1),'Finanças'!$B$10:$B$1509,"<="&DATE(Ano,7+1,0))) -> 0 | L49: =IF($B49="","",SUMIFS('Finanças'!$F$10:$F$1509,'Finanças'!$C$10:$C$1509,"Receita",'Finanças'!$D$10:$D$1509,$B49,'Finanças'!$B$10:$B$1509,">="&DATE(Ano,8,1),'Finanças'!$B$10:$B$1509,"<="&DATE(Ano,8+1,0))) -> 0 | M49: =IF($B49="","",SUMIFS('Finanças'!$F$10:$F$1509,'Finanças'!$C$10:$C$1509,"Receita",'Finanças'!$D$10:$D$1509,$B49,'Finanças'!$B$10:$B$1509,">="&DATE(Ano,9,1),'Finanças'!$B$10:$B$1509,"<="&DATE(Ano,9+1,0))) -> 0 | N49: =IF($B49="","",SUMIFS('Finanças'!$F$10:$F$1509,'Finanças'!$C$10:$C$1509,"Receita",'Finanças'!$D$10:$D$1509,$B49,'Finanças'!$B$10:$B$1509,">="&DATE(Ano,10,1),'Finanças'!$B$10:$B$1509,"<="&DATE(Ano,10+1,0))) -> 0 | O49: =IF($B49="","",SUMIFS('Finanças'!$F$10:$F$1509,'Finanças'!$C$10:$C$1509,"Receita",'Finanças'!$D$10:$D$1509,$B49,'Finanças'!$B$10:$B$1509,">="&DATE(Ano,11,1),'Finanças'!$B$10:$B$1509,"<="&DATE(Ano,11+1,0))) -> 0 | P49: =IF($B49="","",SUMIFS('Finanças'!$F$10:$F$1509,'Finanças'!$C$10:$C$1509,"Receita",'Finanças'!$D$10:$D$1509,$B49,'Finanças'!$B$10:$B$1509,">="&DATE(Ano,12,1),'Finanças'!$B$10:$B$1509,"<="&DATE(Ano,12+1,0))) -> 0 | Q49: =IF(B49="","",SUM(E49:P49)) -> 0 | R49: =IF(B49="","",SUMPRODUCT((COLUMN($E49:$P49)-COLUMN($E49)+1<=RefMes)*$E49:$P49)/RefMes) -> 0 | S49: =IF(B49="","",INDEX(E49:P49,RefMes)) -> 0 | T49: =IF(OR(B49="",N(D49)=0),"",S49/D49) | U49: =IF(T49="","",IF(T49>=1,"✔ Atingido","▲ "&ROUND(T49*100,0)&"%"))
B50: =IF('Config'!$K$8="","",'Config'!$K$8) -> Benefícios | E50: =IF($B50="","",SUMIFS('Finanças'!$F$10:$F$1509,'Finanças'!$C$10:$C$1509,"Receita",'Finanças'!$D$10:$D$1509,$B50,'Finanças'!$B$10:$B$1509,">="&DATE(Ano,1,1),'Finanças'!$B$10:$B$1509,"<="&DATE(Ano,1+1,0))) -> 0 | F50: =IF($B50="","",SUMIFS('Finanças'!$F$10:$F$1509,'Finanças'!$C$10:$C$1509,"Receita",'Finanças'!$D$10:$D$1509,$B50,'Finanças'!$B$10:$B$1509,">="&DATE(Ano,2,1),'Finanças'!$B$10:$B$1509,"<="&DATE(Ano,2+1,0))) -> 0 | G50: =IF($B50="","",SUMIFS('Finanças'!$F$10:$F$1509,'Finanças'!$C$10:$C$1509,"Receita",'Finanças'!$D$10:$D$1509,$B50,'Finanças'!$B$10:$B$1509,">="&DATE(Ano,3,1),'Finanças'!$B$10:$B$1509,"<="&DATE(Ano,3+1,0))) -> 0 | H50: =IF($B50="","",SUMIFS('Finanças'!$F$10:$F$1509,'Finanças'!$C$10:$C$1509,"Receita",'Finanças'!$D$10:$D$1509,$B50,'Finanças'!$B$10:$B$1509,">="&DATE(Ano,4,1),'Finanças'!$B$10:$B$1509,"<="&DATE(Ano,4+1,0))) -> 0 | I50: =IF($B50="","",SUMIFS('Finanças'!$F$10:$F$1509,'Finanças'!$C$10:$C$1509,"Receita",'Finanças'!$D$10:$D$1509,$B50,'Finanças'!$B$10:$B$1509,">="&DATE(Ano,5,1),'Finanças'!$B$10:$B$1509,"<="&DATE(Ano,5+1,0))) -> 0 | J50: =IF($B50="","",SUMIFS('Finanças'!$F$10:$F$1509,'Finanças'!$C$10:$C$1509,"Receita",'Finanças'!$D$10:$D$1509,$B50,'Finanças'!$B$10:$B$1509,">="&DATE(Ano,6,1),'Finanças'!$B$10:$B$1509,"<="&DATE(Ano,6+1,0))) -> 0 | K50: =IF($B50="","",SUMIFS('Finanças'!$F$10:$F$1509,'Finanças'!$C$10:$C$1509,"Receita",'Finanças'!$D$10:$D$1509,$B50,'Finanças'!$B$10:$B$1509,">="&DATE(Ano,7,1),'Finanças'!$B$10:$B$1509,"<="&DATE(Ano,7+1,0))) -> 0 | L50: =IF($B50="","",SUMIFS('Finanças'!$F$10:$F$1509,'Finanças'!$C$10:$C$1509,"Receita",'Finanças'!$D$10:$D$1509,$B50,'Finanças'!$B$10:$B$1509,">="&DATE(Ano,8,1),'Finanças'!$B$10:$B$1509,"<="&DATE(Ano,8+1,0))) -> 0 | M50: =IF($B50="","",SUMIFS('Finanças'!$F$10:$F$1509,'Finanças'!$C$10:$C$1509,"Receita",'Finanças'!$D$10:$D$1509,$B50,'Finanças'!$B$10:$B$1509,">="&DATE(Ano,9,1),'Finanças'!$B$10:$B$1509,"<="&DATE(Ano,9+1,0))) -> 0 | N50: =IF($B50="","",SUMIFS('Finanças'!$F$10:$F$1509,'Finanças'!$C$10:$C$1509,"Receita",'Finanças'!$D$10:$D$1509,$B50,'Finanças'!$B$10:$B$1509,">="&DATE(Ano,10,1),'Finanças'!$B$10:$B$1509,"<="&DATE(Ano,10+1,0))) -> 0 | O50: =IF($B50="","",SUMIFS('Finanças'!$F$10:$F$1509,'Finanças'!$C$10:$C$1509,"Receita",'Finanças'!$D$10:$D$1509,$B50,'Finanças'!$B$10:$B$1509,">="&DATE(Ano,11,1),'Finanças'!$B$10:$B$1509,"<="&DATE(Ano,11+1,0))) -> 0 | P50: =IF($B50="","",SUMIFS('Finanças'!$F$10:$F$1509,'Finanças'!$C$10:$C$1509,"Receita",'Finanças'!$D$10:$D$1509,$B50,'Finanças'!$B$10:$B$1509,">="&DATE(Ano,12,1),'Finanças'!$B$10:$B$1509,"<="&DATE(Ano,12+1,0))) -> 0 | Q50: =IF(B50="","",SUM(E50:P50)) -> 0 | R50: =IF(B50="","",SUMPRODUCT((COLUMN($E50:$P50)-COLUMN($E50)+1<=RefMes)*$E50:$P50)/RefMes) -> 0 | S50: =IF(B50="","",INDEX(E50:P50,RefMes)) -> 0 | T50: =IF(OR(B50="",N(D50)=0),"",S50/D50) | U50: =IF(T50="","",IF(T50>=1,"✔ Atingido","▲ "&ROUND(T50*100,0)&"%"))
B51: =IF('Config'!$K$9="","",'Config'!$K$9) -> Rendimentos | E51: =IF($B51="","",SUMIFS('Finanças'!$F$10:$F$1509,'Finanças'!$C$10:$C$1509,"Receita",'Finanças'!$D$10:$D$1509,$B51,'Finanças'!$B$10:$B$1509,">="&DATE(Ano,1,1),'Finanças'!$B$10:$B$1509,"<="&DATE(Ano,1+1,0))) -> 0 | F51: =IF($B51="","",SUMIFS('Finanças'!$F$10:$F$1509,'Finanças'!$C$10:$C$1509,"Receita",'Finanças'!$D$10:$D$1509,$B51,'Finanças'!$B$10:$B$1509,">="&DATE(Ano,2,1),'Finanças'!$B$10:$B$1509,"<="&DATE(Ano,2+1,0))) -> 0 | G51: =IF($B51="","",SUMIFS('Finanças'!$F$10:$F$1509,'Finanças'!$C$10:$C$1509,"Receita",'Finanças'!$D$10:$D$1509,$B51,'Finanças'!$B$10:$B$1509,">="&DATE(Ano,3,1),'Finanças'!$B$10:$B$1509,"<="&DATE(Ano,3+1,0))) -> 0 | H51: =IF($B51="","",SUMIFS('Finanças'!$F$10:$F$1509,'Finanças'!$C$10:$C$1509,"Receita",'Finanças'!$D$10:$D$1509,$B51,'Finanças'!$B$10:$B$1509,">="&DATE(Ano,4,1),'Finanças'!$B$10:$B$1509,"<="&DATE(Ano,4+1,0))) -> 0 | I51: =IF($B51="","",SUMIFS('Finanças'!$F$10:$F$1509,'Finanças'!$C$10:$C$1509,"Receita",'Finanças'!$D$10:$D$1509,$B51,'Finanças'!$B$10:$B$1509,">="&DATE(Ano,5,1),'Finanças'!$B$10:$B$1509,"<="&DATE(Ano,5+1,0))) -> 0 | J51: =IF($B51="","",SUMIFS('Finanças'!$F$10:$F$1509,'Finanças'!$C$10:$C$1509,"Receita",'Finanças'!$D$10:$D$1509,$B51,'Finanças'!$B$10:$B$1509,">="&DATE(Ano,6,1),'Finanças'!$B$10:$B$1509,"<="&DATE(Ano,6+1,0))) -> 0 | K51: =IF($B51="","",SUMIFS('Finanças'!$F$10:$F$1509,'Finanças'!$C$10:$C$1509,"Receita",'Finanças'!$D$10:$D$1509,$B51,'Finanças'!$B$10:$B$1509,">="&DATE(Ano,7,1),'Finanças'!$B$10:$B$1509,"<="&DATE(Ano,7+1,0))) -> 0 | L51: =IF($B51="","",SUMIFS('Finanças'!$F$10:$F$1509,'Finanças'!$C$10:$C$1509,"Receita",'Finanças'!$D$10:$D$1509,$B51,'Finanças'!$B$10:$B$1509,">="&DATE(Ano,8,1),'Finanças'!$B$10:$B$1509,"<="&DATE(Ano,8+1,0))) -> 0 | M51: =IF($B51="","",SUMIFS('Finanças'!$F$10:$F$1509,'Finanças'!$C$10:$C$1509,"Receita",'Finanças'!$D$10:$D$1509,$B51,'Finanças'!$B$10:$B$1509,">="&DATE(Ano,9,1),'Finanças'!$B$10:$B$1509,"<="&DATE(Ano,9+1,0))) -> 0 | N51: =IF($B51="","",SUMIFS('Finanças'!$F$10:$F$1509,'Finanças'!$C$10:$C$1509,"Receita",'Finanças'!$D$10:$D$1509,$B51,'Finanças'!$B$10:$B$1509,">="&DATE(Ano,10,1),'Finanças'!$B$10:$B$1509,"<="&DATE(Ano,10+1,0))) -> 0 | O51: =IF($B51="","",SUMIFS('Finanças'!$F$10:$F$1509,'Finanças'!$C$10:$C$1509,"Receita",'Finanças'!$D$10:$D$1509,$B51,'Finanças'!$B$10:$B$1509,">="&DATE(Ano,11,1),'Finanças'!$B$10:$B$1509,"<="&DATE(Ano,11+1,0))) -> 0 | P51: =IF($B51="","",SUMIFS('Finanças'!$F$10:$F$1509,'Finanças'!$C$10:$C$1509,"Receita",'Finanças'!$D$10:$D$1509,$B51,'Finanças'!$B$10:$B$1509,">="&DATE(Ano,12,1),'Finanças'!$B$10:$B$1509,"<="&DATE(Ano,12+1,0))) -> 0 | Q51: =IF(B51="","",SUM(E51:P51)) -> 0 | R51: =IF(B51="","",SUMPRODUCT((COLUMN($E51:$P51)-COLUMN($E51)+1<=RefMes)*$E51:$P51)/RefMes) -> 0 | S51: =IF(B51="","",INDEX(E51:P51,RefMes)) -> 0 | T51: =IF(OR(B51="",N(D51)=0),"",S51/D51) | U51: =IF(T51="","",IF(T51>=1,"✔ Atingido","▲ "&ROUND(T51*100,0)&"%"))
B52: =IF('Config'!$K$10="","",'Config'!$K$10) -> Reembolsos | E52: =IF($B52="","",SUMIFS('Finanças'!$F$10:$F$1509,'Finanças'!$C$10:$C$1509,"Receita",'Finanças'!$D$10:$D$1509,$B52,'Finanças'!$B$10:$B$1509,">="&DATE(Ano,1,1),'Finanças'!$B$10:$B$1509,"<="&DATE(Ano,1+1,0))) -> 0 | F52: =IF($B52="","",SUMIFS('Finanças'!$F$10:$F$1509,'Finanças'!$C$10:$C$1509,"Receita",'Finanças'!$D$10:$D$1509,$B52,'Finanças'!$B$10:$B$1509,">="&DATE(Ano,2,1),'Finanças'!$B$10:$B$1509,"<="&DATE(Ano,2+1,0))) -> 0 | G52: =IF($B52="","",SUMIFS('Finanças'!$F$10:$F$1509,'Finanças'!$C$10:$C$1509,"Receita",'Finanças'!$D$10:$D$1509,$B52,'Finanças'!$B$10:$B$1509,">="&DATE(Ano,3,1),'Finanças'!$B$10:$B$1509,"<="&DATE(Ano,3+1,0))) -> 0 | H52: =IF($B52="","",SUMIFS('Finanças'!$F$10:$F$1509,'Finanças'!$C$10:$C$1509,"Receita",'Finanças'!$D$10:$D$1509,$B52,'Finanças'!$B$10:$B$1509,">="&DATE(Ano,4,1),'Finanças'!$B$10:$B$1509,"<="&DATE(Ano,4+1,0))) -> 0 | I52: =IF($B52="","",SUMIFS('Finanças'!$F$10:$F$1509,'Finanças'!$C$10:$C$1509,"Receita",'Finanças'!$D$10:$D$1509,$B52,'Finanças'!$B$10:$B$1509,">="&DATE(Ano,5,1),'Finanças'!$B$10:$B$1509,"<="&DATE(Ano,5+1,0))) -> 0 | J52: =IF($B52="","",SUMIFS('Finanças'!$F$10:$F$1509,'Finanças'!$C$10:$C$1509,"Receita",'Finanças'!$D$10:$D$1509,$B52,'Finanças'!$B$10:$B$1509,">="&DATE(Ano,6,1),'Finanças'!$B$10:$B$1509,"<="&DATE(Ano,6+1,0))) -> 0 | K52: =IF($B52="","",SUMIFS('Finanças'!$F$10:$F$1509,'Finanças'!$C$10:$C$1509,"Receita",'Finanças'!$D$10:$D$1509,$B52,'Finanças'!$B$10:$B$1509,">="&DATE(Ano,7,1),'Finanças'!$B$10:$B$1509,"<="&DATE(Ano,7+1,0))) -> 0 | L52: =IF($B52="","",SUMIFS('Finanças'!$F$10:$F$1509,'Finanças'!$C$10:$C$1509,"Receita",'Finanças'!$D$10:$D$1509,$B52,'Finanças'!$B$10:$B$1509,">="&DATE(Ano,8,1),'Finanças'!$B$10:$B$1509,"<="&DATE(Ano,8+1,0))) -> 0 | M52: =IF($B52="","",SUMIFS('Finanças'!$F$10:$F$1509,'Finanças'!$C$10:$C$1509,"Receita",'Finanças'!$D$10:$D$1509,$B52,'Finanças'!$B$10:$B$1509,">="&DATE(Ano,9,1),'Finanças'!$B$10:$B$1509,"<="&DATE(Ano,9+1,0))) -> 0 | N52: =IF($B52="","",SUMIFS('Finanças'!$F$10:$F$1509,'Finanças'!$C$10:$C$1509,"Receita",'Finanças'!$D$10:$D$1509,$B52,'Finanças'!$B$10:$B$1509,">="&DATE(Ano,10,1),'Finanças'!$B$10:$B$1509,"<="&DATE(Ano,10+1,0))) -> 0 | O52: =IF($B52="","",SUMIFS('Finanças'!$F$10:$F$1509,'Finanças'!$C$10:$C$1509,"Receita",'Finanças'!$D$10:$D$1509,$B52,'Finanças'!$B$10:$B$1509,">="&DATE(Ano,11,1),'Finanças'!$B$10:$B$1509,"<="&DATE(Ano,11+1,0))) -> 0 | P52: =IF($B52="","",SUMIFS('Finanças'!$F$10:$F$1509,'Finanças'!$C$10:$C$1509,"Receita",'Finanças'!$D$10:$D$1509,$B52,'Finanças'!$B$10:$B$1509,">="&DATE(Ano,12,1),'Finanças'!$B$10:$B$1509,"<="&DATE(Ano,12+1,0))) -> 0 | Q52: =IF(B52="","",SUM(E52:P52)) -> 0 | R52: =IF(B52="","",SUMPRODUCT((COLUMN($E52:$P52)-COLUMN($E52)+1<=RefMes)*$E52:$P52)/RefMes) -> 0 | S52: =IF(B52="","",INDEX(E52:P52,RefMes)) -> 0 | T52: =IF(OR(B52="",N(D52)=0),"",S52/D52) | U52: =IF(T52="","",IF(T52>=1,"✔ Atingido","▲ "&ROUND(T52*100,0)&"%"))
B53: =IF('Config'!$K$11="","",'Config'!$K$11) -> Presentes recebidos | E53: =IF($B53="","",SUMIFS('Finanças'!$F$10:$F$1509,'Finanças'!$C$10:$C$1509,"Receita",'Finanças'!$D$10:$D$1509,$B53,'Finanças'!$B$10:$B$1509,">="&DATE(Ano,1,1),'Finanças'!$B$10:$B$1509,"<="&DATE(Ano,1+1,0))) -> 0 | F53: =IF($B53="","",SUMIFS('Finanças'!$F$10:$F$1509,'Finanças'!$C$10:$C$1509,"Receita",'Finanças'!$D$10:$D$1509,$B53,'Finanças'!$B$10:$B$1509,">="&DATE(Ano,2,1),'Finanças'!$B$10:$B$1509,"<="&DATE(Ano,2+1,0))) -> 0 | G53: =IF($B53="","",SUMIFS('Finanças'!$F$10:$F$1509,'Finanças'!$C$10:$C$1509,"Receita",'Finanças'!$D$10:$D$1509,$B53,'Finanças'!$B$10:$B$1509,">="&DATE(Ano,3,1),'Finanças'!$B$10:$B$1509,"<="&DATE(Ano,3+1,0))) -> 0 | H53: =IF($B53="","",SUMIFS('Finanças'!$F$10:$F$1509,'Finanças'!$C$10:$C$1509,"Receita",'Finanças'!$D$10:$D$1509,$B53,'Finanças'!$B$10:$B$1509,">="&DATE(Ano,4,1),'Finanças'!$B$10:$B$1509,"<="&DATE(Ano,4+1,0))) -> 0 | I53: =IF($B53="","",SUMIFS('Finanças'!$F$10:$F$1509,'Finanças'!$C$10:$C$1509,"Receita",'Finanças'!$D$10:$D$1509,$B53,'Finanças'!$B$10:$B$1509,">="&DATE(Ano,5,1),'Finanças'!$B$10:$B$1509,"<="&DATE(Ano,5+1,0))) -> 0 | J53: =IF($B53="","",SUMIFS('Finanças'!$F$10:$F$1509,'Finanças'!$C$10:$C$1509,"Receita",'Finanças'!$D$10:$D$1509,$B53,'Finanças'!$B$10:$B$1509,">="&DATE(Ano,6,1),'Finanças'!$B$10:$B$1509,"<="&DATE(Ano,6+1,0))) -> 0 | K53: =IF($B53="","",SUMIFS('Finanças'!$F$10:$F$1509,'Finanças'!$C$10:$C$1509,"Receita",'Finanças'!$D$10:$D$1509,$B53,'Finanças'!$B$10:$B$1509,">="&DATE(Ano,7,1),'Finanças'!$B$10:$B$1509,"<="&DATE(Ano,7+1,0))) -> 0 | L53: =IF($B53="","",SUMIFS('Finanças'!$F$10:$F$1509,'Finanças'!$C$10:$C$1509,"Receita",'Finanças'!$D$10:$D$1509,$B53,'Finanças'!$B$10:$B$1509,">="&DATE(Ano,8,1),'Finanças'!$B$10:$B$1509,"<="&DATE(Ano,8+1,0))) -> 0 | M53: =IF($B53="","",SUMIFS('Finanças'!$F$10:$F$1509,'Finanças'!$C$10:$C$1509,"Receita",'Finanças'!$D$10:$D$1509,$B53,'Finanças'!$B$10:$B$1509,">="&DATE(Ano,9,1),'Finanças'!$B$10:$B$1509,"<="&DATE(Ano,9+1,0))) -> 0 | N53: =IF($B53="","",SUMIFS('Finanças'!$F$10:$F$1509,'Finanças'!$C$10:$C$1509,"Receita",'Finanças'!$D$10:$D$1509,$B53,'Finanças'!$B$10:$B$1509,">="&DATE(Ano,10,1),'Finanças'!$B$10:$B$1509,"<="&DATE(Ano,10+1,0))) -> 0 | O53: =IF($B53="","",SUMIFS('Finanças'!$F$10:$F$1509,'Finanças'!$C$10:$C$1509,"Receita",'Finanças'!$D$10:$D$1509,$B53,'Finanças'!$B$10:$B$1509,">="&DATE(Ano,11,1),'Finanças'!$B$10:$B$1509,"<="&DATE(Ano,11+1,0))) -> 0 | P53: =IF($B53="","",SUMIFS('Finanças'!$F$10:$F$1509,'Finanças'!$C$10:$C$1509,"Receita",'Finanças'!$D$10:$D$1509,$B53,'Finanças'!$B$10:$B$1509,">="&DATE(Ano,12,1),'Finanças'!$B$10:$B$1509,"<="&DATE(Ano,12+1,0))) -> 0 | Q53: =IF(B53="","",SUM(E53:P53)) -> 0 | R53: =IF(B53="","",SUMPRODUCT((COLUMN($E53:$P53)-COLUMN($E53)+1<=RefMes)*$E53:$P53)/RefMes) -> 0 | S53: =IF(B53="","",INDEX(E53:P53,RefMes)) -> 0 | T53: =IF(OR(B53="",N(D53)=0),"",S53/D53) | U53: =IF(T53="","",IF(T53>=1,"✔ Atingido","▲ "&ROUND(T53*100,0)&"%"))
B54: =IF('Config'!$K$12="","",'Config'!$K$12) -> Outras receitas | E54: =IF($B54="","",SUMIFS('Finanças'!$F$10:$F$1509,'Finanças'!$C$10:$C$1509,"Receita",'Finanças'!$D$10:$D$1509,$B54,'Finanças'!$B$10:$B$1509,">="&DATE(Ano,1,1),'Finanças'!$B$10:$B$1509,"<="&DATE(Ano,1+1,0))) -> 0 | F54: =IF($B54="","",SUMIFS('Finanças'!$F$10:$F$1509,'Finanças'!$C$10:$C$1509,"Receita",'Finanças'!$D$10:$D$1509,$B54,'Finanças'!$B$10:$B$1509,">="&DATE(Ano,2,1),'Finanças'!$B$10:$B$1509,"<="&DATE(Ano,2+1,0))) -> 0 | G54: =IF($B54="","",SUMIFS('Finanças'!$F$10:$F$1509,'Finanças'!$C$10:$C$1509,"Receita",'Finanças'!$D$10:$D$1509,$B54,'Finanças'!$B$10:$B$1509,">="&DATE(Ano,3,1),'Finanças'!$B$10:$B$1509,"<="&DATE(Ano,3+1,0))) -> 0 | H54: =IF($B54="","",SUMIFS('Finanças'!$F$10:$F$1509,'Finanças'!$C$10:$C$1509,"Receita",'Finanças'!$D$10:$D$1509,$B54,'Finanças'!$B$10:$B$1509,">="&DATE(Ano,4,1),'Finanças'!$B$10:$B$1509,"<="&DATE(Ano,4+1,0))) -> 0 | I54: =IF($B54="","",SUMIFS('Finanças'!$F$10:$F$1509,'Finanças'!$C$10:$C$1509,"Receita",'Finanças'!$D$10:$D$1509,$B54,'Finanças'!$B$10:$B$1509,">="&DATE(Ano,5,1),'Finanças'!$B$10:$B$1509,"<="&DATE(Ano,5+1,0))) -> 0 | J54: =IF($B54="","",SUMIFS('Finanças'!$F$10:$F$1509,'Finanças'!$C$10:$C$1509,"Receita",'Finanças'!$D$10:$D$1509,$B54,'Finanças'!$B$10:$B$1509,">="&DATE(Ano,6,1),'Finanças'!$B$10:$B$1509,"<="&DATE(Ano,6+1,0))) -> 0 | K54: =IF($B54="","",SUMIFS('Finanças'!$F$10:$F$1509,'Finanças'!$C$10:$C$1509,"Receita",'Finanças'!$D$10:$D$1509,$B54,'Finanças'!$B$10:$B$1509,">="&DATE(Ano,7,1),'Finanças'!$B$10:$B$1509,"<="&DATE(Ano,7+1,0))) -> 0 | L54: =IF($B54="","",SUMIFS('Finanças'!$F$10:$F$1509,'Finanças'!$C$10:$C$1509,"Receita",'Finanças'!$D$10:$D$1509,$B54,'Finanças'!$B$10:$B$1509,">="&DATE(Ano,8,1),'Finanças'!$B$10:$B$1509,"<="&DATE(Ano,8+1,0))) -> 0 | M54: =IF($B54="","",SUMIFS('Finanças'!$F$10:$F$1509,'Finanças'!$C$10:$C$1509,"Receita",'Finanças'!$D$10:$D$1509,$B54,'Finanças'!$B$10:$B$1509,">="&DATE(Ano,9,1),'Finanças'!$B$10:$B$1509,"<="&DATE(Ano,9+1,0))) -> 0 | N54: =IF($B54="","",SUMIFS('Finanças'!$F$10:$F$1509,'Finanças'!$C$10:$C$1509,"Receita",'Finanças'!$D$10:$D$1509,$B54,'Finanças'!$B$10:$B$1509,">="&DATE(Ano,10,1),'Finanças'!$B$10:$B$1509,"<="&DATE(Ano,10+1,0))) -> 0 | O54: =IF($B54="","",SUMIFS('Finanças'!$F$10:$F$1509,'Finanças'!$C$10:$C$1509,"Receita",'Finanças'!$D$10:$D$1509,$B54,'Finanças'!$B$10:$B$1509,">="&DATE(Ano,11,1),'Finanças'!$B$10:$B$1509,"<="&DATE(Ano,11+1,0))) -> 0 | P54: =IF($B54="","",SUMIFS('Finanças'!$F$10:$F$1509,'Finanças'!$C$10:$C$1509,"Receita",'Finanças'!$D$10:$D$1509,$B54,'Finanças'!$B$10:$B$1509,">="&DATE(Ano,12,1),'Finanças'!$B$10:$B$1509,"<="&DATE(Ano,12+1,0))) -> 0 | Q54: =IF(B54="","",SUM(E54:P54)) -> 0 | R54: =IF(B54="","",SUMPRODUCT((COLUMN($E54:$P54)-COLUMN($E54)+1<=RefMes)*$E54:$P54)/RefMes) -> 0 | S54: =IF(B54="","",INDEX(E54:P54,RefMes)) -> 0 | T54: =IF(OR(B54="",N(D54)=0),"",S54/D54) | U54: =IF(T54="","",IF(T54>=1,"✔ Atingido","▲ "&ROUND(T54*100,0)&"%"))
B55: =IF('Config'!$K$13="","",'Config'!$K$13) | E55: =IF($B55="","",SUMIFS('Finanças'!$F$10:$F$1509,'Finanças'!$C$10:$C$1509,"Receita",'Finanças'!$D$10:$D$1509,$B55,'Finanças'!$B$10:$B$1509,">="&DATE(Ano,1,1),'Finanças'!$B$10:$B$1509,"<="&DATE(Ano,1+1,0))) | F55: =IF($B55="","",SUMIFS('Finanças'!$F$10:$F$1509,'Finanças'!$C$10:$C$1509,"Receita",'Finanças'!$D$10:$D$1509,$B55,'Finanças'!$B$10:$B$1509,">="&DATE(Ano,2,1),'Finanças'!$B$10:$B$1509,"<="&DATE(Ano,2+1,0))) | G55: =IF($B55="","",SUMIFS('Finanças'!$F$10:$F$1509,'Finanças'!$C$10:$C$1509,"Receita",'Finanças'!$D$10:$D$1509,$B55,'Finanças'!$B$10:$B$1509,">="&DATE(Ano,3,1),'Finanças'!$B$10:$B$1509,"<="&DATE(Ano,3+1,0))) | H55: =IF($B55="","",SUMIFS('Finanças'!$F$10:$F$1509,'Finanças'!$C$10:$C$1509,"Receita",'Finanças'!$D$10:$D$1509,$B55,'Finanças'!$B$10:$B$1509,">="&DATE(Ano,4,1),'Finanças'!$B$10:$B$1509,"<="&DATE(Ano,4+1,0))) | I55: =IF($B55="","",SUMIFS('Finanças'!$F$10:$F$1509,'Finanças'!$C$10:$C$1509,"Receita",'Finanças'!$D$10:$D$1509,$B55,'Finanças'!$B$10:$B$1509,">="&DATE(Ano,5,1),'Finanças'!$B$10:$B$1509,"<="&DATE(Ano,5+1,0))) | J55: =IF($B55="","",SUMIFS('Finanças'!$F$10:$F$1509,'Finanças'!$C$10:$C$1509,"Receita",'Finanças'!$D$10:$D$1509,$B55,'Finanças'!$B$10:$B$1509,">="&DATE(Ano,6,1),'Finanças'!$B$10:$B$1509,"<="&DATE(Ano,6+1,0))) | K55: =IF($B55="","",SUMIFS('Finanças'!$F$10:$F$1509,'Finanças'!$C$10:$C$1509,"Receita",'Finanças'!$D$10:$D$1509,$B55,'Finanças'!$B$10:$B$1509,">="&DATE(Ano,7,1),'Finanças'!$B$10:$B$1509,"<="&DATE(Ano,7+1,0))) | L55: =IF($B55="","",SUMIFS('Finanças'!$F$10:$F$1509,'Finanças'!$C$10:$C$1509,"Receita",'Finanças'!$D$10:$D$1509,$B55,'Finanças'!$B$10:$B$1509,">="&DATE(Ano,8,1),'Finanças'!$B$10:$B$1509,"<="&DATE(Ano,8+1,0))) | M55: =IF($B55="","",SUMIFS('Finanças'!$F$10:$F$1509,'Finanças'!$C$10:$C$1509,"Receita",'Finanças'!$D$10:$D$1509,$B55,'Finanças'!$B$10:$B$1509,">="&DATE(Ano,9,1),'Finanças'!$B$10:$B$1509,"<="&DATE(Ano,9+1,0))) | N55: =IF($B55="","",SUMIFS('Finanças'!$F$10:$F$1509,'Finanças'!$C$10:$C$1509,"Receita",'Finanças'!$D$10:$D$1509,$B55,'Finanças'!$B$10:$B$1509,">="&DATE(Ano,10,1),'Finanças'!$B$10:$B$1509,"<="&DATE(Ano,10+1,0))) | O55: =IF($B55="","",SUMIFS('Finanças'!$F$10:$F$1509,'Finanças'!$C$10:$C$1509,"Receita",'Finanças'!$D$10:$D$1509,$B55,'Finanças'!$B$10:$B$1509,">="&DATE(Ano,11,1),'Finanças'!$B$10:$B$1509,"<="&DATE(Ano,11+1,0))) | P55: =IF($B55="","",SUMIFS('Finanças'!$F$10:$F$1509,'Finanças'!$C$10:$C$1509,"Receita",'Finanças'!$D$10:$D$1509,$B55,'Finanças'!$B$10:$B$1509,">="&DATE(Ano,12,1),'Finanças'!$B$10:$B$1509,"<="&DATE(Ano,12+1,0))) | Q55: =IF(B55="","",SUM(E55:P55)) | R55: =IF(B55="","",SUMPRODUCT((COLUMN($E55:$P55)-COLUMN($E55)+1<=RefMes)*$E55:$P55)/RefMes) | S55: =IF(B55="","",INDEX(E55:P55,RefMes)) | T55: =IF(OR(B55="",N(D55)=0),"",S55/D55) | U55: =IF(T55="","",IF(T55>=1,"✔ Atingido","▲ "&ROUND(T55*100,0)&"%"))
B56: =IF('Config'!$K$14="","",'Config'!$K$14) | E56: =IF($B56="","",SUMIFS('Finanças'!$F$10:$F$1509,'Finanças'!$C$10:$C$1509,"Receita",'Finanças'!$D$10:$D$1509,$B56,'Finanças'!$B$10:$B$1509,">="&DATE(Ano,1,1),'Finanças'!$B$10:$B$1509,"<="&DATE(Ano,1+1,0))) | F56: =IF($B56="","",SUMIFS('Finanças'!$F$10:$F$1509,'Finanças'!$C$10:$C$1509,"Receita",'Finanças'!$D$10:$D$1509,$B56,'Finanças'!$B$10:$B$1509,">="&DATE(Ano,2,1),'Finanças'!$B$10:$B$1509,"<="&DATE(Ano,2+1,0))) | G56: =IF($B56="","",SUMIFS('Finanças'!$F$10:$F$1509,'Finanças'!$C$10:$C$1509,"Receita",'Finanças'!$D$10:$D$1509,$B56,'Finanças'!$B$10:$B$1509,">="&DATE(Ano,3,1),'Finanças'!$B$10:$B$1509,"<="&DATE(Ano,3+1,0))) | H56: =IF($B56="","",SUMIFS('Finanças'!$F$10:$F$1509,'Finanças'!$C$10:$C$1509,"Receita",'Finanças'!$D$10:$D$1509,$B56,'Finanças'!$B$10:$B$1509,">="&DATE(Ano,4,1),'Finanças'!$B$10:$B$1509,"<="&DATE(Ano,4+1,0))) | I56: =IF($B56="","",SUMIFS('Finanças'!$F$10:$F$1509,'Finanças'!$C$10:$C$1509,"Receita",'Finanças'!$D$10:$D$1509,$B56,'Finanças'!$B$10:$B$1509,">="&DATE(Ano,5,1),'Finanças'!$B$10:$B$1509,"<="&DATE(Ano,5+1,0))) | J56: =IF($B56="","",SUMIFS('Finanças'!$F$10:$F$1509,'Finanças'!$C$10:$C$1509,"Receita",'Finanças'!$D$10:$D$1509,$B56,'Finanças'!$B$10:$B$1509,">="&DATE(Ano,6,1),'Finanças'!$B$10:$B$1509,"<="&DATE(Ano,6+1,0))) | K56: =IF($B56="","",SUMIFS('Finanças'!$F$10:$F$1509,'Finanças'!$C$10:$C$1509,"Receita",'Finanças'!$D$10:$D$1509,$B56,'Finanças'!$B$10:$B$1509,">="&DATE(Ano,7,1),'Finanças'!$B$10:$B$1509,"<="&DATE(Ano,7+1,0))) | L56: =IF($B56="","",SUMIFS('Finanças'!$F$10:$F$1509,'Finanças'!$C$10:$C$1509,"Receita",'Finanças'!$D$10:$D$1509,$B56,'Finanças'!$B$10:$B$1509,">="&DATE(Ano,8,1),'Finanças'!$B$10:$B$1509,"<="&DATE(Ano,8+1,0))) | M56: =IF($B56="","",SUMIFS('Finanças'!$F$10:$F$1509,'Finanças'!$C$10:$C$1509,"Receita",'Finanças'!$D$10:$D$1509,$B56,'Finanças'!$B$10:$B$1509,">="&DATE(Ano,9,1),'Finanças'!$B$10:$B$1509,"<="&DATE(Ano,9+1,0))) | N56: =IF($B56="","",SUMIFS('Finanças'!$F$10:$F$1509,'Finanças'!$C$10:$C$1509,"Receita",'Finanças'!$D$10:$D$1509,$B56,'Finanças'!$B$10:$B$1509,">="&DATE(Ano,10,1),'Finanças'!$B$10:$B$1509,"<="&DATE(Ano,10+1,0))) | O56: =IF($B56="","",SUMIFS('Finanças'!$F$10:$F$1509,'Finanças'!$C$10:$C$1509,"Receita",'Finanças'!$D$10:$D$1509,$B56,'Finanças'!$B$10:$B$1509,">="&DATE(Ano,11,1),'Finanças'!$B$10:$B$1509,"<="&DATE(Ano,11+1,0))) | P56: =IF($B56="","",SUMIFS('Finanças'!$F$10:$F$1509,'Finanças'!$C$10:$C$1509,"Receita",'Finanças'!$D$10:$D$1509,$B56,'Finanças'!$B$10:$B$1509,">="&DATE(Ano,12,1),'Finanças'!$B$10:$B$1509,"<="&DATE(Ano,12+1,0))) | Q56: =IF(B56="","",SUM(E56:P56)) | R56: =IF(B56="","",SUMPRODUCT((COLUMN($E56:$P56)-COLUMN($E56)+1<=RefMes)*$E56:$P56)/RefMes) | S56: =IF(B56="","",INDEX(E56:P56,RefMes)) | T56: =IF(OR(B56="",N(D56)=0),"",S56/D56) | U56: =IF(T56="","",IF(T56>=1,"✔ Atingido","▲ "&ROUND(T56*100,0)&"%"))
B57: =IF('Config'!$K$15="","",'Config'!$K$15) | E57: =IF($B57="","",SUMIFS('Finanças'!$F$10:$F$1509,'Finanças'!$C$10:$C$1509,"Receita",'Finanças'!$D$10:$D$1509,$B57,'Finanças'!$B$10:$B$1509,">="&DATE(Ano,1,1),'Finanças'!$B$10:$B$1509,"<="&DATE(Ano,1+1,0))) | F57: =IF($B57="","",SUMIFS('Finanças'!$F$10:$F$1509,'Finanças'!$C$10:$C$1509,"Receita",'Finanças'!$D$10:$D$1509,$B57,'Finanças'!$B$10:$B$1509,">="&DATE(Ano,2,1),'Finanças'!$B$10:$B$1509,"<="&DATE(Ano,2+1,0))) | G57: =IF($B57="","",SUMIFS('Finanças'!$F$10:$F$1509,'Finanças'!$C$10:$C$1509,"Receita",'Finanças'!$D$10:$D$1509,$B57,'Finanças'!$B$10:$B$1509,">="&DATE(Ano,3,1),'Finanças'!$B$10:$B$1509,"<="&DATE(Ano,3+1,0))) | H57: =IF($B57="","",SUMIFS('Finanças'!$F$10:$F$1509,'Finanças'!$C$10:$C$1509,"Receita",'Finanças'!$D$10:$D$1509,$B57,'Finanças'!$B$10:$B$1509,">="&DATE(Ano,4,1),'Finanças'!$B$10:$B$1509,"<="&DATE(Ano,4+1,0))) | I57: =IF($B57="","",SUMIFS('Finanças'!$F$10:$F$1509,'Finanças'!$C$10:$C$1509,"Receita",'Finanças'!$D$10:$D$1509,$B57,'Finanças'!$B$10:$B$1509,">="&DATE(Ano,5,1),'Finanças'!$B$10:$B$1509,"<="&DATE(Ano,5+1,0))) | J57: =IF($B57="","",SUMIFS('Finanças'!$F$10:$F$1509,'Finanças'!$C$10:$C$1509,"Receita",'Finanças'!$D$10:$D$1509,$B57,'Finanças'!$B$10:$B$1509,">="&DATE(Ano,6,1),'Finanças'!$B$10:$B$1509,"<="&DATE(Ano,6+1,0))) | K57: =IF($B57="","",SUMIFS('Finanças'!$F$10:$F$1509,'Finanças'!$C$10:$C$1509,"Receita",'Finanças'!$D$10:$D$1509,$B57,'Finanças'!$B$10:$B$1509,">="&DATE(Ano,7,1),'Finanças'!$B$10:$B$1509,"<="&DATE(Ano,7+1,0))) | L57: =IF($B57="","",SUMIFS('Finanças'!$F$10:$F$1509,'Finanças'!$C$10:$C$1509,"Receita",'Finanças'!$D$10:$D$1509,$B57,'Finanças'!$B$10:$B$1509,">="&DATE(Ano,8,1),'Finanças'!$B$10:$B$1509,"<="&DATE(Ano,8+1,0))) | M57: =IF($B57="","",SUMIFS('Finanças'!$F$10:$F$1509,'Finanças'!$C$10:$C$1509,"Receita",'Finanças'!$D$10:$D$1509,$B57,'Finanças'!$B$10:$B$1509,">="&DATE(Ano,9,1),'Finanças'!$B$10:$B$1509,"<="&DATE(Ano,9+1,0))) | N57: =IF($B57="","",SUMIFS('Finanças'!$F$10:$F$1509,'Finanças'!$C$10:$C$1509,"Receita",'Finanças'!$D$10:$D$1509,$B57,'Finanças'!$B$10:$B$1509,">="&DATE(Ano,10,1),'Finanças'!$B$10:$B$1509,"<="&DATE(Ano,10+1,0))) | O57: =IF($B57="","",SUMIFS('Finanças'!$F$10:$F$1509,'Finanças'!$C$10:$C$1509,"Receita",'Finanças'!$D$10:$D$1509,$B57,'Finanças'!$B$10:$B$1509,">="&DATE(Ano,11,1),'Finanças'!$B$10:$B$1509,"<="&DATE(Ano,11+1,0))) | P57: =IF($B57="","",SUMIFS('Finanças'!$F$10:$F$1509,'Finanças'!$C$10:$C$1509,"Receita",'Finanças'!$D$10:$D$1509,$B57,'Finanças'!$B$10:$B$1509,">="&DATE(Ano,12,1),'Finanças'!$B$10:$B$1509,"<="&DATE(Ano,12+1,0))) | Q57: =IF(B57="","",SUM(E57:P57)) | R57: =IF(B57="","",SUMPRODUCT((COLUMN($E57:$P57)-COLUMN($E57)+1<=RefMes)*$E57:$P57)/RefMes) | S57: =IF(B57="","",INDEX(E57:P57,RefMes)) | T57: =IF(OR(B57="",N(D57)=0),"",S57/D57) | U57: =IF(T57="","",IF(T57>=1,"✔ Atingido","▲ "&ROUND(T57*100,0)&"%"))
B58: =IF('Config'!$K$16="","",'Config'!$K$16) | E58: =IF($B58="","",SUMIFS('Finanças'!$F$10:$F$1509,'Finanças'!$C$10:$C$1509,"Receita",'Finanças'!$D$10:$D$1509,$B58,'Finanças'!$B$10:$B$1509,">="&DATE(Ano,1,1),'Finanças'!$B$10:$B$1509,"<="&DATE(Ano,1+1,0))) | F58: =IF($B58="","",SUMIFS('Finanças'!$F$10:$F$1509,'Finanças'!$C$10:$C$1509,"Receita",'Finanças'!$D$10:$D$1509,$B58,'Finanças'!$B$10:$B$1509,">="&DATE(Ano,2,1),'Finanças'!$B$10:$B$1509,"<="&DATE(Ano,2+1,0))) | G58: =IF($B58="","",SUMIFS('Finanças'!$F$10:$F$1509,'Finanças'!$C$10:$C$1509,"Receita",'Finanças'!$D$10:$D$1509,$B58,'Finanças'!$B$10:$B$1509,">="&DATE(Ano,3,1),'Finanças'!$B$10:$B$1509,"<="&DATE(Ano,3+1,0))) | H58: =IF($B58="","",SUMIFS('Finanças'!$F$10:$F$1509,'Finanças'!$C$10:$C$1509,"Receita",'Finanças'!$D$10:$D$1509,$B58,'Finanças'!$B$10:$B$1509,">="&DATE(Ano,4,1),'Finanças'!$B$10:$B$1509,"<="&DATE(Ano,4+1,0))) | I58: =IF($B58="","",SUMIFS('Finanças'!$F$10:$F$1509,'Finanças'!$C$10:$C$1509,"Receita",'Finanças'!$D$10:$D$1509,$B58,'Finanças'!$B$10:$B$1509,">="&DATE(Ano,5,1),'Finanças'!$B$10:$B$1509,"<="&DATE(Ano,5+1,0))) | J58: =IF($B58="","",SUMIFS('Finanças'!$F$10:$F$1509,'Finanças'!$C$10:$C$1509,"Receita",'Finanças'!$D$10:$D$1509,$B58,'Finanças'!$B$10:$B$1509,">="&DATE(Ano,6,1),'Finanças'!$B$10:$B$1509,"<="&DATE(Ano,6+1,0))) | K58: =IF($B58="","",SUMIFS('Finanças'!$F$10:$F$1509,'Finanças'!$C$10:$C$1509,"Receita",'Finanças'!$D$10:$D$1509,$B58,'Finanças'!$B$10:$B$1509,">="&DATE(Ano,7,1),'Finanças'!$B$10:$B$1509,"<="&DATE(Ano,7+1,0))) | L58: =IF($B58="","",SUMIFS('Finanças'!$F$10:$F$1509,'Finanças'!$C$10:$C$1509,"Receita",'Finanças'!$D$10:$D$1509,$B58,'Finanças'!$B$10:$B$1509,">="&DATE(Ano,8,1),'Finanças'!$B$10:$B$1509,"<="&DATE(Ano,8+1,0))) | M58: =IF($B58="","",SUMIFS('Finanças'!$F$10:$F$1509,'Finanças'!$C$10:$C$1509,"Receita",'Finanças'!$D$10:$D$1509,$B58,'Finanças'!$B$10:$B$1509,">="&DATE(Ano,9,1),'Finanças'!$B$10:$B$1509,"<="&DATE(Ano,9+1,0))) | N58: =IF($B58="","",SUMIFS('Finanças'!$F$10:$F$1509,'Finanças'!$C$10:$C$1509,"Receita",'Finanças'!$D$10:$D$1509,$B58,'Finanças'!$B$10:$B$1509,">="&DATE(Ano,10,1),'Finanças'!$B$10:$B$1509,"<="&DATE(Ano,10+1,0))) | O58: =IF($B58="","",SUMIFS('Finanças'!$F$10:$F$1509,'Finanças'!$C$10:$C$1509,"Receita",'Finanças'!$D$10:$D$1509,$B58,'Finanças'!$B$10:$B$1509,">="&DATE(Ano,11,1),'Finanças'!$B$10:$B$1509,"<="&DATE(Ano,11+1,0))) | P58: =IF($B58="","",SUMIFS('Finanças'!$F$10:$F$1509,'Finanças'!$C$10:$C$1509,"Receita",'Finanças'!$D$10:$D$1509,$B58,'Finanças'!$B$10:$B$1509,">="&DATE(Ano,12,1),'Finanças'!$B$10:$B$1509,"<="&DATE(Ano,12+1,0))) | Q58: =IF(B58="","",SUM(E58:P58)) | R58: =IF(B58="","",SUMPRODUCT((COLUMN($E58:$P58)-COLUMN($E58)+1<=RefMes)*$E58:$P58)/RefMes) | S58: =IF(B58="","",INDEX(E58:P58,RefMes)) | T58: =IF(OR(B58="",N(D58)=0),"",S58/D58) | U58: =IF(T58="","",IF(T58>=1,"✔ Atingido","▲ "&ROUND(T58*100,0)&"%"))
B59: =IF('Config'!$K$17="","",'Config'!$K$17) | E59: =IF($B59="","",SUMIFS('Finanças'!$F$10:$F$1509,'Finanças'!$C$10:$C$1509,"Receita",'Finanças'!$D$10:$D$1509,$B59,'Finanças'!$B$10:$B$1509,">="&DATE(Ano,1,1),'Finanças'!$B$10:$B$1509,"<="&DATE(Ano,1+1,0))) | F59: =IF($B59="","",SUMIFS('Finanças'!$F$10:$F$1509,'Finanças'!$C$10:$C$1509,"Receita",'Finanças'!$D$10:$D$1509,$B59,'Finanças'!$B$10:$B$1509,">="&DATE(Ano,2,1),'Finanças'!$B$10:$B$1509,"<="&DATE(Ano,2+1,0))) | G59: =IF($B59="","",SUMIFS('Finanças'!$F$10:$F$1509,'Finanças'!$C$10:$C$1509,"Receita",'Finanças'!$D$10:$D$1509,$B59,'Finanças'!$B$10:$B$1509,">="&DATE(Ano,3,1),'Finanças'!$B$10:$B$1509,"<="&DATE(Ano,3+1,0))) | H59: =IF($B59="","",SUMIFS('Finanças'!$F$10:$F$1509,'Finanças'!$C$10:$C$1509,"Receita",'Finanças'!$D$10:$D$1509,$B59,'Finanças'!$B$10:$B$1509,">="&DATE(Ano,4,1),'Finanças'!$B$10:$B$1509,"<="&DATE(Ano,4+1,0))) | I59: =IF($B59="","",SUMIFS('Finanças'!$F$10:$F$1509,'Finanças'!$C$10:$C$1509,"Receita",'Finanças'!$D$10:$D$1509,$B59,'Finanças'!$B$10:$B$1509,">="&DATE(Ano,5,1),'Finanças'!$B$10:$B$1509,"<="&DATE(Ano,5+1,0))) | J59: =IF($B59="","",SUMIFS('Finanças'!$F$10:$F$1509,'Finanças'!$C$10:$C$1509,"Receita",'Finanças'!$D$10:$D$1509,$B59,'Finanças'!$B$10:$B$1509,">="&DATE(Ano,6,1),'Finanças'!$B$10:$B$1509,"<="&DATE(Ano,6+1,0))) | K59: =IF($B59="","",SUMIFS('Finanças'!$F$10:$F$1509,'Finanças'!$C$10:$C$1509,"Receita",'Finanças'!$D$10:$D$1509,$B59,'Finanças'!$B$10:$B$1509,">="&DATE(Ano,7,1),'Finanças'!$B$10:$B$1509,"<="&DATE(Ano,7+1,0))) | L59: =IF($B59="","",SUMIFS('Finanças'!$F$10:$F$1509,'Finanças'!$C$10:$C$1509,"Receita",'Finanças'!$D$10:$D$1509,$B59,'Finanças'!$B$10:$B$1509,">="&DATE(Ano,8,1),'Finanças'!$B$10:$B$1509,"<="&DATE(Ano,8+1,0))) | M59: =IF($B59="","",SUMIFS('Finanças'!$F$10:$F$1509,'Finanças'!$C$10:$C$1509,"Receita",'Finanças'!$D$10:$D$1509,$B59,'Finanças'!$B$10:$B$1509,">="&DATE(Ano,9,1),'Finanças'!$B$10:$B$1509,"<="&DATE(Ano,9+1,0))) | N59: =IF($B59="","",SUMIFS('Finanças'!$F$10:$F$1509,'Finanças'!$C$10:$C$1509,"Receita",'Finanças'!$D$10:$D$1509,$B59,'Finanças'!$B$10:$B$1509,">="&DATE(Ano,10,1),'Finanças'!$B$10:$B$1509,"<="&DATE(Ano,10+1,0))) | O59: =IF($B59="","",SUMIFS('Finanças'!$F$10:$F$1509,'Finanças'!$C$10:$C$1509,"Receita",'Finanças'!$D$10:$D$1509,$B59,'Finanças'!$B$10:$B$1509,">="&DATE(Ano,11,1),'Finanças'!$B$10:$B$1509,"<="&DATE(Ano,11+1,0))) | P59: =IF($B59="","",SUMIFS('Finanças'!$F$10:$F$1509,'Finanças'!$C$10:$C$1509,"Receita",'Finanças'!$D$10:$D$1509,$B59,'Finanças'!$B$10:$B$1509,">="&DATE(Ano,12,1),'Finanças'!$B$10:$B$1509,"<="&DATE(Ano,12+1,0))) | Q59: =IF(B59="","",SUM(E59:P59)) | R59: =IF(B59="","",SUMPRODUCT((COLUMN($E59:$P59)-COLUMN($E59)+1<=RefMes)*$E59:$P59)/RefMes) | S59: =IF(B59="","",INDEX(E59:P59,RefMes)) | T59: =IF(OR(B59="",N(D59)=0),"",S59/D59) | U59: =IF(T59="","",IF(T59>=1,"✔ Atingido","▲ "&ROUND(T59*100,0)&"%"))
B60: =IF('Config'!$K$18="","",'Config'!$K$18) | E60: =IF($B60="","",SUMIFS('Finanças'!$F$10:$F$1509,'Finanças'!$C$10:$C$1509,"Receita",'Finanças'!$D$10:$D$1509,$B60,'Finanças'!$B$10:$B$1509,">="&DATE(Ano,1,1),'Finanças'!$B$10:$B$1509,"<="&DATE(Ano,1+1,0))) | F60: =IF($B60="","",SUMIFS('Finanças'!$F$10:$F$1509,'Finanças'!$C$10:$C$1509,"Receita",'Finanças'!$D$10:$D$1509,$B60,'Finanças'!$B$10:$B$1509,">="&DATE(Ano,2,1),'Finanças'!$B$10:$B$1509,"<="&DATE(Ano,2+1,0))) | G60: =IF($B60="","",SUMIFS('Finanças'!$F$10:$F$1509,'Finanças'!$C$10:$C$1509,"Receita",'Finanças'!$D$10:$D$1509,$B60,'Finanças'!$B$10:$B$1509,">="&DATE(Ano,3,1),'Finanças'!$B$10:$B$1509,"<="&DATE(Ano,3+1,0))) | H60: =IF($B60="","",SUMIFS('Finanças'!$F$10:$F$1509,'Finanças'!$C$10:$C$1509,"Receita",'Finanças'!$D$10:$D$1509,$B60,'Finanças'!$B$10:$B$1509,">="&DATE(Ano,4,1),'Finanças'!$B$10:$B$1509,"<="&DATE(Ano,4+1,0))) | I60: =IF($B60="","",SUMIFS('Finanças'!$F$10:$F$1509,'Finanças'!$C$10:$C$1509,"Receita",'Finanças'!$D$10:$D$1509,$B60,'Finanças'!$B$10:$B$1509,">="&DATE(Ano,5,1),'Finanças'!$B$10:$B$1509,"<="&DATE(Ano,5+1,0))) | J60: =IF($B60="","",SUMIFS('Finanças'!$F$10:$F$1509,'Finanças'!$C$10:$C$1509,"Receita",'Finanças'!$D$10:$D$1509,$B60,'Finanças'!$B$10:$B$1509,">="&DATE(Ano,6,1),'Finanças'!$B$10:$B$1509,"<="&DATE(Ano,6+1,0))) | K60: =IF($B60="","",SUMIFS('Finanças'!$F$10:$F$1509,'Finanças'!$C$10:$C$1509,"Receita",'Finanças'!$D$10:$D$1509,$B60,'Finanças'!$B$10:$B$1509,">="&DATE(Ano,7,1),'Finanças'!$B$10:$B$1509,"<="&DATE(Ano,7+1,0))) | L60: =IF($B60="","",SUMIFS('Finanças'!$F$10:$F$1509,'Finanças'!$C$10:$C$1509,"Receita",'Finanças'!$D$10:$D$1509,$B60,'Finanças'!$B$10:$B$1509,">="&DATE(Ano,8,1),'Finanças'!$B$10:$B$1509,"<="&DATE(Ano,8+1,0))) | M60: =IF($B60="","",SUMIFS('Finanças'!$F$10:$F$1509,'Finanças'!$C$10:$C$1509,"Receita",'Finanças'!$D$10:$D$1509,$B60,'Finanças'!$B$10:$B$1509,">="&DATE(Ano,9,1),'Finanças'!$B$10:$B$1509,"<="&DATE(Ano,9+1,0))) | N60: =IF($B60="","",SUMIFS('Finanças'!$F$10:$F$1509,'Finanças'!$C$10:$C$1509,"Receita",'Finanças'!$D$10:$D$1509,$B60,'Finanças'!$B$10:$B$1509,">="&DATE(Ano,10,1),'Finanças'!$B$10:$B$1509,"<="&DATE(Ano,10+1,0))) | O60: =IF($B60="","",SUMIFS('Finanças'!$F$10:$F$1509,'Finanças'!$C$10:$C$1509,"Receita",'Finanças'!$D$10:$D$1509,$B60,'Finanças'!$B$10:$B$1509,">="&DATE(Ano,11,1),'Finanças'!$B$10:$B$1509,"<="&DATE(Ano,11+1,0))) | P60: =IF($B60="","",SUMIFS('Finanças'!$F$10:$F$1509,'Finanças'!$C$10:$C$1509,"Receita",'Finanças'!$D$10:$D$1509,$B60,'Finanças'!$B$10:$B$1509,">="&DATE(Ano,12,1),'Finanças'!$B$10:$B$1509,"<="&DATE(Ano,12+1,0))) | Q60: =IF(B60="","",SUM(E60:P60)) | R60: =IF(B60="","",SUMPRODUCT((COLUMN($E60:$P60)-COLUMN($E60)+1<=RefMes)*$E60:$P60)/RefMes) | S60: =IF(B60="","",INDEX(E60:P60,RefMes)) | T60: =IF(OR(B60="",N(D60)=0),"",S60/D60) | U60: =IF(T60="","",IF(T60>=1,"✔ Atingido","▲ "&ROUND(T60*100,0)&"%"))
B61: =IF('Config'!$K$19="","",'Config'!$K$19) | E61: =IF($B61="","",SUMIFS('Finanças'!$F$10:$F$1509,'Finanças'!$C$10:$C$1509,"Receita",'Finanças'!$D$10:$D$1509,$B61,'Finanças'!$B$10:$B$1509,">="&DATE(Ano,1,1),'Finanças'!$B$10:$B$1509,"<="&DATE(Ano,1+1,0))) | F61: =IF($B61="","",SUMIFS('Finanças'!$F$10:$F$1509,'Finanças'!$C$10:$C$1509,"Receita",'Finanças'!$D$10:$D$1509,$B61,'Finanças'!$B$10:$B$1509,">="&DATE(Ano,2,1),'Finanças'!$B$10:$B$1509,"<="&DATE(Ano,2+1,0))) | G61: =IF($B61="","",SUMIFS('Finanças'!$F$10:$F$1509,'Finanças'!$C$10:$C$1509,"Receita",'Finanças'!$D$10:$D$1509,$B61,'Finanças'!$B$10:$B$1509,">="&DATE(Ano,3,1),'Finanças'!$B$10:$B$1509,"<="&DATE(Ano,3+1,0))) | H61: =IF($B61="","",SUMIFS('Finanças'!$F$10:$F$1509,'Finanças'!$C$10:$C$1509,"Receita",'Finanças'!$D$10:$D$1509,$B61,'Finanças'!$B$10:$B$1509,">="&DATE(Ano,4,1),'Finanças'!$B$10:$B$1509,"<="&DATE(Ano,4+1,0))) | I61: =IF($B61="","",SUMIFS('Finanças'!$F$10:$F$1509,'Finanças'!$C$10:$C$1509,"Receita",'Finanças'!$D$10:$D$1509,$B61,'Finanças'!$B$10:$B$1509,">="&DATE(Ano,5,1),'Finanças'!$B$10:$B$1509,"<="&DATE(Ano,5+1,0))) | J61: =IF($B61="","",SUMIFS('Finanças'!$F$10:$F$1509,'Finanças'!$C$10:$C$1509,"Receita",'Finanças'!$D$10:$D$1509,$B61,'Finanças'!$B$10:$B$1509,">="&DATE(Ano,6,1),'Finanças'!$B$10:$B$1509,"<="&DATE(Ano,6+1,0))) | K61: =IF($B61="","",SUMIFS('Finanças'!$F$10:$F$1509,'Finanças'!$C$10:$C$1509,"Receita",'Finanças'!$D$10:$D$1509,$B61,'Finanças'!$B$10:$B$1509,">="&DATE(Ano,7,1),'Finanças'!$B$10:$B$1509,"<="&DATE(Ano,7+1,0))) | L61: =IF($B61="","",SUMIFS('Finanças'!$F$10:$F$1509,'Finanças'!$C$10:$C$1509,"Receita",'Finanças'!$D$10:$D$1509,$B61,'Finanças'!$B$10:$B$1509,">="&DATE(Ano,8,1),'Finanças'!$B$10:$B$1509,"<="&DATE(Ano,8+1,0))) | M61: =IF($B61="","",SUMIFS('Finanças'!$F$10:$F$1509,'Finanças'!$C$10:$C$1509,"Receita",'Finanças'!$D$10:$D$1509,$B61,'Finanças'!$B$10:$B$1509,">="&DATE(Ano,9,1),'Finanças'!$B$10:$B$1509,"<="&DATE(Ano,9+1,0))) | N61: =IF($B61="","",SUMIFS('Finanças'!$F$10:$F$1509,'Finanças'!$C$10:$C$1509,"Receita",'Finanças'!$D$10:$D$1509,$B61,'Finanças'!$B$10:$B$1509,">="&DATE(Ano,10,1),'Finanças'!$B$10:$B$1509,"<="&DATE(Ano,10+1,0))) | O61: =IF($B61="","",SUMIFS('Finanças'!$F$10:$F$1509,'Finanças'!$C$10:$C$1509,"Receita",'Finanças'!$D$10:$D$1509,$B61,'Finanças'!$B$10:$B$1509,">="&DATE(Ano,11,1),'Finanças'!$B$10:$B$1509,"<="&DATE(Ano,11+1,0))) | P61: =IF($B61="","",SUMIFS('Finanças'!$F$10:$F$1509,'Finanças'!$C$10:$C$1509,"Receita",'Finanças'!$D$10:$D$1509,$B61,'Finanças'!$B$10:$B$1509,">="&DATE(Ano,12,1),'Finanças'!$B$10:$B$1509,"<="&DATE(Ano,12+1,0))) | Q61: =IF(B61="","",SUM(E61:P61)) | R61: =IF(B61="","",SUMPRODUCT((COLUMN($E61:$P61)-COLUMN($E61)+1<=RefMes)*$E61:$P61)/RefMes) | S61: =IF(B61="","",INDEX(E61:P61,RefMes)) | T61: =IF(OR(B61="",N(D61)=0),"",S61/D61) | U61: =IF(T61="","",IF(T61>=1,"✔ Atingido","▲ "&ROUND(T61*100,0)&"%"))
